Workbook

Sheet Summary
A1: RENTAL INCOME — UNIT SUMMARY
A2: Balances update automatically from each unit ledger. Red = arrears, Green = paid/credit.
A3: Unit | B3: Tenant | C3: Rent | D3: Garbage | E3: Deposit Held | F3: Current Balance | G3: Months Out. | H3: Status | I3: Priority
A4: C1 | B4: ='C1'!J3 | C4: ='C1'!D3 | D4: ='C1'!F3 | E4: ='C1'!L3 | F4: ='C1'!H3 | G4: =IF(C4+D4=0,0,MAX(0,F4)/(C4+D4)) | H4: =IF(F4<=0,"Paid / Credit",IF(G4<1,"<1 month",IF(G4<2,"1–2 months",IF(G4<3,"2–3 months",">3 months")))) | I4: =IF(F4<=0,"PAID",IF(G4<1,"LOW",IF(G4<2,"MEDIUM","HIGH")))
A5: B3 | B5: ='B3'!J3 | C5: ='B3'!D3 | D5: ='B3'!F3 | E5: ='B3'!L3 | F5: ='B3'!H3 | G5: =IF(C5+D5=0,0,MAX(0,F5)/(C5+D5)) | H5: =IF(F5<=0,"Paid / Credit",IF(G5<1,"<1 month",IF(G5<2,"1–2 months",IF(G5<3,"2–3 months",">3 months")))) | I5: =IF(F5<=0,"PAID",IF(G5<1,"LOW",IF(G5<2,"MEDIUM","HIGH")))
A6: A7 | B6: ='A7'!J3 | C6: ='A7'!D3 | D6: ='A7'!F3 | E6: ='A7'!L3 | F6: ='A7'!H3 | G6: =IF(C6+D6=0,0,MAX(0,F6)/(C6+D6)) | H6: =IF(F6<=0,"Paid / Credit",IF(G6<1,"<1 month",IF(G6<2,"1–2 months",IF(G6<3,"2–3 months",">3 months")))) | I6: =IF(F6<=0,"PAID",IF(G6<1,"LOW",IF(G6<2,"MEDIUM","HIGH")))
A7: A6 | B7: ='A6'!J3 | C7: ='A6'!D3 | D7: ='A6'!F3 | E7: ='A6'!L3 | F7: ='A6'!H3 | G7: =IF(C7+D7=0,0,MAX(0,F7)/(C7+D7)) | H7: =IF(F7<=0,"Paid / Credit",IF(G7<1,"<1 month",IF(G7<2,"1–2 months",IF(G7<3,"2–3 months",">3 months")))) | I7: =IF(F7<=0,"PAID",IF(G7<1,"LOW",IF(G7<2,"MEDIUM","HIGH")))
A8: C3 | B8: ='C3'!J3 | C8: ='C3'!D3 | D8: ='C3'!F3 | E8: ='C3'!L3 | F8: ='C3'!H3 | G8: =IF(C8+D8=0,0,MAX(0,F8)/(C8+D8)) | H8: =IF(F8<=0,"Paid / Credit",IF(G8<1,"<1 month",IF(G8<2,"1–2 months",IF(G8<3,"2–3 months",">3 months")))) | I8: =IF(F8<=0,"PAID",IF(G8<1,"LOW",IF(G8<2,"MEDIUM","HIGH")))
A9: A1 | B9: ='A1'!J3 | C9: ='A1'!D3 | D9: ='A1'!F3 | E9: ='A1'!L3 | F9: ='A1'!H3 | G9: =IF(C9+D9=0,0,MAX(0,F9)/(C9+D9)) | H9: =IF(F9<=0,"Paid / Credit",IF(G9<1,"<1 month",IF(G9<2,"1–2 months",IF(G9<3,"2–3 months",">3 months")))) | I9: =IF(F9<=0,"PAID",IF(G9<1,"LOW",IF(G9<2,"MEDIUM","HIGH")))
A10: B1 | B10: ='B1'!J3 | C10: ='B1'!D3 | D10: ='B1'!F3 | E10: ='B1'!L3 | F10: ='B1'!H3 | G10: =IF(C10+D10=0,0,MAX(0,F10)/(C10+D10)) | H10: =IF(F10<=0,"Paid / Credit",IF(G10<1,"<1 month",IF(G10<2,"1–2 months",IF(G10<3,"2–3 months",">3 months")))) | I10: =IF(F10<=0,"PAID",IF(G10<1,"LOW",IF(G10<2,"MEDIUM","HIGH")))
A11: C2 | B11: ='C2'!J3 | C11: ='C2'!D3 | D11: ='C2'!F3 | E11: ='C2'!L3 | F11: ='C2'!H3 | G11: =IF(C11+D11=0,0,MAX(0,F11)/(C11+D11)) | H11: =IF(F11<=0,"Paid / Credit",IF(G11<1,"<1 month",IF(G11<2,"1–2 months",IF(G11<3,"2–3 months",">3 months")))) | I11: =IF(F11<=0,"PAID",IF(G11<1,"LOW",IF(G11<2,"MEDIUM","HIGH")))
A12: A2 | B12: ='A2'!J3 | C12: ='A2'!D3 | D12: ='A2'!F3 | E12: ='A2'!L3 | F12: ='A2'!H3 | G12: =IF(C12+D12=0,0,MAX(0,F12)/(C12+D12)) | H12: =IF(F12<=0,"Paid / Credit",IF(G12<1,"<1 month",IF(G12<2,"1–2 months",IF(G12<3,"2–3 months",">3 months")))) | I12: =IF(F12<=0,"PAID",IF(G12<1,"LOW",IF(G12<2,"MEDIUM","HIGH")))
A13: A3 | B13: ='A3'!J3 | C13: ='A3'!D3 | D13: ='A3'!F3 | E13: ='A3'!L3 | F13: ='A3'!H3 | G13: =IF(C13+D13=0,0,MAX(0,F13)/(C13+D13)) | H13: =IF(F13<=0,"Paid / Credit",IF(G13<1,"<1 month",IF(G13<2,"1–2 months",IF(G13<3,"2–3 months",">3 months")))) | I13: =IF(F13<=0,"PAID",IF(G13<1,"LOW",IF(G13<2,"MEDIUM","HIGH")))
A14: A4 | B14: ='A4'!J3 | C14: ='A4'!D3 | D14: ='A4'!F3 | E14: ='A4'!L3 | F14: ='A4'!H3 | G14: =IF(C14+D14=0,0,MAX(0,F14)/(C14+D14)) | H14: =IF(F14<=0,"Paid / Credit",IF(G14<1,"<1 month",IF(G14<2,"1–2 months",IF(G14<3,"2–3 months",">3 months")))) | I14: =IF(F14<=0,"PAID",IF(G14<1,"LOW",IF(G14<2,"MEDIUM","HIGH")))
A15: A5 | B15: ='A5'!J3 | C15: ='A5'!D3 | D15: ='A5'!F3 | E15: ='A5'!L3 | F15: ='A5'!H3 | G15: =IF(C15+D15=0,0,MAX(0,F15)/(C15+D15)) | H15: =IF(F15<=0,"Paid / Credit",IF(G15<1,"<1 month",IF(G15<2,"1–2 months",IF(G15<3,"2–3 months",">3 months")))) | I15: =IF(F15<=0,"PAID",IF(G15<1,"LOW",IF(G15<2,"MEDIUM","HIGH")))
A16: B2 | B16: ='B2'!J3 | C16: ='B2'!D3 | D16: ='B2'!F3 | E16: ='B2'!L3 | F16: ='B2'!H3 | G16: =IF(C16+D16=0,0,MAX(0,F16)/(C16+D16)) | H16: =IF(F16<=0,"Paid / Credit",IF(G16<1,"<1 month",IF(G16<2,"1–2 months",IF(G16<3,"2–3 months",">3 months")))) | I16: =IF(F16<=0,"PAID",IF(G16<1,"LOW",IF(G16<2,"MEDIUM","HIGH")))
A17: Shop 1 | B17: ='Shop 1'!J3 | C17: ='Shop 1'!D3 | D17: ='Shop 1'!F3 | E17: ='Shop 1'!L3 | F17: ='Shop 1'!H3 | G17: =IF(C17+D17=0,0,MAX(0,F17)/(C17+D17)) | H17: =IF(F17<=0,"Paid / Credit",IF(G17<1,"<1 month",IF(G17<2,"1–2 months",IF(G17<3,"2–3 months",">3 months")))) | I17: =IF(F17<=0,"PAID",IF(G17<1,"LOW",IF(G17<2,"MEDIUM","HIGH")))
A18: Shop 2 | B18: ='Shop 2'!J3 | C18: ='Shop 2'!D3 | D18: ='Shop 2'!F3 | E18: 5000 | F18: ='Shop 2'!H3 | G18: =IF(C18+D18=0,0,MAX(0,F18)/(C18+D18)) | H18: =IF(F18<=0,"Paid / Credit",IF(G18<1,"<1 month",IF(G18<2,"1–2 months",IF(G18<3,"2–3 months",">3 months")))) | I18: =IF(F18<=0,"PAID",IF(G18<1,"LOW",IF(G18<2,"MEDIUM","HIGH")))
A21: UNIT STATUS — all units
A22: Every unit is listed. Priority and suggested action update automatically. Click any column header arrow in the table below to Sort or Filter (e.g. Balance).
A23: Unit | B23: Tenant | C23: Balance | D23: Months | E23: Priority | F23: Suggested Action
A24: =A4 | B24: =B4 | C24: =F4 | D24: =G4 | E24: =IF(F4<=0,"PAID",IF(G4<1,"LOW",IF(G4<2,"MEDIUM","HIGH"))) | F24: =IF(F4<=0,"NO ACTION NEEDED",IF(G4<1,"MONITOR",IF(G4<2,"FOLLOW UP","URGENT")))
A25: =A5 | B25: =B5 | C25: =F5 | D25: =G5 | E25: =IF(F5<=0,"PAID",IF(G5<1,"LOW",IF(G5<2,"MEDIUM","HIGH"))) | F25: =IF(F5<=0,"NO ACTION NEEDED",IF(G5<1,"MONITOR",IF(G5<2,"FOLLOW UP","URGENT")))
A26: =A6 | B26: =B6 | C26: =F6 | D26: =G6 | E26: =IF(F6<=0,"PAID",IF(G6<1,"LOW",IF(G6<2,"MEDIUM","HIGH"))) | F26: =IF(F6<=0,"NO ACTION NEEDED",IF(G6<1,"MONITOR",IF(G6<2,"FOLLOW UP","URGENT")))
A27: =A7 | B27: =B7 | C27: =F7 | D27: =G7 | E27: =IF(F7<=0,"PAID",IF(G7<1,"LOW",IF(G7<2,"MEDIUM","HIGH"))) | F27: =IF(F7<=0,"NO ACTION NEEDED",IF(G7<1,"MONITOR",IF(G7<2,"FOLLOW UP","URGENT")))
A28: =A8 | B28: =B8 | C28: =F8 | D28: =G8 | E28: =IF(F8<=0,"PAID",IF(G8<1,"LOW",IF(G8<2,"MEDIUM","HIGH"))) | F28: =IF(F8<=0,"NO ACTION NEEDED",IF(G8<1,"MONITOR",IF(G8<2,"FOLLOW UP","URGENT")))
A29: =A9 | B29: =B9 | C29: =F9 | D29: =G9 | E29: =IF(F9<=0,"PAID",IF(G9<1,"LOW",IF(G9<2,"MEDIUM","HIGH"))) | F29: =IF(F9<=0,"NO ACTION NEEDED",IF(G9<1,"MONITOR",IF(G9<2,"FOLLOW UP","URGENT")))
A30: =A10 | B30: =B10 | C30: =F10 | D30: =G10 | E30: =IF(F10<=0,"PAID",IF(G10<1,"LOW",IF(G10<2,"MEDIUM","HIGH"))) | F30: =IF(F10<=0,"NO ACTION NEEDED",IF(G10<1,"MONITOR",IF(G10<2,"FOLLOW UP","URGENT")))
A31: =A11 | B31: =B11 | C31: =F11 | D31: =G11 | E31: =IF(F11<=0,"PAID",IF(G11<1,"LOW",IF(G11<2,"MEDIUM","HIGH"))) | F31: =IF(F11<=0,"NO ACTION NEEDED",IF(G11<1,"MONITOR",IF(G11<2,"FOLLOW UP","URGENT")))
A32: =A12 | B32: =B12 | C32: =F12 | D32: =G12 | E32: =IF(F12<=0,"PAID",IF(G12<1,"LOW",IF(G12<2,"MEDIUM","HIGH"))) | F32: =IF(F12<=0,"NO ACTION NEEDED",IF(G12<1,"MONITOR",IF(G12<2,"FOLLOW UP","URGENT")))
A33: =A13 | B33: =B13 | C33: =F13 | D33: =G13 | E33: =IF(F13<=0,"PAID",IF(G13<1,"LOW",IF(G13<2,"MEDIUM","HIGH"))) | F33: =IF(F13<=0,"NO ACTION NEEDED",IF(G13<1,"MONITOR",IF(G13<2,"FOLLOW UP","URGENT")))
A34: =A14 | B34: =B14 | C34: =F14 | D34: =G14 | E34: =IF(F14<=0,"PAID",IF(G14<1,"LOW",IF(G14<2,"MEDIUM","HIGH"))) | F34: =IF(F14<=0,"NO ACTION NEEDED",IF(G14<1,"MONITOR",IF(G14<2,"FOLLOW UP","URGENT")))
A35: =A15 | B35: =B15 | C35: =F15 | D35: =G15 | E35: =IF(F15<=0,"PAID",IF(G15<1,"LOW",IF(G15<2,"MEDIUM","HIGH"))) | F35: =IF(F15<=0,"NO ACTION NEEDED",IF(G15<1,"MONITOR",IF(G15<2,"FOLLOW UP","URGENT")))
... A38: =A18 | B38: =B18 | C38: =F18 | D38: =G18 | E38: =IF(F18<=0,"PAID",IF(G18<1,"LOW",IF(G18<2,"MEDIUM","HIGH"))) | F38: =IF(F18<=0,"NO ACTION NEEDED",IF(G18<1,"MONITOR",IF(G18<2,"FOLLOW UP","URGENT")))

Sheet Statement
A1: TENANT STATEMENT
A2: Select a unit in cell B3. The statement below updates automatically. Print this sheet (or export to PDF) to share with the tenant.
A3: Select Unit: | B3: A1 | C3: ← Change this to generate another tenant's statement
A5: Unit | B5: =B3
A6: Tenant | B6: =IFERROR(INDEX(Summary!B4:B18,MATCH(B3,Summary!A4:A18,0)),"")
A7: Monthly Rent | B7: =IFERROR(INDEX(Summary!C4:C18,MATCH(B3,Summary!A4:A18,0)),0)
A8: Garbage Fee | B8: =IFERROR(INDEX(Summary!D4:D18,MATCH(B3,Summary!A4:A18,0)),0)
A9: Current Balance | B9: =IFERROR(INDEX(Summary!E4:E18,MATCH(B3,Summary!A4:A18,0)),0)
A10: Deposit Held | B10: =IFERROR(INDEX(Summary!E4:E18,MATCH(B3,Summary!A4:A18,0)),0)
A11: TRANSACTION HISTORY
A12: Date | B12: Month | C12: Description | D12: Rent Charged | E12: Garbage | F12: Payment Received | G12: Running Balance
A13: =IF(INDIRECT("'"&$B$3&"'!A6")="","",INDIRECT("'"&$B$3&"'!A6")) | B13: =IF(INDIRECT("'"&$B$3&"'!B6")="","",INDIRECT("'"&$B$3&"'!B6")) | C13: =IF(INDIRECT("'"&$B$3&"'!C6")="","",INDIRECT("'"&$B$3&"'!C6")) | D13: =IF(INDIRECT("'"&$B$3&"'!E6")="","",INDIRECT("'"&$B$3&"'!E6")) | E13: =IF(INDIRECT("'"&$B$3&"'!F6")="","",INDIRECT("'"&$B$3&"'!F6")) | F13: =IF(INDIRECT("'"&$B$3&"'!G6")="","",INDIRECT("'"&$B$3&"'!G6")) | G13: =IF(INDIRECT("'"&$B$3&"'!I6")="","",INDIRECT("'"&$B$3&"'!I6"))
A14: =IF(INDIRECT("'"&$B$3&"'!A7")="","",INDIRECT("'"&$B$3&"'!A7")) | B14: =IF(INDIRECT("'"&$B$3&"'!B7")="","",INDIRECT("'"&$B$3&"'!B7")) | C14: =IF(INDIRECT("'"&$B$3&"'!C7")="","",INDIRECT("'"&$B$3&"'!C7")) | D14: =IF(INDIRECT("'"&$B$3&"'!E7")="","",INDIRECT("'"&$B$3&"'!E7")) | E14: =IF(INDIRECT("'"&$B$3&"'!F7")="","",INDIRECT("'"&$B$3&"'!F7")) | F14: =IF(INDIRECT("'"&$B$3&"'!G7")="","",INDIRECT("'"&$B$3&"'!G7")) | G14: =IF(INDIRECT("'"&$B$3&"'!I7")="","",INDIRECT("'"&$B$3&"'!I7"))
A15: =IF(INDIRECT("'"&$B$3&"'!A8")="","",INDIRECT("'"&$B$3&"'!A8")) | B15: =IF(INDIRECT("'"&$B$3&"'!B8")="","",INDIRECT("'"&$B$3&"'!B8")) | C15: =IF(INDIRECT("'"&$B$3&"'!C8")="","",INDIRECT("'"&$B$3&"'!C8")) | D15: =IF(INDIRECT("'"&$B$3&"'!E8")="","",INDIRECT("'"&$B$3&"'!E8")) | E15: =IF(INDIRECT("'"&$B$3&"'!F8")="","",INDIRECT("'"&$B$3&"'!F8")) | F15: =IF(INDIRECT("'"&$B$3&"'!G8")="","",INDIRECT("'"&$B$3&"'!G8")) | G15: =IF(INDIRECT("'"&$B$3&"'!I8")="","",INDIRECT("'"&$B$3&"'!I8"))
A16: =IF(INDIRECT("'"&$B$3&"'!A9")="","",INDIRECT("'"&$B$3&"'!A9")) | B16: =IF(INDIRECT("'"&$B$3&"'!B9")="","",INDIRECT("'"&$B$3&"'!B9")) | C16: =IF(INDIRECT("'"&$B$3&"'!C9")="","",INDIRECT("'"&$B$3&"'!C9")) | D16: =IF(INDIRECT("'"&$B$3&"'!E9")="","",INDIRECT("'"&$B$3&"'!E9")) | E16: =IF(INDIRECT("'"&$B$3&"'!F9")="","",INDIRECT("'"&$B$3&"'!F9")) | F16: =IF(INDIRECT("'"&$B$3&"'!G9")="","",INDIRECT("'"&$B$3&"'!G9")) | G16: =IF(INDIRECT("'"&$B$3&"'!I9")="","",INDIRECT("'"&$B$3&"'!I9"))
A17: =IF(INDIRECT("'"&$B$3&"'!A10")="","",INDIRECT("'"&$B$3&"'!A10")) | B17: =IF(INDIRECT("'"&$B$3&"'!B10")="","",INDIRECT("'"&$B$3&"'!B10")) | C17: =IF(INDIRECT("'"&$B$3&"'!C10")="","",INDIRECT("'"&$B$3&"'!C10")) | D17: =IF(INDIRECT("'"&$B$3&"'!E10")="","",INDIRECT("'"&$B$3&"'!E10")) | E17: =IF(INDIRECT("'"&$B$3&"'!F10")="","",INDIRECT("'"&$B$3&"'!F10")) | F17: =IF(INDIRECT("'"&$B$3&"'!G10")="","",INDIRECT("'"&$B$3&"'!G10")) | G17: =IF(INDIRECT("'"&$B$3&"'!I10")="","",INDIRECT("'"&$B$3&"'!I10"))
A18: =IF(INDIRECT("'"&$B$3&"'!A11")="","",INDIRECT("'"&$B$3&"'!A11")) | B18: =IF(INDIRECT("'"&$B$3&"'!B11")="","",INDIRECT("'"&$B$3&"'!B11")) | C18: =IF(INDIRECT("'"&$B$3&"'!C11")="","",INDIRECT("'"&$B$3&"'!C11")) | D18: =IF(INDIRECT("'"&$B$3&"'!E11")="","",INDIRECT("'"&$B$3&"'!E11")) | E18: =IF(INDIRECT("'"&$B$3&"'!F11")="","",INDIRECT("'"&$B$3&"'!F11")) | F18: =IF(INDIRECT("'"&$B$3&"'!G11")="","",INDIRECT("'"&$B$3&"'!G11")) | G18: =IF(INDIRECT("'"&$B$3&"'!I11")="","",INDIRECT("'"&$B$3&"'!I11"))
A19: =IF(INDIRECT("'"&$B$3&"'!A12")="","",INDIRECT("'"&$B$3&"'!A12")) | B19: =IF(INDIRECT("'"&$B$3&"'!B12")="","",INDIRECT("'"&$B$3&"'!B12")) | C19: =IF(INDIRECT("'"&$B$3&"'!C12")="","",INDIRECT("'"&$B$3&"'!C12")) | D19: =IF(INDIRECT("'"&$B$3&"'!E12")="","",INDIRECT("'"&$B$3&"'!E12")) | E19: =IF(INDIRECT("'"&$B$3&"'!F12")="","",INDIRECT("'"&$B$3&"'!F12")) | F19: =IF(INDIRECT("'"&$B$3&"'!G12")="","",INDIRECT("'"&$B$3&"'!G12")) | G19: =IF(INDIRECT("'"&$B$3&"'!I12")="","",INDIRECT("'"&$B$3&"'!I12"))
A20: =IF(INDIRECT("'"&$B$3&"'!A13")="","",INDIRECT("'"&$B$3&"'!A13")) | B20: =IF(INDIRECT("'"&$B$3&"'!B13")="","",INDIRECT("'"&$B$3&"'!B13")) | C20: =IF(INDIRECT("'"&$B$3&"'!C13")="","",INDIRECT("'"&$B$3&"'!C13")) | D20: =IF(INDIRECT("'"&$B$3&"'!E13")="","",INDIRECT("'"&$B$3&"'!E13")) | E20: =IF(INDIRECT("'"&$B$3&"'!F13")="","",INDIRECT("'"&$B$3&"'!F13")) | F20: =IF(INDIRECT("'"&$B$3&"'!G13")="","",INDIRECT("'"&$B$3&"'!G13")) | G20: =IF(INDIRECT("'"&$B$3&"'!I13")="","",INDIRECT("'"&$B$3&"'!I13"))
A21: =IF(INDIRECT("'"&$B$3&"'!A14")="","",INDIRECT("'"&$B$3&"'!A14")) | B21: =IF(INDIRECT("'"&$B$3&"'!B14")="","",INDIRECT("'"&$B$3&"'!B14")) | C21: =IF(INDIRECT("'"&$B$3&"'!C14")="","",INDIRECT("'"&$B$3&"'!C14")) | D21: =IF(INDIRECT("'"&$B$3&"'!E14")="","",INDIRECT("'"&$B$3&"'!E14")) | E21: =IF(INDIRECT("'"&$B$3&"'!F14")="","",INDIRECT("'"&$B$3&"'!F14")) | F21: =IF(INDIRECT("'"&$B$3&"'!G14")="","",INDIRECT("'"&$B$3&"'!G14")) | G21: =IF(INDIRECT("'"&$B$3&"'!I14")="","",INDIRECT("'"&$B$3&"'!I14"))
A22: =IF(INDIRECT("'"&$B$3&"'!A15")="","",INDIRECT("'"&$B$3&"'!A15")) | B22: =IF(INDIRECT("'"&$B$3&"'!B15")="","",INDIRECT("'"&$B$3&"'!B15")) | C22: =IF(INDIRECT("'"&$B$3&"'!C15")="","",INDIRECT("'"&$B$3&"'!C15")) | D22: =IF(INDIRECT("'"&$B$3&"'!E15")="","",INDIRECT("'"&$B$3&"'!E15")) | E22: =IF(INDIRECT("'"&$B$3&"'!F15")="","",INDIRECT("'"&$B$3&"'!F15")) | F22: =IF(INDIRECT("'"&$B$3&"'!G15")="","",INDIRECT("'"&$B$3&"'!G15")) | G22: =IF(INDIRECT("'"&$B$3&"'!I15")="","",INDIRECT("'"&$B$3&"'!I15"))
A23: =IF(INDIRECT("'"&$B$3&"'!A16")="","",INDIRECT("'"&$B$3&"'!A16")) | B23: =IF(INDIRECT("'"&$B$3&"'!B16")="","",INDIRECT("'"&$B$3&"'!B16")) | C23: =IF(INDIRECT("'"&$B$3&"'!C16")="","",INDIRECT("'"&$B$3&"'!C16")) | D23: =IF(INDIRECT("'"&$B$3&"'!E16")="","",INDIRECT("'"&$B$3&"'!E16")) | E23: =IF(INDIRECT("'"&$B$3&"'!F16")="","",INDIRECT("'"&$B$3&"'!F16")) | F23: =IF(INDIRECT("'"&$B$3&"'!G16")="","",INDIRECT("'"&$B$3&"'!G16")) | G23: =IF(INDIRECT("'"&$B$3&"'!I16")="","",INDIRECT("'"&$B$3&"'!I16"))
A24: =IF(INDIRECT("'"&$B$3&"'!A17")="","",INDIRECT("'"&$B$3&"'!A17")) | B24: =IF(INDIRECT("'"&$B$3&"'!B17")="","",INDIRECT("'"&$B$3&"'!B17")) | C24: =IF(INDIRECT("'"&$B$3&"'!C17")="","",INDIRECT("'"&$B$3&"'!C17")) | D24: =IF(INDIRECT("'"&$B$3&"'!E17")="","",INDIRECT("'"&$B$3&"'!E17")) | E24: =IF(INDIRECT("'"&$B$3&"'!F17")="","",INDIRECT("'"&$B$3&"'!F17")) | F24: =IF(INDIRECT("'"&$B$3&"'!G17")="","",INDIRECT("'"&$B$3&"'!G17")) | G24: =IF(INDIRECT("'"&$B$3&"'!I17")="","",INDIRECT("'"&$B$3&"'!I17"))
A25: =IF(INDIRECT("'"&$B$3&"'!A18")="","",INDIRECT("'"&$B$3&"'!A18")) | B25: =IF(INDIRECT("'"&$B$3&"'!B18")="","",INDIRECT("'"&$B$3&"'!B18")) | C25: =IF(INDIRECT("'"&$B$3&"'!C18")="","",INDIRECT("'"&$B$3&"'!C18")) | D25: =IF(INDIRECT("'"&$B$3&"'!E18")="","",INDIRECT("'"&$B$3&"'!E18")) | E25: =IF(INDIRECT("'"&$B$3&"'!F18")="","",INDIRECT("'"&$B$3&"'!F18")) | F25: =IF(INDIRECT("'"&$B$3&"'!G18")="","",INDIRECT("'"&$B$3&"'!G18")) | G25: =IF(INDIRECT("'"&$B$3&"'!I18")="","",INDIRECT("'"&$B$3&"'!I18"))
A26: =IF(INDIRECT("'"&$B$3&"'!A19")="","",INDIRECT("'"&$B$3&"'!A19")) | B26: =IF(INDIRECT("'"&$B$3&"'!B19")="","",INDIRECT("'"&$B$3&"'!B19")) | C26: =IF(INDIRECT("'"&$B$3&"'!C19")="","",INDIRECT("'"&$B$3&"'!C19")) | D26: =IF(INDIRECT("'"&$B$3&"'!E19")="","",INDIRECT("'"&$B$3&"'!E19")) | E26: =IF(INDIRECT("'"&$B$3&"'!F19")="","",INDIRECT("'"&$B$3&"'!F19")) | F26: =IF(INDIRECT("'"&$B$3&"'!G19")="","",INDIRECT("'"&$B$3&"'!G19")) | G26: =IF(INDIRECT("'"&$B$3&"'!I19")="","",INDIRECT("'"&$B$3&"'!I19"))
A27: =IF(INDIRECT("'"&$B$3&"'!A20")="","",INDIRECT("'"&$B$3&"'!A20")) | B27: =IF(INDIRECT("'"&$B$3&"'!B20")="","",INDIRECT("'"&$B$3&"'!B20")) | C27: =IF(INDIRECT("'"&$B$3&"'!C20")="","",INDIRECT("'"&$B$3&"'!C20")) | D27: =IF(INDIRECT("'"&$B$3&"'!E20")="","",INDIRECT("'"&$B$3&"'!E20")) | E27: =IF(INDIRECT("'"&$B$3&"'!F20")="","",INDIRECT("'"&$B$3&"'!F20")) | F27: =IF(INDIRECT("'"&$B$3&"'!G20")="","",INDIRECT("'"&$B$3&"'!G20")) | G27: =IF(INDIRECT("'"&$B$3&"'!I20")="","",INDIRECT("'"&$B$3&"'!I20"))
A28: =IF(INDIRECT("'"&$B$3&"'!A21")="","",INDIRECT("'"&$B$3&"'!A21")) | B28: =IF(INDIRECT("'"&$B$3&"'!B21")="","",INDIRECT("'"&$B$3&"'!B21")) | C28: =IF(INDIRECT("'"&$B$3&"'!C21")="","",INDIRECT("'"&$B$3&"'!C21")) | D28: =IF(INDIRECT("'"&$B$3&"'!E21")="","",INDIRECT("'"&$B$3&"'!E21")) | E28: =IF(INDIRECT("'"&$B$3&"'!F21")="","",INDIRECT("'"&$B$3&"'!F21")) | F28: =IF(INDIRECT("'"&$B$3&"'!G21")="","",INDIRECT("'"&$B$3&"'!G21")) | G28: =IF(INDIRECT("'"&$B$3&"'!I21")="","",INDIRECT("'"&$B$3&"'!I21"))
A29: =IF(INDIRECT("'"&$B$3&"'!A22")="","",INDIRECT("'"&$B$3&"'!A22")) | B29: =IF(INDIRECT("'"&$B$3&"'!B22")="","",INDIRECT("'"&$B$3&"'!B22")) | C29: =IF(INDIRECT("'"&$B$3&"'!C22")="","",INDIRECT("'"&$B$3&"'!C22")) | D29: =IF(INDIRECT("'"&$B$3&"'!E22")="","",INDIRECT("'"&$B$3&"'!E22")) | E29: =IF(INDIRECT("'"&$B$3&"'!F22")="","",INDIRECT("'"&$B$3&"'!F22")) | F29: =IF(INDIRECT("'"&$B$3&"'!G22")="","",INDIRECT("'"&$B$3&"'!G22")) | G29: =IF(INDIRECT("'"&$B$3&"'!I22")="","",INDIRECT("'"&$B$3&"'!I22"))
A30: =IF(INDIRECT("'"&$B$3&"'!A23")="","",INDIRECT("'"&$B$3&"'!A23")) | B30: =IF(INDIRECT("'"&$B$3&"'!B23")="","",INDIRECT("'"&$B$3&"'!B23")) | C30: =IF(INDIRECT("'"&$B$3&"'!C23")="","",INDIRECT("'"&$B$3&"'!C23")) | D30: =IF(INDIRECT("'"&$B$3&"'!E23")="","",INDIRECT("'"&$B$3&"'!E23")) | E30: =IF(INDIRECT("'"&$B$3&"'!F23")="","",INDIRECT("'"&$B$3&"'!F23")) | F30: =IF(INDIRECT("'"&$B$3&"'!G23")="","",INDIRECT("'"&$B$3&"'!G23")) | G30: =IF(INDIRECT("'"&$B$3&"'!I23")="","",INDIRECT("'"&$B$3&"'!I23"))
A31: =IF(INDIRECT("'"&$B$3&"'!A24")="","",INDIRECT("'"&$B$3&"'!A24")) | B31: =IF(INDIRECT("'"&$B$3&"'!B24")="","",INDIRECT("'"&$B$3&"'!B24")) | C31: =IF(INDIRECT("'"&$B$3&"'!C24")="","",INDIRECT("'"&$B$3&"'!C24")) | D31: =IF(INDIRECT("'"&$B$3&"'!E24")="","",INDIRECT("'"&$B$3&"'!E24")) | E31: =IF(INDIRECT("'"&$B$3&"'!F24")="","",INDIRECT("'"&$B$3&"'!F24")) | F31: =IF(INDIRECT("'"&$B$3&"'!G24")="","",INDIRECT("'"&$B$3&"'!G24")) | G31: =IF(INDIRECT("'"&$B$3&"'!I24")="","",INDIRECT("'"&$B$3&"'!I24"))
A32: =IF(INDIRECT("'"&$B$3&"'!A25")="","",INDIRECT("'"&$B$3&"'!A25")) | B32: =IF(INDIRECT("'"&$B$3&"'!B25")="","",INDIRECT("'"&$B$3&"'!B25")) | C32: =IF(INDIRECT("'"&$B$3&"'!C25")="","",INDIRECT("'"&$B$3&"'!C25")) | D32: =IF(INDIRECT("'"&$B$3&"'!E25")="","",INDIRECT("'"&$B$3&"'!E25")) | E32: =IF(INDIRECT("'"&$B$3&"'!F25")="","",INDIRECT("'"&$B$3&"'!F25")) | F32: =IF(INDIRECT("'"&$B$3&"'!G25")="","",INDIRECT("'"&$B$3&"'!G25")) | G32: =IF(INDIRECT("'"&$B$3&"'!I25")="","",INDIRECT("'"&$B$3&"'!I25"))
A33: =IF(INDIRECT("'"&$B$3&"'!A26")="","",INDIRECT("'"&$B$3&"'!A26")) | B33: =IF(INDIRECT("'"&$B$3&"'!B26")="","",INDIRECT("'"&$B$3&"'!B26")) | C33: =IF(INDIRECT("'"&$B$3&"'!C26")="","",INDIRECT("'"&$B$3&"'!C26")) | D33: =IF(INDIRECT("'"&$B$3&"'!E26")="","",INDIRECT("'"&$B$3&"'!E26")) | E33: =IF(INDIRECT("'"&$B$3&"'!F26")="","",INDIRECT("'"&$B$3&"'!F26")) | F33: =IF(INDIRECT("'"&$B$3&"'!G26")="","",INDIRECT("'"&$B$3&"'!G26")) | G33: =IF(INDIRECT("'"&$B$3&"'!I26")="","",INDIRECT("'"&$B$3&"'!I26"))
A34: =IF(INDIRECT("'"&$B$3&"'!A27")="","",INDIRECT("'"&$B$3&"'!A27")) | B34: =IF(INDIRECT("'"&$B$3&"'!B27")="","",INDIRECT("'"&$B$3&"'!B27")) | C34: =IF(INDIRECT("'"&$B$3&"'!C27")="","",INDIRECT("'"&$B$3&"'!C27")) | D34: =IF(INDIRECT("'"&$B$3&"'!E27")="","",INDIRECT("'"&$B$3&"'!E27")) | E34: =IF(INDIRECT("'"&$B$3&"'!F27")="","",INDIRECT("'"&$B$3&"'!F27")) | F34: =IF(INDIRECT("'"&$B$3&"'!G27")="","",INDIRECT("'"&$B$3&"'!G27")) | G34: =IF(INDIRECT("'"&$B$3&"'!I27")="","",INDIRECT("'"&$B$3&"'!I27"))
A35: =IF(INDIRECT("'"&$B$3&"'!A28")="","",INDIRECT("'"&$B$3&"'!A28")) | B35: =IF(INDIRECT("'"&$B$3&"'!B28")="","",INDIRECT("'"&$B$3&"'!B28")) | C35: =IF(INDIRECT("'"&$B$3&"'!C28")="","",INDIRECT("'"&$B$3&"'!C28")) | D35: =IF(INDIRECT("'"&$B$3&"'!E28")="","",INDIRECT("'"&$B$3&"'!E28")) | E35: =IF(INDIRECT("'"&$B$3&"'!F28")="","",INDIRECT("'"&$B$3&"'!F28")) | F35: =IF(INDIRECT("'"&$B$3&"'!G28")="","",INDIRECT("'"&$B$3&"'!G28")) | G35: =IF(INDIRECT("'"&$B$3&"'!I28")="","",INDIRECT("'"&$B$3&"'!I28"))
A36: =IF(INDIRECT("'"&$B$3&"'!A29")="","",INDIRECT("'"&$B$3&"'!A29")) | B36: =IF(INDIRECT("'"&$B$3&"'!B29")="","",INDIRECT("'"&$B$3&"'!B29")) | C36: =IF(INDIRECT("'"&$B$3&"'!C29")="","",INDIRECT("'"&$B$3&"'!C29")) | D36: =IF(INDIRECT("'"&$B$3&"'!E29")="","",INDIRECT("'"&$B$3&"'!E29")) | E36: =IF(INDIRECT("'"&$B$3&"'!F29")="","",INDIRECT("'"&$B$3&"'!F29")) | F36: =IF(INDIRECT("'"&$B$3&"'!G29")="","",INDIRECT("'"&$B$3&"'!G29")) | G36: =IF(INDIRECT("'"&$B$3&"'!I29")="","",INDIRECT("'"&$B$3&"'!I29"))
A37: =IF(INDIRECT("'"&$B$3&"'!A30")="","",INDIRECT("'"&$B$3&"'!A30")) | B37: =IF(INDIRECT("'"&$B$3&"'!B30")="","",INDIRECT("'"&$B$3&"'!B30")) | C37: =IF(INDIRECT("'"&$B$3&"'!C30")="","",INDIRECT("'"&$B$3&"'!C30")) | D37: =IF(INDIRECT("'"&$B$3&"'!E30")="","",INDIRECT("'"&$B$3&"'!E30")) | E37: =IF(INDIRECT("'"&$B$3&"'!F30")="","",INDIRECT("'"&$B$3&"'!F30")) | F37: =IF(INDIRECT("'"&$B$3&"'!G30")="","",INDIRECT("'"&$B$3&"'!G30")) | G37: =IF(INDIRECT("'"&$B$3&"'!I30")="","",INDIRECT("'"&$B$3&"'!I30"))
A38: =IF(INDIRECT("'"&$B$3&"'!A31")="","",INDIRECT("'"&$B$3&"'!A31")) | B38: =IF(INDIRECT("'"&$B$3&"'!B31")="","",INDIRECT("'"&$B$3&"'!B31")) | C38: =IF(INDIRECT("'"&$B$3&"'!C31")="","",INDIRECT("'"&$B$3&"'!C31")) | D38: =IF(INDIRECT("'"&$B$3&"'!E31")="","",INDIRECT("'"&$B$3&"'!E31")) | E38: =IF(INDIRECT("'"&$B$3&"'!F31")="","",INDIRECT("'"&$B$3&"'!F31")) | F38: =IF(INDIRECT("'"&$B$3&"'!G31")="","",INDIRECT("'"&$B$3&"'!G31")) | G38: =IF(INDIRECT("'"&$B$3&"'!I31")="","",INDIRECT("'"&$B$3&"'!I31"))
A39: =IF(INDIRECT("'"&$B$3&"'!A32")="","",INDIRECT("'"&$B$3&"'!A32")) | B39: =IF(INDIRECT("'"&$B$3&"'!B32")="","",INDIRECT("'"&$B$3&"'!B32")) | C39: =IF(INDIRECT("'"&$B$3&"'!C32")="","",INDIRECT("'"&$B$3&"'!C32")) | D39: =IF(INDIRECT("'"&$B$3&"'!E32")="","",INDIRECT("'"&$B$3&"'!E32")) | E39: =IF(INDIRECT("'"&$B$3&"'!F32")="","",INDIRECT("'"&$B$3&"'!F32")) | F39: =IF(INDIRECT("'"&$B$3&"'!G32")="","",INDIRECT("'"&$B$3&"'!G32")) | G39: =IF(INDIRECT("'"&$B$3&"'!I32")="","",INDIRECT("'"&$B$3&"'!I32"))
A40: =IF(INDIRECT("'"&$B$3&"'!A33")="","",INDIRECT("'"&$B$3&"'!A33")) | B40: =IF(INDIRECT("'"&$B$3&"'!B33")="","",INDIRECT("'"&$B$3&"'!B33")) | C40: =IF(INDIRECT("'"&$B$3&"'!C33")="","",INDIRECT("'"&$B$3&"'!C33")) | D40: =IF(INDIRECT("'"&$B$3&"'!E33")="","",INDIRECT("'"&$B$3&"'!E33")) | E40: =IF(INDIRECT("'"&$B$3&"'!F33")="","",INDIRECT("'"&$B$3&"'!F33")) | F40: =IF(INDIRECT("'"&$B$3&"'!G33")="","",INDIRECT("'"&$B$3&"'!G33")) | G40: =IF(INDIRECT("'"&$B$3&"'!I33")="","",INDIRECT("'"&$B$3&"'!I33"))
A41: =IF(INDIRECT("'"&$B$3&"'!A34")="","",INDIRECT("'"&$B$3&"'!A34")) | B41: =IF(INDIRECT("'"&$B$3&"'!B34")="","",INDIRECT("'"&$B$3&"'!B34")) | C41: =IF(INDIRECT("'"&$B$3&"'!C34")="","",INDIRECT("'"&$B$3&"'!C34")) | D41: =IF(INDIRECT("'"&$B$3&"'!E34")="","",INDIRECT("'"&$B$3&"'!E34")) | E41: =IF(INDIRECT("'"&$B$3&"'!F34")="","",INDIRECT("'"&$B$3&"'!F34")) | F41: =IF(INDIRECT("'"&$B$3&"'!G34")="","",INDIRECT("'"&$B$3&"'!G34")) | G41: =IF(INDIRECT("'"&$B$3&"'!I34")="","",INDIRECT("'"&$B$3&"'!I34"))
A42: =IF(INDIRECT("'"&$B$3&"'!A35")="","",INDIRECT("'"&$B$3&"'!A35")) | B42: =IF(INDIRECT("'"&$B$3&"'!B35")="","",INDIRECT("'"&$B$3&"'!B35")) | C42: =IF(INDIRECT("'"&$B$3&"'!C35")="","",INDIRECT("'"&$B$3&"'!C35")) | D42: =IF(INDIRECT("'"&$B$3&"'!E35")="","",INDIRECT("'"&$B$3&"'!E35")) | E42: =IF(INDIRECT("'"&$B$3&"'!F35")="","",INDIRECT("'"&$B$3&"'!F35")) | F42: =IF(INDIRECT("'"&$B$3&"'!G35")="","",INDIRECT("'"&$B$3&"'!G35")) | G42: =IF(INDIRECT("'"&$B$3&"'!I35")="","",INDIRECT("'"&$B$3&"'!I35"))
A43: =IF(INDIRECT("'"&$B$3&"'!A36")="","",INDIRECT("'"&$B$3&"'!A36")) | B43: =IF(INDIRECT("'"&$B$3&"'!B36")="","",INDIRECT("'"&$B$3&"'!B36")) | C43: =IF(INDIRECT("'"&$B$3&"'!C36")="","",INDIRECT("'"&$B$3&"'!C36")) | D43: =IF(INDIRECT("'"&$B$3&"'!E36")="","",INDIRECT("'"&$B$3&"'!E36")) | E43: =IF(INDIRECT("'"&$B$3&"'!F36")="","",INDIRECT("'"&$B$3&"'!F36")) | F43: =IF(INDIRECT("'"&$B$3&"'!G36")="","",INDIRECT("'"&$B$3&"'!G36")) | G43: =IF(INDIRECT("'"&$B$3&"'!I36")="","",INDIRECT("'"&$B$3&"'!I36"))
A44: =IF(INDIRECT("'"&$B$3&"'!A37")="","",INDIRECT("'"&$B$3&"'!A37")) | B44: =IF(INDIRECT("'"&$B$3&"'!B37")="","",INDIRECT("'"&$B$3&"'!B37")) | C44: =IF(INDIRECT("'"&$B$3&"'!C37")="","",INDIRECT("'"&$B$3&"'!C37")) | D44: =IF(INDIRECT("'"&$B$3&"'!E37")="","",INDIRECT("'"&$B$3&"'!E37")) | E44: =IF(INDIRECT("'"&$B$3&"'!F37")="","",INDIRECT("'"&$B$3&"'!F37")) | F44: =IF(INDIRECT("'"&$B$3&"'!G37")="","",INDIRECT("'"&$B$3&"'!G37")) | G44: =IF(INDIRECT("'"&$B$3&"'!I37")="","",INDIRECT("'"&$B$3&"'!I37"))
A45: =IF(INDIRECT("'"&$B$3&"'!A38")="","",INDIRECT("'"&$B$3&"'!A38")) | B45: =IF(INDIRECT("'"&$B$3&"'!B38")="","",INDIRECT("'"&$B$3&"'!B38")) | C45: =IF(INDIRECT("'"&$B$3&"'!C38")="","",INDIRECT("'"&$B$3&"'!C38")) | D45: =IF(INDIRECT("'"&$B$3&"'!E38")="","",INDIRECT("'"&$B$3&"'!E38")) | E45: =IF(INDIRECT("'"&$B$3&"'!F38")="","",INDIRECT("'"&$B$3&"'!F38")) | F45: =IF(INDIRECT("'"&$B$3&"'!G38")="","",INDIRECT("'"&$B$3&"'!G38")) | G45: =IF(INDIRECT("'"&$B$3&"'!I38")="","",INDIRECT("'"&$B$3&"'!I38"))
A46: =IF(INDIRECT("'"&$B$3&"'!A39")="","",INDIRECT("'"&$B$3&"'!A39")) | B46: =IF(INDIRECT("'"&$B$3&"'!B39")="","",INDIRECT("'"&$B$3&"'!B39")) | C46: =IF(INDIRECT("'"&$B$3&"'!C39")="","",INDIRECT("'"&$B$3&"'!C39")) | D46: =IF(INDIRECT("'"&$B$3&"'!E39")="","",INDIRECT("'"&$B$3&"'!E39")) | E46: =IF(INDIRECT("'"&$B$3&"'!F39")="","",INDIRECT("'"&$B$3&"'!F39")) | F46: =IF(INDIRECT("'"&$B$3&"'!G39")="","",INDIRECT("'"&$B$3&"'!G39")) | G46: =IF(INDIRECT("'"&$B$3&"'!I39")="","",INDIRECT("'"&$B$3&"'!I39"))
A47: =IF(INDIRECT("'"&$B$3&"'!A40")="","",INDIRECT("'"&$B$3&"'!A40")) | B47: =IF(INDIRECT("'"&$B$3&"'!B40")="","",INDIRECT("'"&$B$3&"'!B40")) | C47: =IF(INDIRECT("'"&$B$3&"'!C40")="","",INDIRECT("'"&$B$3&"'!C40")) | D47: =IF(INDIRECT("'"&$B$3&"'!E40")="","",INDIRECT("'"&$B$3&"'!E40")) | E47: =IF(INDIRECT("'"&$B$3&"'!F40")="","",INDIRECT("'"&$B$3&"'!F40")) | F47: =IF(INDIRECT("'"&$B$3&"'!G40")="","",INDIRECT("'"&$B$3&"'!G40")) | G47: =IF(INDIRECT("'"&$B$3&"'!I40")="","",INDIRECT("'"&$B$3&"'!I40"))
A48: =IF(INDIRECT("'"&$B$3&"'!A41")="","",INDIRECT("'"&$B$3&"'!A41")) | B48: =IF(INDIRECT("'"&$B$3&"'!B41")="","",INDIRECT("'"&$B$3&"'!B41")) | C48: =IF(INDIRECT("'"&$B$3&"'!C41")="","",INDIRECT("'"&$B$3&"'!C41")) | D48: =IF(INDIRECT("'"&$B$3&"'!E41")="","",INDIRECT("'"&$B$3&"'!E41")) | E48: =IF(INDIRECT("'"&$B$3&"'!F41")="","",INDIRECT("'"&$B$3&"'!F41")) | F48: =IF(INDIRECT("'"&$B$3&"'!G41")="","",INDIRECT("'"&$B$3&"'!G41")) | G48: =IF(INDIRECT("'"&$B$3&"'!I41")="","",INDIRECT("'"&$B$3&"'!I41"))
A49: =IF(INDIRECT("'"&$B$3&"'!A42")="","",INDIRECT("'"&$B$3&"'!A42")) | B49: =IF(INDIRECT("'"&$B$3&"'!B42")="","",INDIRECT("'"&$B$3&"'!B42")) | C49: =IF(INDIRECT("'"&$B$3&"'!C42")="","",INDIRECT("'"&$B$3&"'!C42")) | D49: =IF(INDIRECT("'"&$B$3&"'!E42")="","",INDIRECT("'"&$B$3&"'!E42")) | E49: =IF(INDIRECT("'"&$B$3&"'!F42")="","",INDIRECT("'"&$B$3&"'!F42")) | F49: =IF(INDIRECT("'"&$B$3&"'!G42")="","",INDIRECT("'"&$B$3&"'!G42")) | G49: =IF(INDIRECT("'"&$B$3&"'!I42")="","",INDIRECT("'"&$B$3&"'!I42"))
A50: =IF(INDIRECT("'"&$B$3&"'!A43")="","",INDIRECT("'"&$B$3&"'!A43")) | B50: =IF(INDIRECT("'"&$B$3&"'!B43")="","",INDIRECT("'"&$B$3&"'!B43")) | C50: =IF(INDIRECT("'"&$B$3&"'!C43")="","",INDIRECT("'"&$B$3&"'!C43")) | D50: =IF(INDIRECT("'"&$B$3&"'!E43")="","",INDIRECT("'"&$B$3&"'!E43")) | E50: =IF(INDIRECT("'"&$B$3&"'!F43")="","",INDIRECT("'"&$B$3&"'!F43")) | F50: =IF(INDIRECT("'"&$B$3&"'!G43")="","",INDIRECT("'"&$B$3&"'!G43")) | G50: =IF(INDIRECT("'"&$B$3&"'!I43")="","",INDIRECT("'"&$B$3&"'!I43"))
A51: =IF(INDIRECT("'"&$B$3&"'!A44")="","",INDIRECT("'"&$B$3&"'!A44")) | B51: =IF(INDIRECT("'"&$B$3&"'!B44")="","",INDIRECT("'"&$B$3&"'!B44")) | C51: =IF(INDIRECT("'"&$B$3&"'!C44")="","",INDIRECT("'"&$B$3&"'!C44")) | D51: =IF(INDIRECT("'"&$B$3&"'!E44")="","",INDIRECT("'"&$B$3&"'!E44")) | E51: =IF(INDIRECT("'"&$B$3&"'!F44")="","",INDIRECT("'"&$B$3&"'!F44")) | F51: =IF(INDIRECT("'"&$B$3&"'!G44")="","",INDIRECT("'"&$B$3&"'!G44")) | G51: =IF(INDIRECT("'"&$B$3&"'!I44")="","",INDIRECT("'"&$B$3&"'!I44"))
A52: =IF(INDIRECT("'"&$B$3&"'!A45")="","",INDIRECT("'"&$B$3&"'!A45")) | B52: =IF(INDIRECT("'"&$B$3&"'!B45")="","",INDIRECT("'"&$B$3&"'!B45")) | C52: =IF(INDIRECT("'"&$B$3&"'!C45")="","",INDIRECT("'"&$B$3&"'!C45")) | D52: =IF(INDIRECT("'"&$B$3&"'!E45")="","",INDIRECT("'"&$B$3&"'!E45")) | E52: =IF(INDIRECT("'"&$B$3&"'!F45")="","",INDIRECT("'"&$B$3&"'!F45")) | F52: =IF(INDIRECT("'"&$B$3&"'!G45")="","",INDIRECT("'"&$B$3&"'!G45")) | G52: =IF(INDIRECT("'"&$B$3&"'!I45")="","",INDIRECT("'"&$B$3&"'!I45"))
A53: =IF(INDIRECT("'"&$B$3&"'!A46")="","",INDIRECT("'"&$B$3&"'!A46")) | B53: =IF(INDIRECT("'"&$B$3&"'!B46")="","",INDIRECT("'"&$B$3&"'!B46")) | C53: =IF(INDIRECT("'"&$B$3&"'!C46")="","",INDIRECT("'"&$B$3&"'!C46")) | D53: =IF(INDIRECT("'"&$B$3&"'!E46")="","",INDIRECT("'"&$B$3&"'!E46")) | E53: =IF(INDIRECT("'"&$B$3&"'!F46")="","",INDIRECT("'"&$B$3&"'!F46")) | F53: =IF(INDIRECT("'"&$B$3&"'!G46")="","",INDIRECT("'"&$B$3&"'!G46")) | G53: =IF(INDIRECT("'"&$B$3&"'!I46")="","",INDIRECT("'"&$B$3&"'!I46"))
A54: =IF(INDIRECT("'"&$B$3&"'!A47")="","",INDIRECT("'"&$B$3&"'!A47")) | B54: =IF(INDIRECT("'"&$B$3&"'!B47")="","",INDIRECT("'"&$B$3&"'!B47")) | C54: =IF(INDIRECT("'"&$B$3&"'!C47")="","",INDIRECT("'"&$B$3&"'!C47")) | D54: =IF(INDIRECT("'"&$B$3&"'!E47")="","",INDIRECT("'"&$B$3&"'!E47")) | E54: =IF(INDIRECT("'"&$B$3&"'!F47")="","",INDIRECT("'"&$B$3&"'!F47")) | F54: =IF(INDIRECT("'"&$B$3&"'!G47")="","",INDIRECT("'"&$B$3&"'!G47")) | G54: =IF(INDIRECT("'"&$B$3&"'!I47")="","",INDIRECT("'"&$B$3&"'!I47"))
A55: =IF(INDIRECT("'"&$B$3&"'!A48")="","",INDIRECT("'"&$B$3&"'!A48")) | B55: =IF(INDIRECT("'"&$B$3&"'!B48")="","",INDIRECT("'"&$B$3&"'!B48")) | C55: =IF(INDIRECT("'"&$B$3&"'!C48")="","",INDIRECT("'"&$B$3&"'!C48")) | D55: =IF(INDIRECT("'"&$B$3&"'!E48")="","",INDIRECT("'"&$B$3&"'!E48")) | E55: =IF(INDIRECT("'"&$B$3&"'!F48")="","",INDIRECT("'"&$B$3&"'!F48")) | F55: =IF(INDIRECT("'"&$B$3&"'!G48")="","",INDIRECT("'"&$B$3&"'!G48")) | G55: =IF(INDIRECT("'"&$B$3&"'!I48")="","",INDIRECT("'"&$B$3&"'!I48"))
A56: =IF(INDIRECT("'"&$B$3&"'!A49")="","",INDIRECT("'"&$B$3&"'!A49")) | B56: =IF(INDIRECT("'"&$B$3&"'!B49")="","",INDIRECT("'"&$B$3&"'!B49")) | C56: =IF(INDIRECT("'"&$B$3&"'!C49")="","",INDIRECT("'"&$B$3&"'!C49")) | D56: =IF(INDIRECT("'"&$B$3&"'!E49")="","",INDIRECT("'"&$B$3&"'!E49")) | E56: =IF(INDIRECT("'"&$B$3&"'!F49")="","",INDIRECT("'"&$B$3&"'!F49")) | F56: =IF(INDIRECT("'"&$B$3&"'!G49")="","",INDIRECT("'"&$B$3&"'!G49")) | G56: =IF(INDIRECT("'"&$B$3&"'!I49")="","",INDIRECT("'"&$B$3&"'!I49"))
A57: =IF(INDIRECT("'"&$B$3&"'!A50")="","",INDIRECT("'"&$B$3&"'!A50")) | B57: =IF(INDIRECT("'"&$B$3&"'!B50")="","",INDIRECT("'"&$B$3&"'!B50")) | C57: =IF(INDIRECT("'"&$B$3&"'!C50")="","",INDIRECT("'"&$B$3&"'!C50")) | D57: =IF(INDIRECT("'"&$B$3&"'!E50")="","",INDIRECT("'"&$B$3&"'!E50")) | E57: =IF(INDIRECT("'"&$B$3&"'!F50")="","",INDIRECT("'"&$B$3&"'!F50")) | F57: =IF(INDIRECT("'"&$B$3&"'!G50")="","",INDIRECT("'"&$B$3&"'!G50")) | G57: =IF(INDIRECT("'"&$B$3&"'!I50")="","",INDIRECT("'"&$B$3&"'!I50"))
A58: =IF(INDIRECT("'"&$B$3&"'!A51")="","",INDIRECT("'"&$B$3&"'!A51")) | B58: =IF(INDIRECT("'"&$B$3&"'!B51")="","",INDIRECT("'"&$B$3&"'!B51")) | C58: =IF(INDIRECT("'"&$B$3&"'!C51")="","",INDIRECT("'"&$B$3&"'!C51")) | D58: =IF(INDIRECT("'"&$B$3&"'!E51")="","",INDIRECT("'"&$B$3&"'!E51")) | E58: =IF(INDIRECT("'"&$B$3&"'!F51")="","",INDIRECT("'"&$B$3&"'!F51")) | F58: =IF(INDIRECT("'"&$B$3&"'!G51")="","",INDIRECT("'"&$B$3&"'!G51")) | G58: =IF(INDIRECT("'"&$B$3&"'!I51")="","",INDIRECT("'"&$B$3&"'!I51"))
A59: =IF(INDIRECT("'"&$B$3&"'!A52")="","",INDIRECT("'"&$B$3&"'!A52")) | B59: =IF(INDIRECT("'"&$B$3&"'!B52")="","",INDIRECT("'"&$B$3&"'!B52")) | C59: =IF(INDIRECT("'"&$B$3&"'!C52")="","",INDIRECT("'"&$B$3&"'!C52")) | D59: =IF(INDIRECT("'"&$B$3&"'!E52")="","",INDIRECT("'"&$B$3&"'!E52")) | E59: =IF(INDIRECT("'"&$B$3&"'!F52")="","",INDIRECT("'"&$B$3&"'!F52")) | F59: =IF(INDIRECT("'"&$B$3&"'!G52")="","",INDIRECT("'"&$B$3&"'!G52")) | G59: =IF(INDIRECT("'"&$B$3&"'!I52")="","",INDIRECT("'"&$B$3&"'!I52"))
A60: =IF(INDIRECT("'"&$B$3&"'!A53")="","",INDIRECT("'"&$B$3&"'!A53")) | B60: =IF(INDIRECT("'"&$B$3&"'!B53")="","",INDIRECT("'"&$B$3&"'!B53")) | C60: =IF(INDIRECT("'"&$B$3&"'!C53")="","",INDIRECT("'"&$B$3&"'!C53")) | D60: =IF(INDIRECT("'"&$B$3&"'!E53")="","",INDIRECT("'"&$B$3&"'!E53")) | E60: =IF(INDIRECT("'"&$B$3&"'!F53")="","",INDIRECT("'"&$B$3&"'!F53")) | F60: =IF(INDIRECT("'"&$B$3&"'!G53")="","",INDIRECT("'"&$B$3&"'!G53")) | G60: =IF(INDIRECT("'"&$B$3&"'!I53")="","",INDIRECT("'"&$B$3&"'!I53"))
A61: =IF(INDIRECT("'"&$B$3&"'!A54")="","",INDIRECT("'"&$B$3&"'!A54")) | B61: =IF(INDIRECT("'"&$B$3&"'!B54")="","",INDIRECT("'"&$B$3&"'!B54")) | C61: =IF(INDIRECT("'"&$B$3&"'!C54")="","",INDIRECT("'"&$B$3&"'!C54")) | D61: =IF(INDIRECT("'"&$B$3&"'!E54")="","",INDIRECT("'"&$B$3&"'!E54")) | E61: =IF(INDIRECT("'"&$B$3&"'!F54")="","",INDIRECT("'"&$B$3&"'!F54")) | F61: =IF(INDIRECT("'"&$B$3&"'!G54")="","",INDIRECT("'"&$B$3&"'!G54")) | G61: =IF(INDIRECT("'"&$B$3&"'!I54")="","",INDIRECT("'"&$B$3&"'!I54"))
A62: =IF(INDIRECT("'"&$B$3&"'!A55")="","",INDIRECT("'"&$B$3&"'!A55")) | B62: =IF(INDIRECT("'"&$B$3&"'!B55")="","",INDIRECT("'"&$B$3&"'!B55")) | C62: =IF(INDIRECT("'"&$B$3&"'!C55")="","",INDIRECT("'"&$B$3&"'!C55")) | D62: =IF(INDIRECT("'"&$B$3&"'!E55")="","",INDIRECT("'"&$B$3&"'!E55")) | E62: =IF(INDIRECT("'"&$B$3&"'!F55")="","",INDIRECT("'"&$B$3&"'!F55")) | F62: =IF(INDIRECT("'"&$B$3&"'!G55")="","",INDIRECT("'"&$B$3&"'!G55")) | G62: =IF(INDIRECT("'"&$B$3&"'!I55")="","",INDIRECT("'"&$B$3&"'!I55"))
A63: =IF(INDIRECT("'"&$B$3&"'!A56")="","",INDIRECT("'"&$B$3&"'!A56")) | B63: =IF(INDIRECT("'"&$B$3&"'!B56")="","",INDIRECT("'"&$B$3&"'!B56")) | C63: =IF(INDIRECT("'"&$B$3&"'!C56")="","",INDIRECT("'"&$B$3&"'!C56")) | D63: =IF(INDIRECT("'"&$B$3&"'!E56")="","",INDIRECT("'"&$B$3&"'!E56")) | E63: =IF(INDIRECT("'"&$B$3&"'!F56")="","",INDIRECT("'"&$B$3&"'!F56")) | F63: =IF(INDIRECT("'"&$B$3&"'!G56")="","",INDIRECT("'"&$B$3&"'!G56")) | G63: =IF(INDIRECT("'"&$B$3&"'!I56")="","",INDIRECT("'"&$B$3&"'!I56"))
A64: =IF(INDIRECT("'"&$B$3&"'!A57")="","",INDIRECT("'"&$B$3&"'!A57")) | B64: =IF(INDIRECT("'"&$B$3&"'!B57")="","",INDIRECT("'"&$B$3&"'!B57")) | C64: =IF(INDIRECT("'"&$B$3&"'!C57")="","",INDIRECT("'"&$B$3&"'!C57")) | D64: =IF(INDIRECT("'"&$B$3&"'!E57")="","",INDIRECT("'"&$B$3&"'!E57")) | E64: =IF(INDIRECT("'"&$B$3&"'!F57")="","",INDIRECT("'"&$B$3&"'!F57")) | F64: =IF(INDIRECT("'"&$B$3&"'!G57")="","",INDIRECT("'"&$B$3&"'!G57")) | G64: =IF(INDIRECT("'"&$B$3&"'!I57")="","",INDIRECT("'"&$B$3&"'!I57"))
A65: =IF(INDIRECT("'"&$B$3&"'!A58")="","",INDIRECT("'"&$B$3&"'!A58")) | B65: =IF(INDIRECT("'"&$B$3&"'!B58")="","",INDIRECT("'"&$B$3&"'!B58")) | C65: =IF(INDIRECT("'"&$B$3&"'!C58")="","",INDIRECT("'"&$B$3&"'!C58")) | D65: =IF(INDIRECT("'"&$B$3&"'!E58")="","",INDIRECT("'"&$B$3&"'!E58")) | E65: =IF(INDIRECT("'"&$B$3&"'!F58")="","",INDIRECT("'"&$B$3&"'!F58")) | F65: =IF(INDIRECT("'"&$B$3&"'!G58")="","",INDIRECT("'"&$B$3&"'!G58")) | G65: =IF(INDIRECT("'"&$B$3&"'!I58")="","",INDIRECT("'"&$B$3&"'!I58"))
A66: =IF(INDIRECT("'"&$B$3&"'!A59")="","",INDIRECT("'"&$B$3&"'!A59")) | B66: =IF(INDIRECT("'"&$B$3&"'!B59")="","",INDIRECT("'"&$B$3&"'!B59")) | C66: =IF(INDIRECT("'"&$B$3&"'!C59")="","",INDIRECT("'"&$B$3&"'!C59")) | D66: =IF(INDIRECT("'"&$B$3&"'!E59")="","",INDIRECT("'"&$B$3&"'!E59")) | E66: =IF(INDIRECT("'"&$B$3&"'!F59")="","",INDIRECT("'"&$B$3&"'!F59")) | F66: =IF(INDIRECT("'"&$B$3&"'!G59")="","",INDIRECT("'"&$B$3&"'!G59")) | G66: =IF(INDIRECT("'"&$B$3&"'!I59")="","",INDIRECT("'"&$B$3&"'!I59"))
A67: =IF(INDIRECT("'"&$B$3&"'!A60")="","",INDIRECT("'"&$B$3&"'!A60")) | B67: =IF(INDIRECT("'"&$B$3&"'!B60")="","",INDIRECT("'"&$B$3&"'!B60")) | C67: =IF(INDIRECT("'"&$B$3&"'!C60")="","",INDIRECT("'"&$B$3&"'!C60")) | D67: =IF(INDIRECT("'"&$B$3&"'!E60")="","",INDIRECT("'"&$B$3&"'!E60")) | E67: =IF(INDIRECT("'"&$B$3&"'!F60")="","",INDIRECT("'"&$B$3&"'!F60")) | F67: =IF(INDIRECT("'"&$B$3&"'!G60")="","",INDIRECT("'"&$B$3&"'!G60")) | G67: =IF(INDIRECT("'"&$B$3&"'!I60")="","",INDIRECT("'"&$B$3&"'!I60"))
A68: =IF(INDIRECT("'"&$B$3&"'!A61")="","",INDIRECT("'"&$B$3&"'!A61")) | B68: =IF(INDIRECT("'"&$B$3&"'!B61")="","",INDIRECT("'"&$B$3&"'!B61")) | C68: =IF(INDIRECT("'"&$B$3&"'!C61")="","",INDIRECT("'"&$B$3&"'!C61")) | D68: =IF(INDIRECT("'"&$B$3&"'!E61")="","",INDIRECT("'"&$B$3&"'!E61")) | E68: =IF(INDIRECT("'"&$B$3&"'!F61")="","",INDIRECT("'"&$B$3&"'!F61")) | F68: =IF(INDIRECT("'"&$B$3&"'!G61")="","",INDIRECT("'"&$B$3&"'!G61")) | G68: =IF(INDIRECT("'"&$B$3&"'!I61")="","",INDIRECT("'"&$B$3&"'!I61"))
A69: =IF(INDIRECT("'"&$B$3&"'!A62")="","",INDIRECT("'"&$B$3&"'!A62")) | B69: =IF(INDIRECT("'"&$B$3&"'!B62")="","",INDIRECT("'"&$B$3&"'!B62")) | C69: =IF(INDIRECT("'"&$B$3&"'!C62")="","",INDIRECT("'"&$B$3&"'!C62")) | D69: =IF(INDIRECT("'"&$B$3&"'!E62")="","",INDIRECT("'"&$B$3&"'!E62")) | E69: =IF(INDIRECT("'"&$B$3&"'!F62")="","",INDIRECT("'"&$B$3&"'!F62")) | F69: =IF(INDIRECT("'"&$B$3&"'!G62")="","",INDIRECT("'"&$B$3&"'!G62")) | G69: =IF(INDIRECT("'"&$B$3&"'!I62")="","",INDIRECT("'"&$B$3&"'!I62"))
A70: =IF(INDIRECT("'"&$B$3&"'!A63")="","",INDIRECT("'"&$B$3&"'!A63")) | B70: =IF(INDIRECT("'"&$B$3&"'!B63")="","",INDIRECT("'"&$B$3&"'!B63")) | C70: =IF(INDIRECT("'"&$B$3&"'!C63")="","",INDIRECT("'"&$B$3&"'!C63")) | D70: =IF(INDIRECT("'"&$B$3&"'!E63")="","",INDIRECT("'"&$B$3&"'!E63")) | E70: =IF(INDIRECT("'"&$B$3&"'!F63")="","",INDIRECT("'"&$B$3&"'!F63")) | F70: =IF(INDIRECT("'"&$B$3&"'!G63")="","",INDIRECT("'"&$B$3&"'!G63")) | G70: =IF(INDIRECT("'"&$B$3&"'!I63")="","",INDIRECT("'"&$B$3&"'!I63"))
A71: =IF(INDIRECT("'"&$B$3&"'!A64")="","",INDIRECT("'"&$B$3&"'!A64")) | B71: =IF(INDIRECT("'"&$B$3&"'!B64")="","",INDIRECT("'"&$B$3&"'!B64")) | C71: =IF(INDIRECT("'"&$B$3&"'!C64")="","",INDIRECT("'"&$B$3&"'!C64")) | D71: =IF(INDIRECT("'"&$B$3&"'!E64")="","",INDIRECT("'"&$B$3&"'!E64")) | E71: =IF(INDIRECT("'"&$B$3&"'!F64")="","",INDIRECT("'"&$B$3&"'!F64")) | F71: =IF(INDIRECT("'"&$B$3&"'!G64")="","",INDIRECT("'"&$B$3&"'!G64")) | G71: =IF(INDIRECT("'"&$B$3&"'!I64")="","",INDIRECT("'"&$B$3&"'!I64"))
A72: =IF(INDIRECT("'"&$B$3&"'!A65")="","",INDIRECT("'"&$B$3&"'!A65")) | B72: =IF(INDIRECT("'"&$B$3&"'!B65")="","",INDIRECT("'"&$B$3&"'!B65")) | C72: =IF(INDIRECT("'"&$B$3&"'!C65")="","",INDIRECT("'"&$B$3&"'!C65")) | D72: =IF(INDIRECT("'"&$B$3&"'!E65")="","",INDIRECT("'"&$B$3&"'!E65")) | E72: =IF(INDIRECT("'"&$B$3&"'!F65")="","",INDIRECT("'"&$B$3&"'!F65")) | F72: =IF(INDIRECT("'"&$B$3&"'!G65")="","",INDIRECT("'"&$B$3&"'!G65")) | G72: =IF(INDIRECT("'"&$B$3&"'!I65")="","",INDIRECT("'"&$B$3&"'!I65"))
A73: =IF(INDIRECT("'"&$B$3&"'!A66")="","",INDIRECT("'"&$B$3&"'!A66")) | B73: =IF(INDIRECT("'"&$B$3&"'!B66")="","",INDIRECT("'"&$B$3&"'!B66")) | C73: =IF(INDIRECT("'"&$B$3&"'!C66")="","",INDIRECT("'"&$B$3&"'!C66")) | D73: =IF(INDIRECT("'"&$B$3&"'!E66")="","",INDIRECT("'"&$B$3&"'!E66")) | E73: =IF(INDIRECT("'"&$B$3&"'!F66")="","",INDIRECT("'"&$B$3&"'!F66")) | F73: =IF(INDIRECT("'"&$B$3&"'!G66")="","",INDIRECT("'"&$B$3&"'!G66")) | G73: =IF(INDIRECT("'"&$B$3&"'!I66")="","",INDIRECT("'"&$B$3&"'!I66"))
A74: =IF(INDIRECT("'"&$B$3&"'!A67")="","",INDIRECT("'"&$B$3&"'!A67")) | B74: =IF(INDIRECT("'"&$B$3&"'!B67")="","",INDIRECT("'"&$B$3&"'!B67")) | C74: =IF(INDIRECT("'"&$B$3&"'!C67")="","",INDIRECT("'"&$B$3&"'!C67")) | D74: =IF(INDIRECT("'"&$B$3&"'!E67")="","",INDIRECT("'"&$B$3&"'!E67")) | E74: =IF(INDIRECT("'"&$B$3&"'!F67")="","",INDIRECT("'"&$B$3&"'!F67")) | F74: =IF(INDIRECT("'"&$B$3&"'!G67")="","",INDIRECT("'"&$B$3&"'!G67")) | G74: =IF(INDIRECT("'"&$B$3&"'!I67")="","",INDIRECT("'"&$B$3&"'!I67"))
A75: =IF(INDIRECT("'"&$B$3&"'!A68")="","",INDIRECT("'"&$B$3&"'!A68")) | B75: =IF(INDIRECT("'"&$B$3&"'!B68")="","",INDIRECT("'"&$B$3&"'!B68")) | C75: =IF(INDIRECT("'"&$B$3&"'!C68")="","",INDIRECT("'"&$B$3&"'!C68")) | D75: =IF(INDIRECT("'"&$B$3&"'!E68")="","",INDIRECT("'"&$B$3&"'!E68")) | E75: =IF(INDIRECT("'"&$B$3&"'!F68")="","",INDIRECT("'"&$B$3&"'!F68")) | F75: =IF(INDIRECT("'"&$B$3&"'!G68")="","",INDIRECT("'"&$B$3&"'!G68")) | G75: =IF(INDIRECT("'"&$B$3&"'!I68")="","",INDIRECT("'"&$B$3&"'!I68"))
A76: =IF(INDIRECT("'"&$B$3&"'!A69")="","",INDIRECT("'"&$B$3&"'!A69")) | B76: =IF(INDIRECT("'"&$B$3&"'!B69")="","",INDIRECT("'"&$B$3&"'!B69")) | C76: =IF(INDIRECT("'"&$B$3&"'!C69")="","",INDIRECT("'"&$B$3&"'!C69")) | D76: =IF(INDIRECT("'"&$B$3&"'!E69")="","",INDIRECT("'"&$B$3&"'!E69")) | E76: =IF(INDIRECT("'"&$B$3&"'!F69")="","",INDIRECT("'"&$B$3&"'!F69")) | F76: =IF(INDIRECT("'"&$B$3&"'!G69")="","",INDIRECT("'"&$B$3&"'!G69")) | G76: =IF(INDIRECT("'"&$B$3&"'!I69")="","",INDIRECT("'"&$B$3&"'!I69"))
A77: =IF(INDIRECT("'"&$B$3&"'!A70")="","",INDIRECT("'"&$B$3&"'!A70")) | B77: =IF(INDIRECT("'"&$B$3&"'!B70")="","",INDIRECT("'"&$B$3&"'!B70")) | C77: =IF(INDIRECT("'"&$B$3&"'!C70")="","",INDIRECT("'"&$B$3&"'!C70")) | D77: =IF(INDIRECT("'"&$B$3&"'!E70")="","",INDIRECT("'"&$B$3&"'!E70")) | E77: =IF(INDIRECT("'"&$B$3&"'!F70")="","",INDIRECT("'"&$B$3&"'!F70")) | F77: =IF(INDIRECT("'"&$B$3&"'!G70")="","",INDIRECT("'"&$B$3&"'!G70")) | G77: =IF(INDIRECT("'"&$B$3&"'!I70")="","",INDIRECT("'"&$B$3&"'!I70"))
A78: =IF(INDIRECT("'"&$B$3&"'!A71")="","",INDIRECT("'"&$B$3&"'!A71")) | B78: =IF(INDIRECT("'"&$B$3&"'!B71")="","",INDIRECT("'"&$B$3&"'!B71")) | C78: =IF(INDIRECT("'"&$B$3&"'!C71")="","",INDIRECT("'"&$B$3&"'!C71")) | D78: =IF(INDIRECT("'"&$B$3&"'!E71")="","",INDIRECT("'"&$B$3&"'!E71")) | E78: =IF(INDIRECT("'"&$B$3&"'!F71")="","",INDIRECT("'"&$B$3&"'!F71")) | F78: =IF(INDIRECT("'"&$B$3&"'!G71")="","",INDIRECT("'"&$B$3&"'!G71")) | G78: =IF(INDIRECT("'"&$B$3&"'!I71")="","",INDIRECT("'"&$B$3&"'!I71"))
A79: =IF(INDIRECT("'"&$B$3&"'!A72")="","",INDIRECT("'"&$B$3&"'!A72")) | B79: =IF(INDIRECT("'"&$B$3&"'!B72")="","",INDIRECT("'"&$B$3&"'!B72")) | C79: =IF(INDIRECT("'"&$B$3&"'!C72")="","",INDIRECT("'"&$B$3&"'!C72")) | D79: =IF(INDIRECT("'"&$B$3&"'!E72")="","",INDIRECT("'"&$B$3&"'!E72")) | E79: =IF(INDIRECT("'"&$B$3&"'!F72")="","",INDIRECT("'"&$B$3&"'!F72")) | F79: =IF(INDIRECT("'"&$B$3&"'!G72")="","",INDIRECT("'"&$B$3&"'!G72")) | G79: =IF(INDIRECT("'"&$B$3&"'!I72")="","",INDIRECT("'"&$B$3&"'!I72"))
A80: =IF(INDIRECT("'"&$B$3&"'!A73")="","",INDIRECT("'"&$B$3&"'!A73")) | B80: =IF(INDIRECT("'"&$B$3&"'!B73")="","",INDIRECT("'"&$B$3&"'!B73")) | C80: =IF(INDIRECT("'"&$B$3&"'!C73")="","",INDIRECT("'"&$B$3&"'!C73")) | D80: =IF(INDIRECT("'"&$B$3&"'!E73")="","",INDIRECT("'"&$B$3&"'!E73")) | E80: =IF(INDIRECT("'"&$B$3&"'!F73")="","",INDIRECT("'"&$B$3&"'!F73")) | F80: =IF(INDIRECT("'"&$B$3&"'!G73")="","",INDIRECT("'"&$B$3&"'!G73")) | G80: =IF(INDIRECT("'"&$B$3&"'!I73")="","",INDIRECT("'"&$B$3&"'!I73"))
A82: This statement is generated from the unit ledger. For queries contact the property manager.
A83: Printed on: | B83: =TODAY()
A85: AUTOMATED PDF (desktop Excel + VBA)
A86: 1. Press Alt+F11 → Insert → Module → paste the macro from the Instructions sheet (section PDF AUTOMATION).
A87: 2. Close VBA. On Statement sheet set unit in yellow B3.
A88: 3. Press Alt+F8 → run GenerateTenantPDF → PDF is saved next to this workbook.
A89: 4. Optional: run GenerateAllTenantPDFs to create one PDF per unit into a "Statements" folder.

Sheet Archive
A1: TENANCY ARCHIVE — previous tenants only
A2: When a tenant vacates: copy their full ledger from the unit sheet into this Archive, then clear the unit sheet for the new tenant. Unit sheets should only show the CURRENT tenant.
A4: CLOSED TENANCIES REGISTER
A5: Unit | B5: Tenant Name | C5: Move-in Date | D5: Move-out Date | E5: Final Balance | F5: Deposit Held | G5: Deposit Refunded | H5: Deposit Forfeited | I5: Reason for Leaving | J5: Notes | K5: Arrears Outcome
B6: =IF(A6="","",IFERROR(INDIRECT("'"&A6&"'!J3"),"")) | C6: =IF(A6="","",IFERROR(INDEX(INDIRECT("'"&A6&"'!A6:A200"),MATCH(TRUE,INDEX(INDIRECT("'"&A6&"'!A6:A200")<>"",0),0)),"")) | E6: =IF(A6="","",IFERROR(INDIRECT("'"&A6&"'!H3"),"")) | F6: =IF(A6="","",IFERROR(INDIRECT("'"&A6&"'!L3"),""))
B7: =IF(A7="","",IFERROR(INDIRECT("'"&A7&"'!J3"),"")) | C7: =IF(A7="","",IFERROR(INDEX(INDIRECT("'"&A7&"'!A6:A200"),MATCH(TRUE,INDEX(INDIRECT("'"&A7&"'!A6:A200")<>"",0),0)),"")) | E7: =IF(A7="","",IFERROR(INDIRECT("'"&A7&"'!H3"),"")) | F7: =IF(A7="","",IFERROR(INDIRECT("'"&A7&"'!L3"),""))
B8: =IF(A8="","",IFERROR(INDIRECT("'"&A8&"'!J3"),"")) | C8: =IF(A8="","",IFERROR(INDEX(INDIRECT("'"&A8&"'!A6:A200"),MATCH(TRUE,INDEX(INDIRECT("'"&A8&"'!A6:A200")<>"",0),0)),"")) | E8: =IF(A8="","",IFERROR(INDIRECT("'"&A8&"'!H3"),"")) | F8: =IF(A8="","",IFERROR(INDIRECT("'"&A8&"'!L3"),""))
B9: =IF(A9="","",IFERROR(INDIRECT("'"&A9&"'!J3"),"")) | C9: =IF(A9="","",IFERROR(INDEX(INDIRECT("'"&A9&"'!A6:A200"),MATCH(TRUE,INDEX(INDIRECT("'"&A9&"'!A6:A200")<>"",0),0)),"")) | E9: =IF(A9="","",IFERROR(INDIRECT("'"&A9&"'!H3"),"")) | F9: =IF(A9="","",IFERROR(INDIRECT("'"&A9&"'!L3"),""))
B10: =IF(A10="","",IFERROR(INDIRECT("'"&A10&"'!J3"),"")) | C10: =IF(A10="","",IFERROR(INDEX(INDIRECT("'"&A10&"'!A6:A200"),MATCH(TRUE,INDEX(INDIRECT("'"&A10&"'!A6:A200")<>"",0),0)),"")) | E10: =IF(A10="","",IFERROR(INDIRECT("'"&A10&"'!H3"),"")) | F10: =IF(A10="","",IFERROR(INDIRECT("'"&A10&"'!L3"),""))
B11: =IF(A11="","",IFERROR(INDIRECT("'"&A11&"'!J3"),"")) | C11: =IF(A11="","",IFERROR(INDEX(INDIRECT("'"&A11&"'!A6:A200"),MATCH(TRUE,INDEX(INDIRECT("'"&A11&"'!A6:A200")<>"",0),0)),"")) | E11: =IF(A11="","",IFERROR(INDIRECT("'"&A11&"'!H3"),"")) | F11: =IF(A11="","",IFERROR(INDIRECT("'"&A11&"'!L3"),""))
B12: =IF(A12="","",IFERROR(INDIRECT("'"&A12&"'!J3"),"")) | C12: =IF(A12="","",IFERROR(INDEX(INDIRECT("'"&A12&"'!A6:A200"),MATCH(TRUE,INDEX(INDIRECT("'"&A12&"'!A6:A200")<>"",0),0)),"")) | E12: =IF(A12="","",IFERROR(INDIRECT("'"&A12&"'!H3"),"")) | F12: =IF(A12="","",IFERROR(INDIRECT("'"&A12&"'!L3"),""))
B13: =IF(A13="","",IFERROR(INDIRECT("'"&A13&"'!J3"),"")) | C13: =IF(A13="","",IFERROR(INDEX(INDIRECT("'"&A13&"'!A6:A200"),MATCH(TRUE,INDEX(INDIRECT("'"&A13&"'!A6:A200")<>"",0),0)),"")) | E13: =IF(A13="","",IFERROR(INDIRECT("'"&A13&"'!H3"),"")) | F13: =IF(A13="","",IFERROR(INDIRECT("'"&A13&"'!L3"),""))
B14: =IF(A14="","",IFERROR(INDIRECT("'"&A14&"'!J3"),"")) | C14: =IF(A14="","",IFERROR(INDEX(INDIRECT("'"&A14&"'!A6:A200"),MATCH(TRUE,INDEX(INDIRECT("'"&A14&"'!A6:A200")<>"",0),0)),"")) | E14: =IF(A14="","",IFERROR(INDIRECT("'"&A14&"'!H3"),"")) | F14: =IF(A14="","",IFERROR(INDIRECT("'"&A14&"'!L3"),""))
B15: =IF(A15="","",IFERROR(INDIRECT("'"&A15&"'!J3"),"")) | C15: =IF(A15="","",IFERROR(INDEX(INDIRECT("'"&A15&"'!A6:A200"),MATCH(TRUE,INDEX(INDIRECT("'"&A15&"'!A6:A200")<>"",0),0)),"")) | E15: =IF(A15="","",IFERROR(INDIRECT("'"&A15&"'!H3"),"")) | F15: =IF(A15="","",IFERROR(INDIRECT("'"&A15&"'!L3"),""))
B16: =IF(A16="","",IFERROR(INDIRECT("'"&A16&"'!J3"),"")) | C16: =IF(A16="","",IFERROR(INDEX(INDIRECT("'"&A16&"'!A6:A200"),MATCH(TRUE,INDEX(INDIRECT("'"&A16&"'!A6:A200")<>"",0),0)),"")) | E16: =IF(A16="","",IFERROR(INDIRECT("'"&A16&"'!H3"),"")) | F16: =IF(A16="","",IFERROR(INDIRECT("'"&A16&"'!L3"),""))
B17: =IF(A17="","",IFERROR(INDIRECT("'"&A17&"'!J3"),"")) | C17: =IF(A17="","",IFERROR(INDEX(INDIRECT("'"&A17&"'!A6:A200"),MATCH(TRUE,INDEX(INDIRECT("'"&A17&"'!A6:A200")<>"",0),0)),"")) | E17: =IF(A17="","",IFERROR(INDIRECT("'"&A17&"'!H3"),"")) | F17: =IF(A17="","",IFERROR(INDIRECT("'"&A17&"'!L3"),""))
... B35: =IF(A35="","",IFERROR(INDIRECT("'"&A35&"'!J3"),"")) | C35: =IF(A35="","",IFERROR(INDEX(INDIRECT("'"&A35&"'!A6:A200"),MATCH(TRUE,INDEX(INDIRECT("'"&A35&"'!A6:A200")<>"",0),0)),"")) | E35: =IF(A35="","",IFERROR(INDIRECT("'"&A35&"'!H3"),"")) | F35: =IF(A35="","",IFERROR(INDIRECT("'"&A35&"'!L3"),""))
A36: EVICTION / UNPAID ARREARS: Set Reason = Eviction. Set Arrears Outcome = Written off (or Still pursuing). Final Balance = amount left unpaid. Notes = notice date, lock date, deposit applied, and whether you will pursue further. Then clear the unit sheet so the next tenant starts at 0.
A37: DETAILED TRANSACTION HISTORY (paste full ledger rows here when a tenant leaves)
A38: Include Unit and Tenant Name on every row so you can filter later. Copy Date, Month, Description, Rent, Garbage, Payment, M-Pesa Ref, Running Balance, Remarks from the unit sheet.
A39: Unit | B39: Tenant Name | C39: Date | D39: Month | E39: Description | F39: Rent Charged | G39: Garbage Charged | H39: Payment Received | I39: M-Pesa Reference | J39: Running Balance | K39: Remarks | L39: Archived On

Sheet Instructions
A1: HOW TO USE THIS WORKBOOK
A4: SHEETS OVERVIEW
A5: Summary | B5: All current units — balances, priority, suggested action.
A6: Statement | B6: Printable / PDF statement for the CURRENT tenant of any unit.
A7: Archive | B7: History of PREVIOUS tenants. Unit sheets stay current-tenant only.
A8: A1 – Shop 2 | B8: One ledger per unit — current tenant only.
A10: DAILY / WEEKLY USE
A11: 1. Open Summary | B11: Check Priority column and Unit Status table at the bottom.
A12: 2. Record payments | B12: Go to the unit sheet → use blank rows at the bottom.
A13: 3. Monthly charge | B13: Select Month in column B → Date & Description fill automatically.
A14: 4. Payment | B14: Leave Month blank → choose Payment Received → enter Amount + M-Pesa Ref.
A16: WHEN A TENANT VACATES
A17: Step 1 — Settle | B17: Enter final charges and payments. Clear the balance if possible.
A18: Step 2 — Deposit | B18: Refund or forfeit. Update Deposit Held (L3) to 0 when settled.
A19: Step 3 — Archive register | B19: On Archive sheet, fill one row in CLOSED TENANCIES REGISTER (unit, name, dates, final balance, deposit outcome).
A20: Step 4 — Archive transactions | B20: Copy all transaction rows from the unit sheet into DETAILED TRANSACTION HISTORY on Archive. Add Unit + Tenant Name on every row. Put today’s date in Archived On.
A21: Step 5 — Clear unit sheet | B21: Delete the transaction rows on the unit sheet (keep the header row 1–5). Running Balance will restart at 0 for the next tenant.
A22: Step 6 — Remarks | B22: Optional: leave a note in Remarks on Archive: “Vacated [date]”.
A24: WHEN A NEW TENANT JOINS
A25: Step 1 — Confirm clear | B25: Unit sheet transaction area should be empty (only header + blank template rows).
A26: Step 2 — Update header | B26: J3 = new tenant name. D3 = rent. F3 = garbage. L3 = deposit received.
A27: Step 3 — First charge | B27: Select the move-in month in column B to create the first Monthly Rent Charge.
A28: Step 4 — Deposit note | B28: Record deposit as Payment Received (or note in Remarks) and keep L3 updated.
A29: Step 5 — Check Summary | B29: New name and balance should appear automatically.
A31: TENANT STATEMENT
A32: Current tenant | B32: Statement sheet → change yellow cell B3 to the unit → Print or Save as PDF.
A33: Previous tenant | B33: Go to Archive → filter by Tenant Name → copy the rows you need, or recreate a simple statement from the archived data.
A35: COLOUR & PRIORITY
A36: PAID (green) | B36: NO ACTION NEEDED
A37: LOW (yellow) | B37: MONITOR
A38: MEDIUM (orange) | B38: FOLLOW UP
A39: HIGH (red) | B39: URGENT
A41: GOOGLE DRIVE & PHONE
A42: Master file | B42: One master copy on Google Drive.
A43: Editing | B43: Download → edit on computer → re-upload. Avoid simultaneous phone + computer edits.
A44: Viewing | B44: Phone is fine for checking balances and history.
A46: IMPORTANT RULES
A47: Unit sheet = current tenant only | B47: Never keep two tenants mixed on the same unit sheet.
A48: Never delete Archive rows | B48: History is permanent.
A49: Always record M-Pesa refs | B49: Protects you in disputes.
A51: WHEN A TENANT IS EVICTED
A52: Step 1 — Keep recording | B52: Continue entering charges and payments on the unit sheet until the tenancy is closed. Note notice date and eviction date in Remarks.
A53: Step 2 — Final settlement | B53: Add last rent, damages, or costs. Record any final payment. Decide deposit: apply to arrears, refund remainder, or forfeit.
A54: Step 3 — Archive register | B54: On Archive → Closed Tenancies Register: fill Unit, Name, Move-in, Move-out (eviction date), Final Balance, Deposit amounts. Set Reason for Leaving = Eviction.
A55: Step 4 — Archive transactions | B55: Copy all unit sheet transaction rows into Archive Detailed History. Add Unit + Tenant Name on every row. Put date in Archived On.
A56: Step 5 — Notes | B56: In Archive Notes write: notice date, lock/eviction date, and whether arrears are still being pursued or written off.
A57: Step 6 — Clear unit sheet | B57: Delete transaction rows on the unit sheet. Set Deposit Held (L3) to 0. Unit is ready for a new tenant.
A58: Arrears after eviction | B58: If still pursuing: note in Archive. If written off: note the date. Unit sheet balance should return to 0 so Summary stays clean.
A60: UNPAID ARREARS AFTER EVICTION
A61: Common situation | B61: Tenant cannot pay. Eviction is last resort. Arrears remain unpaid.
A62: Unit sheet stays clean | B62: After archiving, clear the unit ledger and set Deposit Held (L3) to 0. Next tenant starts at balance 0. Summary stays accurate.
A63: Record the debt in Archive | B63: Closed Tenancies Register: Final Balance = amount still owed. Reason = Eviction. Arrears Outcome = Written off OR Still pursuing.
A64: Arrears Outcome options | B64: Settled in full | Partial recovery | Written off | Still pursuing | Not applicable
A65: Written off | B65: No further recovery expected. Note the date in Notes. History is kept; unit is free for a new tenant.
A66: Still pursuing | B66: You may follow up later or via an advocate. Note case ref in Notes. Unit sheet still goes to 0.
A67: Deposit | B67: Apply what you can against arrears. Record Deposit Forfeited / Refunded. Remainder of debt stays in Final Balance.
A68: Example Notes | B68: "Evicted 20-Aug-2026. Deposit KSh 5,000 applied to arrears. Balance KSh 32,400 written off. Not pursuing."
A80: PDF AUTOMATION (VBA)
A81: Setup (once) | B81: Open this file in desktop Excel (Windows or Mac). Press Alt+F11 (Option+F11 on Mac).
A82: Add module | B82: In VBA: Insert → Module. Paste ALL of the code block below. Save workbook as .xlsm (macro-enabled).
A83: One tenant PDF | B83: Go to Statement → set yellow B3 to the unit → Alt+F8 → GenerateTenantPDF → Run.
A84: All tenants PDFs | B84: Alt+F8 → GenerateAllTenantPDFs → Run. Creates folder "Statements" next to the file with one PDF per unit.
A85: Where PDFs go | B85: Same folder as the workbook. Filename: Statement_Unit_Tenant_Date.pdf
A86: Google Drive | B86: Upload the PDF to Drive to share with the tenant. Macros do not run on phone.

Sheet A1
A1: Unit A1 — Tenant Statement / Ledger
A2: Select a month to create a Monthly Rent Charge: the date fills as the first day of that month (current year) and description fills automatically. For a payment, leave Month blank and choose Payment Received.
A3: Unit | B3: A1 | C3: Current Rent | D3: 5000 | E3: Garbage | F3: 100 | G3: Current Balance | H3: =IFERROR(LOOKUP(9.99E+307,I6:I32),0) | I3: Tenant | J3: Colins Lugua | K3: Deposit Held | L3: 5000
A4: Current tenant only. When vacating → copy rows to Archive sheet, then clear this ledger.
A5: Date | B5: Month | C5: Description | D5: Tenant | E5: Rent Charged | F5: Garbage Charged | G5: Payment Received | H5: M-Pesa Reference | I5: Running Balance | J5: Remarks
A6: =IF(B6="","",DATE(YEAR(TODAY()),MATCH(B6,{"January","February","March","April","May","June","July","August","September","October","November","December"},0),1)) | B6: March | C6: =IF(B6="","","Monthly Rent Charge") | E6: 7500 | F6: =IF(C6="Monthly Rent Charge",$F$3,"") | I6: =IF(A6="","",IF(C6="Payment Received",-IFERROR(G6,0),IF(C6="Monthly Rent Charge",IFERROR(E6,0)+IFERROR(F6,0),0))) | J6: 5,000 Depo
A7: 46099 | C7: Payment Received | G7: 4900 | H7: UCIF49T5M4 | I7: =IF(A7="","",IF(C7="Payment Received",I6-IFERROR(G7,0),IF(C7="Monthly Rent Charge",I6+IFERROR(E7,0)+IFERROR(F7,0),I6)))
A8: 46103 | C8: Payment Received | G8: 2500 | H8: UCMF4A800A | I8: =IF(A8="","",IF(C8="Payment Received",I7-IFERROR(G8,0),IF(C8="Monthly Rent Charge",I7+IFERROR(E8,0)+IFERROR(F8,0),I7))) | J8: Depo cleared
A9: 46105 | C9: Payment Received | G9: 5000 | H9: UCOF4AG7GA | I9: =IF(A9="","",IF(C9="Payment Received",I8-IFERROR(G9,0),IF(C9="Monthly Rent Charge",I8+IFERROR(E9,0)+IFERROR(F9,0),I8)))
A10: 46113 | B10: April | C10: Monthly Rent Charge | E10: 5000 | F10: 100 | I10: =IF(A10="","",IF(C10="Payment Received",I9-IFERROR(G10,0),IF(C10="Monthly Rent Charge",I9+IFERROR(E10,0)+IFERROR(F10,0),I9)))
A11: 46143 | B11: May | C11: Monthly Rent Charge | E11: 5000 | F11: 100 | I11: =IF(A11="","",IF(C11="Payment Received",I10-IFERROR(G11,0),IF(C11="Monthly Rent Charge",I10+IFERROR(E11,0)+IFERROR(F11,0),I10)))
A12: 46146 | C12: Payment Received | G12: 5000 | H12: UE4F437KW2 | I12: =IF(A12="","",IF(C12="Payment Received",I11-IFERROR(G12,0),IF(C12="Monthly Rent Charge",I11+IFERROR(E12,0)+IFERROR(F12,0),I11)))
A13: 46174 | B13: June | C13: Monthly Rent Charge | E13: =IF(C13="Monthly Rent Charge",$D$3,"") | F13: =IF(C13="Monthly Rent Charge",$F$3,"") | I13: =IF(AND(A13="",C13=""),"",IF(C13="Payment Received",I12-IFERROR(G13,0),IF(C13="Monthly Rent Charge",I12+IFERROR(E13,0)+IFERROR(F13,0),I12)))
A14: 46176 | C14: Payment Received | E14: =IF(C14="Monthly Rent Charge",$D$3,"") | F14: =IF(C14="Monthly Rent Charge",$F$3,"") | G14: 5000 | H14: UF3F46N58H | I14: =IF(AND(A14="",C14=""),"",IF(C14="Payment Received",I13-IFERROR(G14,0),IF(C14="Monthly Rent Charge",I13+IFERROR(E14,0)+IFERROR(F14,0),I13)))
A15: =IF(B15="","",DATE(YEAR(TODAY()),MATCH(B15,{"January","February","March","April","May","June","July","August","September","October","November","December"},0),1)) | B15: July | C15: =IF(B15="","","Monthly Rent Charge") | E15: =IF(C15="Monthly Rent Charge",$D$3,"") | F15: =IF(C15="Monthly Rent Charge",$F$3,"") | I15: =IF(AND(A15="",C15=""),"",IF(C15="Payment Received",I14-IFERROR(G15,0),IF(C15="Monthly Rent Charge",I14+IFERROR(E15,0)+IFERROR(F15,0),I14)))
A16: 46206 | C16: Payment Received | E16: =IF(C16="Monthly Rent Charge",$D$3,"") | F16: =IF(C16="Monthly Rent Charge",$F$3,"") | G16: 5100 | I16: =IF(AND(A16="",C16=""),"",IF(C16="Payment Received",I15-IFERROR(G16,0),IF(C16="Monthly Rent Charge",I15+IFERROR(E16,0)+IFERROR(F16,0),I15)))
A17: =IF(B17="","",DATE(YEAR(TODAY()),MATCH(B17,{"January","February","March","April","May","June","July","August","September","October","November","December"},0),1)) | B17: August | C17: =IF(B17="","","Monthly Rent Charge") | E17: =IF(C17="Monthly Rent Charge",$D$3,"") | F17: =IF(C17="Monthly Rent Charge",$F$3,"") | I17: =IF(AND(A17="",C17=""),"",IF(C17="Payment Received",I16-IFERROR(G17,0),IF(C17="Monthly Rent Charge",I16+IFERROR(E17,0)+IFERROR(F17,0),I16)))
A18: =IF(B18="","",DATE(YEAR(TODAY()),MATCH(B18,{"January","February","March","April","May","June","July","August","September","October","November","December"},0),1)) | C18: =IF(B18="","","Monthly Rent Charge") | E18: =IF(C18="Monthly Rent Charge",$D$3,"") | F18: =IF(C18="Monthly Rent Charge",$F$3,"") | I18: =IF(AND(A18="",C18=""),"",IF(C18="Payment Received",I17-IFERROR(G18,0),IF(C18="Monthly Rent Charge",I17+IFERROR(E18,0)+IFERROR(F18,0),IFERROR(I17,0))))
A19: =IF(B19="","",DATE(YEAR(TODAY()),MATCH(B19,{"January","February","March","April","May","June","July","August","September","October","November","December"},0),1)) | C19: =IF(B19="","","Monthly Rent Charge") | E19: =IF(C19="Monthly Rent Charge",$D$3,"") | F19: =IF(C19="Monthly Rent Charge",$F$3,"") | I19: =IF(AND(A19="",C19=""),"",IF(C19="Payment Received",I18-IFERROR(G19,0),IF(C19="Monthly Rent Charge",I18+IFERROR(E19,0)+IFERROR(F19,0),IFERROR(I18,0))))
A20: =IF(B20="","",DATE(YEAR(TODAY()),MATCH(B20,{"January","February","March","April","May","June","July","August","September","October","November","December"},0),1)) | C20: =IF(B20="","","Monthly Rent Charge") | E20: =IF(C20="Monthly Rent Charge",$D$3,"") | F20: =IF(C20="Monthly Rent Charge",$F$3,"") | I20: =IF(AND(A20="",C20=""),"",IF(C20="Payment Received",I19-IFERROR(G20,0),IF(C20="Monthly Rent Charge",I19+IFERROR(E20,0)+IFERROR(F20,0),IFERROR(I19,0))))
A21: =IF(B21="","",DATE(YEAR(TODAY()),MATCH(B21,{"January","February","March","April","May","June","July","August","September","October","November","December"},0),1)) | C21: =IF(B21="","","Monthly Rent Charge") | E21: =IF(C21="Monthly Rent Charge",$D$3,"") | F21: =IF(C21="Monthly Rent Charge",$F$3,"") | I21: =IF(AND(A21="",C21=""),"",IF(C21="Payment Received",I20-IFERROR(G21,0),IF(C21="Monthly Rent Charge",I20+IFERROR(E21,0)+IFERROR(F21,0),IFERROR(I20,0))))
A22: =IF(B22="","",DATE(YEAR(TODAY()),MATCH(B22,{"January","February","March","April","May","June","July","August","September","October","November","December"},0),1)) | C22: =IF(B22="","","Monthly Rent Charge") | E22: =IF(C22="Monthly Rent Charge",$D$3,"") | F22: =IF(C22="Monthly Rent Charge",$F$3,"") | I22: =IF(AND(A22="",C22=""),"",IF(C22="Payment Received",I21-IFERROR(G22,0),IF(C22="Monthly Rent Charge",I21+IFERROR(E22,0)+IFERROR(F22,0),IFERROR(I21,0))))
A23: =IF(B23="","",DATE(YEAR(TODAY()),MATCH(B23,{"January","February","March","April","May","June","July","August","September","October","November","December"},0),1)) | C23: =IF(B23="","","Monthly Rent Charge") | E23: =IF(C23="Monthly Rent Charge",$D$3,"") | F23: =IF(C23="Monthly Rent Charge",$F$3,"") | I23: =IF(AND(A23="",C23=""),"",IF(C23="Payment Received",I22-IFERROR(G23,0),IF(C23="Monthly Rent Charge",I22+IFERROR(E23,0)+IFERROR(F23,0),IFERROR(I22,0))))
A24: =IF(B24="","",DATE(YEAR(TODAY()),MATCH(B24,{"January","February","March","April","May","June","July","August","September","October","November","December"},0),1)) | C24: =IF(B24="","","Monthly Rent Charge") | E24: =IF(C24="Monthly Rent Charge",$D$3,"") | F24: =IF(C24="Monthly Rent Charge",$F$3,"") | I24: =IF(AND(A24="",C24=""),"",IF(C24="Payment Received",I23-IFERROR(G24,0),IF(C24="Monthly Rent Charge",I23+IFERROR(E24,0)+IFERROR(F24,0),IFERROR(I23,0))))
A25: =IF(B25="","",DATE(YEAR(TODAY()),MATCH(B25,{"January","February","March","April","May","June","July","August","September","October","November","December"},0),1)) | C25: =IF(B25="","","Monthly Rent Charge") | E25: =IF(C25="Monthly Rent Charge",$D$3,"") | F25: =IF(C25="Monthly Rent Charge",$F$3,"") | I25: =IF(AND(A25="",C25=""),"",IF(C25="Payment Received",I24-IFERROR(G25,0),IF(C25="Monthly Rent Charge",I24+IFERROR(E25,0)+IFERROR(F25,0),IFERROR(I24,0))))
A26: =IF(B26="","",DATE(YEAR(TODAY()),MATCH(B26,{"January","February","March","April","May","June","July","August","September","October","November","December"},0),1)) | C26: =IF(B26="","","Monthly Rent Charge") | E26: =IF(C26="Monthly Rent Charge",$D$3,"") | F26: =IF(C26="Monthly Rent Charge",$F$3,"") | I26: =IF(AND(A26="",C26=""),"",IF(C26="Payment Received",I25-IFERROR(G26,0),IF(C26="Monthly Rent Charge",I25+IFERROR(E26,0)+IFERROR(F26,0),IFERROR(I25,0))))
A27: =IF(B27="","",DATE(YEAR(TODAY()),MATCH(B27,{"January","February","March","April","May","June","July","August","September","October","November","December"},0),1)) | C27: =IF(B27="","","Monthly Rent Charge") | E27: =IF(C27="Monthly Rent Charge",$D$3,"") | F27: =IF(C27="Monthly Rent Charge",$F$3,"") | I27: =IF(AND(A27="",C27=""),"",IF(C27="Payment Received",I26-IFERROR(G27,0),IF(C27="Monthly Rent Charge",I26+IFERROR(E27,0)+IFERROR(F27,0),IFERROR(I26,0))))
A28: =IF(B28="","",DATE(YEAR(TODAY()),MATCH(B28,{"January","February","March","April","May","June","July","August","September","October","November","December"},0),1)) | C28: =IF(B28="","","Monthly Rent Charge") | E28: =IF(C28="Monthly Rent Charge",$D$3,"") | F28: =IF(C28="Monthly Rent Charge",$F$3,"") | I28: =IF(AND(A28="",C28=""),"",IF(C28="Payment Received",I27-IFERROR(G28,0),IF(C28="Monthly Rent Charge",I27+IFERROR(E28,0)+IFERROR(F28,0),IFERROR(I27,0))))
A29: =IF(B29="","",DATE(YEAR(TODAY()),MATCH(B29,{"January","February","March","April","May","June","July","August","September","October","November","December"},0),1)) | C29: =IF(B29="","","Monthly Rent Charge") | E29: =IF(C29="Monthly Rent Charge",$D$3,"") | F29: =IF(C29="Monthly Rent Charge",$F$3,"") | I29: =IF(AND(A29="",C29=""),"",IF(C29="Payment Received",I28-IFERROR(G29,0),IF(C29="Monthly Rent Charge",I28+IFERROR(E29,0)+IFERROR(F29,0),IFERROR(I28,0))))
... A32: =IF(B32="","",DATE(YEAR(TODAY()),MATCH(B32,{"January","February","March","April","May","June","July","August","September","October","November","December"},0),1)) | C32: =IF(B32="","","Monthly Rent Charge") | E32: =IF(C32="Monthly Rent Charge",$D$3,"") | F32: =IF(C32="Monthly Rent Charge",$F$3,"") | I32: =IF(AND(A32="",C32=""),"",IF(C32="Payment Received",I31-IFERROR(G32,0),IF(C32="Monthly Rent Charge",I31+IFERROR(E32,0)+IFERROR(F32,0),IFERROR(I31,0))))

Sheet A2
A1: Unit A2 — Tenant Statement / Ledger
A2: Select a month to create a Monthly Rent Charge: the date fills as the first day of that month (current year) and description fills automatically. For a payment, leave Month blank and choose Payment Received.
A3: Unit | B3: A2 | C3: Current Rent | D3: 4500 | E3: Garbage | F3: 0 | G3: Current Balance | H3: =IFERROR(LOOKUP(9.99E+307,I6:I75),0) | I3: Tenant | J3: KATIWA KAMENE | K3: Deposit Held | L3: 0
A4: Current tenant only. When vacating → copy rows to Archive sheet, then clear this ledger.
A5: Date | B5: Month | C5: Description | D5: Tenant | E5: Rent Charged | F5: Garbage Charged | G5: Payment Received | H5: M-Pesa Reference | I5: Running Balance | J5: Remarks
A6: 45413 | B6: May | C6: Monthly Rent Charge | E6: =IF(C6="Monthly Rent Charge",$D$3,"") | F6: =IF(C6="Monthly Rent Charge",$F$3,"") | I6: =IF(A6="","",IF(C6="Payment Received",-IFERROR(G6,0),IF(C6="Monthly Rent Charge",IFERROR(E6,0)+IFERROR(F6,0),0)))
A7: 45417 | C7: Payment Received | E7: =IF(C7="Monthly Rent Charge",$D$3,"") | F7: =IF(C7="Monthly Rent Charge",$F$3,"") | G7: 4500 | H7: SE57AGDEVX | I7: =IF(A7="","",IF(C7="Payment Received",I6-IFERROR(G7,0),IF(C7="Monthly Rent Charge",I6+IFERROR(E7,0)+IFERROR(F7,0),I6)))
A8: 45444 | B8: June | C8: Monthly Rent Charge | E8: =IF(C8="Monthly Rent Charge",$D$3,"") | F8: =IF(C8="Monthly Rent Charge",$F$3,"") | I8: =IF(A8="","",IF(C8="Payment Received",I7-IFERROR(G8,0),IF(C8="Monthly Rent Charge",I7+IFERROR(E8,0)+IFERROR(F8,0),I7)))
A9: 45448 | C9: Payment Received | E9: =IF(C9="Monthly Rent Charge",$D$3,"") | F9: =IF(C9="Monthly Rent Charge",$F$3,"") | G9: 4500 | H9: SF54JVEV5Y | I9: =IF(A9="","",IF(C9="Payment Received",I8-IFERROR(G9,0),IF(C9="Monthly Rent Charge",I8+IFERROR(E9,0)+IFERROR(F9,0),I8)))
A10: 45474 | B10: July | C10: =IF(B10="","","Monthly Rent Charge") | E10: =IF(C10="Monthly Rent Charge",$D$3,"") | F10: =IF(C10="Monthly Rent Charge",$F$3,"") | I10: =IF(A10="","",IF(C10="Payment Received",I9-IFERROR(G10,0),IF(C10="Monthly Rent Charge",I9+IFERROR(E10,0)+IFERROR(F10,0),I9)))
A11: 45479 | C11: Payment Received | E11: =IF(C11="Monthly Rent Charge",$D$3,"") | F11: =IF(C11="Monthly Rent Charge",$F$3,"") | G11: 4500 | H11: SG63QGNDV9 | I11: =IF(A11="","",IF(C11="Payment Received",I10-IFERROR(G11,0),IF(C11="Monthly Rent Charge",I10+IFERROR(E11,0)+IFERROR(F11,0),I10)))
A12: 45505 | B12: August | C12: =IF(B12="","","Monthly Rent Charge") | E12: =IF(C12="Monthly Rent Charge",$D$3,"") | F12: =IF(C12="Monthly Rent Charge",$F$3,"") | I12: =IF(A12="","",IF(C12="Payment Received",I11-IFERROR(G12,0),IF(C12="Monthly Rent Charge",I11+IFERROR(E12,0)+IFERROR(F12,0),I11)))
A13: 45510 | C13: Payment Received | E13: =IF(C13="Monthly Rent Charge",$D$3,"") | F13: =IF(C13="Monthly Rent Charge",$F$3,"") | G13: 4500 | H13: SH654CXXY9 | I13: =IF(A13="","",IF(C13="Payment Received",I12-IFERROR(G13,0),IF(C13="Monthly Rent Charge",I12+IFERROR(E13,0)+IFERROR(F13,0),I12)))
A14: 45536 | B14: September | C14: =IF(B14="","","Monthly Rent Charge") | E14: =IF(C14="Monthly Rent Charge",$D$3,"") | F14: =IF(C14="Monthly Rent Charge",$F$3,"") | I14: =IF(A14="","",IF(C14="Payment Received",I13-IFERROR(G14,0),IF(C14="Monthly Rent Charge",I13+IFERROR(E14,0)+IFERROR(F14,0),I13)))
A15: 45542 | C15: Payment Received | E15: =IF(C15="Monthly Rent Charge",$D$3,"") | F15: =IF(C15="Monthly Rent Charge",$F$3,"") | G15: 4500 | H15: SI72PLCW0I | I15: =IF(A15="","",IF(C15="Payment Received",I14-IFERROR(G15,0),IF(C15="Monthly Rent Charge",I14+IFERROR(E15,0)+IFERROR(F15,0),I14)))
A16: 45566 | B16: October | C16: =IF(B16="","","Monthly Rent Charge") | E16: =IF(C16="Monthly Rent Charge",$D$3,"") | F16: =IF(C16="Monthly Rent Charge",$F$3,"") | I16: =IF(A16="","",IF(C16="Payment Received",I15-IFERROR(G16,0),IF(C16="Monthly Rent Charge",I15+IFERROR(E16,0)+IFERROR(F16,0),I15)))
A17: 45571 | C17: Payment Received | E17: =IF(C17="Monthly Rent Charge",$D$3,"") | F17: =IF(C17="Monthly Rent Charge",$F$3,"") | G17: 4500 | H17: SJ643CA9I2 | I17: =IF(A17="","",IF(C17="Payment Received",I16-IFERROR(G17,0),IF(C17="Monthly Rent Charge",I16+IFERROR(E17,0)+IFERROR(F17,0),I16)))
A18: 45597 | B18: November | C18: Monthly Rent Charge | E18: =IF(C18="Monthly Rent Charge",$D$3,"") | F18: =IF(C18="Monthly Rent Charge",$F$3,"") | I18: =IF(A18="","",IF(C18="Payment Received",I17-IFERROR(G18,0),IF(C18="Monthly Rent Charge",I17+IFERROR(E18,0)+IFERROR(F18,0),I17)))
A19: 45602 | C19: Payment Received | E19: =IF(C19="Monthly Rent Charge",$D$3,"") | F19: =IF(C19="Monthly Rent Charge",$F$3,"") | G19: 3000 | H19: SK67U4HX7V | I19: =IF(A19="","",IF(C19="Payment Received",I18-IFERROR(G19,0),IF(C19="Monthly Rent Charge",I18+IFERROR(E19,0)+IFERROR(F19,0),I18)))
A20: 45627 | B20: December | C20: Monthly Rent Charge | E20: =IF(C20="Monthly Rent Charge",$D$3,"") | F20: =IF(C20="Monthly Rent Charge",$F$3,"") | I20: =IF(A20="","",IF(C20="Payment Received",I19-IFERROR(G20,0),IF(C20="Monthly Rent Charge",I19+IFERROR(E20,0)+IFERROR(F20,0),I19)))
A21: 45631 | C21: Payment Received | E21: =IF(C21="Monthly Rent Charge",$D$3,"") | F21: =IF(C21="Monthly Rent Charge",$F$3,"") | G21: 4500 | H21: SL59DSH8KN | I21: =IF(A21="","",IF(C21="Payment Received",I20-IFERROR(G21,0),IF(C21="Monthly Rent Charge",I20+IFERROR(E21,0)+IFERROR(F21,0),I20)))
A22: 45658 | B22: January | C22: Monthly Rent Charge | E22: =IF(C22="Monthly Rent Charge",$D$3,"") | F22: =IF(C22="Monthly Rent Charge",$F$3,"") | I22: =IF(A22="","",IF(C22="Payment Received",I21-IFERROR(G22,0),IF(C22="Monthly Rent Charge",I21+IFERROR(E22,0)+IFERROR(F22,0),I21)))
A23: 45663 | C23: Payment Received | E23: =IF(C23="Monthly Rent Charge",$D$3,"") | F23: =IF(C23="Monthly Rent Charge",$F$3,"") | G23: 4500 | H23: TA608ISC04 | I23: =IF(A23="","",IF(C23="Payment Received",I22-IFERROR(G23,0),IF(C23="Monthly Rent Charge",I22+IFERROR(E23,0)+IFERROR(F23,0),I22)))
A24: 45689 | B24: February | C24: Monthly Rent Charge | E24: =IF(C24="Monthly Rent Charge",$D$3,"") | F24: =IF(C24="Monthly Rent Charge",$F$3,"") | I24: =IF(A24="","",IF(C24="Payment Received",I23-IFERROR(G24,0),IF(C24="Monthly Rent Charge",I23+IFERROR(E24,0)+IFERROR(F24,0),I23)))
A25: 45694 | C25: Payment Received | E25: =IF(C25="Monthly Rent Charge",$D$3,"") | F25: =IF(C25="Monthly Rent Charge",$F$3,"") | G25: 6000 | H25: TB681U2C3U | I25: =IF(A25="","",IF(C25="Payment Received",I24-IFERROR(G25,0),IF(C25="Monthly Rent Charge",I24+IFERROR(E25,0)+IFERROR(F25,0),I24)))
A26: 45717 | B26: March | C26: Monthly Rent Charge | E26: =IF(C26="Monthly Rent Charge",$D$3,"") | F26: =IF(C26="Monthly Rent Charge",$F$3,"") | I26: =IF(A26="","",IF(C26="Payment Received",I25-IFERROR(G26,0),IF(C26="Monthly Rent Charge",I25+IFERROR(E26,0)+IFERROR(F26,0),I25)))
A27: 45727 | C27: Payment Received | E27: =IF(C27="Monthly Rent Charge",$D$3,"") | F27: =IF(C27="Monthly Rent Charge",$F$3,"") | G27: 4500 | H27: TCB6808HS0 | I27: =IF(A27="","",IF(C27="Payment Received",I26-IFERROR(G27,0),IF(C27="Monthly Rent Charge",I26+IFERROR(E27,0)+IFERROR(F27,0),I26)))
A28: 45748 | B28: April | C28: Monthly Rent Charge | E28: =IF(C28="Monthly Rent Charge",$D$3,"") | F28: =IF(C28="Monthly Rent Charge",$F$3,"") | I28: =IF(A28="","",IF(C28="Payment Received",I27-IFERROR(G28,0),IF(C28="Monthly Rent Charge",I27+IFERROR(E28,0)+IFERROR(F28,0),I27)))
A29: 45754 | C29: Payment Received | E29: =IF(C29="Monthly Rent Charge",$D$3,"") | F29: =IF(C29="Monthly Rent Charge",$F$3,"") | G29: 4500 | H29: TD73T0MGB1 | I29: =IF(A29="","",IF(C29="Payment Received",I28-IFERROR(G29,0),IF(C29="Monthly Rent Charge",I28+IFERROR(E29,0)+IFERROR(F29,0),I28)))
A30: 45778 | B30: May | C30: Monthly Rent Charge | E30: =IF(C30="Monthly Rent Charge",$D$3,"") | F30: =IF(C30="Monthly Rent Charge",$F$3,"") | I30: =IF(A30="","",IF(C30="Payment Received",I29-IFERROR(G30,0),IF(C30="Monthly Rent Charge",I29+IFERROR(E30,0)+IFERROR(F30,0),I29)))
A31: 45782 | C31: Payment Received | E31: =IF(C31="Monthly Rent Charge",$D$3,"") | F31: =IF(C31="Monthly Rent Charge",$F$3,"") | G31: 4500 | H31: TE58KFI578 | I31: =IF(A31="","",IF(C31="Payment Received",I30-IFERROR(G31,0),IF(C31="Monthly Rent Charge",I30+IFERROR(E31,0)+IFERROR(F31,0),I30)))
A32: 45809 | B32: June | C32: Monthly Rent Charge | E32: =IF(C32="Monthly Rent Charge",$D$3,"") | F32: =IF(C32="Monthly Rent Charge",$F$3,"") | I32: =IF(A32="","",IF(C32="Payment Received",I31-IFERROR(G32,0),IF(C32="Monthly Rent Charge",I31+IFERROR(E32,0)+IFERROR(F32,0),I31)))
A33: 45815 | C33: Payment Received | E33: =IF(C33="Monthly Rent Charge",$D$3,"") | F33: =IF(C33="Monthly Rent Charge",$F$3,"") | G33: 4500 | H33: TF71YMZMWL | I33: =IF(A33="","",IF(C33="Payment Received",I32-IFERROR(G33,0),IF(C33="Monthly Rent Charge",I32+IFERROR(E33,0)+IFERROR(F33,0),I32)))
A34: 45839 | B34: July | C34: Monthly Rent Charge | E34: =IF(C34="Monthly Rent Charge",$D$3,"") | F34: =IF(C34="Monthly Rent Charge",$F$3,"") | I34: =IF(A34="","",IF(C34="Payment Received",I33-IFERROR(G34,0),IF(C34="Monthly Rent Charge",I33+IFERROR(E34,0)+IFERROR(F34,0),I33)))
A35: 45845 | C35: Payment Received | E35: =IF(C35="Monthly Rent Charge",$D$3,"") | F35: =IF(C35="Monthly Rent Charge",$F$3,"") | G35: 4500 | H35: TG74ZQPORC | I35: =IF(A35="","",IF(C35="Payment Received",I34-IFERROR(G35,0),IF(C35="Monthly Rent Charge",I34+IFERROR(E35,0)+IFERROR(F35,0),I34)))
A36: 45870 | B36: August | C36: Monthly Rent Charge | E36: =IF(C36="Monthly Rent Charge",$D$3,"") | F36: =IF(C36="Monthly Rent Charge",$F$3,"") | I36: =IF(A36="","",IF(C36="Payment Received",I35-IFERROR(G36,0),IF(C36="Monthly Rent Charge",I35+IFERROR(E36,0)+IFERROR(F36,0),I35)))
A37: 45874 | C37: Payment Received | E37: =IF(C37="Monthly Rent Charge",$D$3,"") | F37: =IF(C37="Monthly Rent Charge",$F$3,"") | G37: 4500 | H37: TH503DKKO4 | I37: =IF(A37="","",IF(C37="Payment Received",I36-IFERROR(G37,0),IF(C37="Monthly Rent Charge",I36+IFERROR(E37,0)+IFERROR(F37,0),I36)))
A38: 45901 | B38: September | C38: Monthly Rent Charge | E38: =IF(C38="Monthly Rent Charge",$D$3,"") | F38: =IF(C38="Monthly Rent Charge",$F$3,"") | I38: =IF(A38="","",IF(C38="Payment Received",I37-IFERROR(G38,0),IF(C38="Monthly Rent Charge",I37+IFERROR(E38,0)+IFERROR(F38,0),I37)))
A39: 45906 | C39: Payment Received | E39: =IF(C39="Monthly Rent Charge",$D$3,"") | F39: =IF(C39="Monthly Rent Charge",$F$3,"") | G39: 4500 | H39: TI61MELPOJ | I39: =IF(A39="","",IF(C39="Payment Received",I38-IFERROR(G39,0),IF(C39="Monthly Rent Charge",I38+IFERROR(E39,0)+IFERROR(F39,0),I38)))
A40: 45931 | B40: October | C40: Monthly Rent Charge | E40: =IF(C40="Monthly Rent Charge",$D$3,"") | F40: =IF(C40="Monthly Rent Charge",$F$3,"") | I40: =IF(A40="","",IF(C40="Payment Received",I39-IFERROR(G40,0),IF(C40="Monthly Rent Charge",I39+IFERROR(E40,0)+IFERROR(F40,0),I39)))
A41: 45935 | C41: Payment Received | E41: =IF(C41="Monthly Rent Charge",$D$3,"") | F41: =IF(C41="Monthly Rent Charge",$F$3,"") | G41: 4500 | H41: TJ55A6NB9I | I41: =IF(A41="","",IF(C41="Payment Received",I40-IFERROR(G41,0),IF(C41="Monthly Rent Charge",I40+IFERROR(E41,0)+IFERROR(F41,0),I40)))
A42: 45962 | B42: November | C42: Monthly Rent Charge | E42: =IF(C42="Monthly Rent Charge",$D$3,"") | F42: =IF(C42="Monthly Rent Charge",$F$3,"") | I42: =IF(A42="","",IF(C42="Payment Received",I41-IFERROR(G42,0),IF(C42="Monthly Rent Charge",I41+IFERROR(E42,0)+IFERROR(F42,0),I41)))
A43: 45967 | C43: Payment Received | E43: =IF(C43="Monthly Rent Charge",$D$3,"") | F43: =IF(C43="Monthly Rent Charge",$F$3,"") | G43: 4500 | H43: TK65A9JNEM | I43: =IF(A43="","",IF(C43="Payment Received",I42-IFERROR(G43,0),IF(C43="Monthly Rent Charge",I42+IFERROR(E43,0)+IFERROR(F43,0),I42)))
A44: 45992 | B44: December | C44: Monthly Rent Charge | E44: =IF(C44="Monthly Rent Charge",$D$3,"") | F44: =IF(C44="Monthly Rent Charge",$F$3,"") | I44: =IF(A44="","",IF(C44="Payment Received",I43-IFERROR(G44,0),IF(C44="Monthly Rent Charge",I43+IFERROR(E44,0)+IFERROR(F44,0),I43)))
A45: 46000 | C45: Payment Received | E45: =IF(C45="Monthly Rent Charge",$D$3,"") | F45: =IF(C45="Monthly Rent Charge",$F$3,"") | G45: 3000 | H45: TL95A0N451 | I45: =IF(A45="","",IF(C45="Payment Received",I44-IFERROR(G45,0),IF(C45="Monthly Rent Charge",I44+IFERROR(E45,0)+IFERROR(F45,0),I44)))
A46: 46023 | B46: January | C46: Monthly Rent Charge | E46: =IF(C46="Monthly Rent Charge",$D$3,"") | F46: =IF(C46="Monthly Rent Charge",$F$3,"") | I46: =IF(A46="","",IF(C46="Payment Received",I45-IFERROR(G46,0),IF(C46="Monthly Rent Charge",I45+IFERROR(E46,0)+IFERROR(F46,0),I45)))
A47: 46029 | C47: Payment Received | E47: =IF(C47="Monthly Rent Charge",$D$3,"") | F47: =IF(C47="Monthly Rent Charge",$F$3,"") | G47: 4500 | H47: UA75A3BV4U | I47: =IF(A47="","",IF(C47="Payment Received",I46-IFERROR(G47,0),IF(C47="Monthly Rent Charge",I46+IFERROR(E47,0)+IFERROR(F47,0),I46)))
A48: 46054 | B48: February | C48: Monthly Rent Charge | E48: =IF(C48="Monthly Rent Charge",$D$3,"") | F48: =IF(C48="Monthly Rent Charge",$F$3,"") | I48: =IF(A48="","",IF(C48="Payment Received",I47-IFERROR(G48,0),IF(C48="Monthly Rent Charge",I47+IFERROR(E48,0)+IFERROR(F48,0),I47)))
A49: 46060 | C49: Payment Received | E49: =IF(C49="Monthly Rent Charge",$D$3,"") | F49: =IF(C49="Monthly Rent Charge",$F$3,"") | G49: 4500 | H49: UB75A69STV | I49: =IF(A49="","",IF(C49="Payment Received",I48-IFERROR(G49,0),IF(C49="Monthly Rent Charge",I48+IFERROR(E49,0)+IFERROR(F49,0),I48)))
A50: 46082 | B50: March | C50: Monthly Rent Charge | E50: =IF(C50="Monthly Rent Charge",$D$3,"") | F50: =IF(C50="Monthly Rent Charge",$F$3,"") | I50: =IF(A50="","",IF(C50="Payment Received",I49-IFERROR(G50,0),IF(C50="Monthly Rent Charge",I49+IFERROR(E50,0)+IFERROR(F50,0),I49)))
A51: 46088 | C51: Payment Received | E51: =IF(C51="Monthly Rent Charge",$D$3,"") | F51: =IF(C51="Monthly Rent Charge",$F$3,"") | G51: 6000 | H51: UC75A8Z2ZV | I51: =IF(A51="","",IF(C51="Payment Received",I50-IFERROR(G51,0),IF(C51="Monthly Rent Charge",I50+IFERROR(E51,0)+IFERROR(F51,0),I50)))
A52: 46113 | B52: April | C52: Monthly Rent Charge | E52: =IF(C52="Monthly Rent Charge",$D$3,"") | F52: =IF(C52="Monthly Rent Charge",$F$3,"") | I52: =IF(A52="","",IF(C52="Payment Received",I51-IFERROR(G52,0),IF(C52="Monthly Rent Charge",I51+IFERROR(E52,0)+IFERROR(F52,0),I51)))
A53: 46118 | C53: Payment Received | E53: =IF(C53="Monthly Rent Charge",$D$3,"") | F53: =IF(C53="Monthly Rent Charge",$F$3,"") | G53: 4500 | H53: UD65A0771S | I53: =IF(A53="","",IF(C53="Payment Received",I52-IFERROR(G53,0),IF(C53="Monthly Rent Charge",I52+IFERROR(E53,0)+IFERROR(F53,0),I52)))
A54: =IF(B54="","",DATE(YEAR(TODAY()),MATCH(B54,{"January","February","March","April","May","June","July","August","September","October","November","December"},0),1)) | B54: May | C54: =IF(B54="","","Monthly Rent Charge") | E54: =IF(C54="Monthly Rent Charge",$D$3,"") | F54: =IF(C54="Monthly Rent Charge",$F$3,"") | I54: =IF(A54="","",IF(C54="Payment Received",I53-IFERROR(G54,0),IF(C54="Monthly Rent Charge",I53+IFERROR(E54,0)+IFERROR(F54,0),I53)))
A55: 46145 | C55: Payment Received | E55: =IF(C55="Monthly Rent Charge",$D$3,"") | F55: =IF(C55="Monthly Rent Charge",$F$3,"") | G55: 4500 | H55: UE35A3DTAF | I55: =IF(A55="","",IF(C55="Payment Received",I54-IFERROR(G55,0),IF(C55="Monthly Rent Charge",I54+IFERROR(E55,0)+IFERROR(F55,0),I54)))
A56: =IF(B56="","",DATE(YEAR(TODAY()),MATCH(B56,{"January","February","March","April","May","June","July","August","September","October","November","December"},0),1)) | B56: June | C56: =IF(B56="","","Monthly Rent Charge") | E56: =IF(C56="Monthly Rent Charge",$D$3,"") | F56: =IF(C56="Monthly Rent Charge",$F$3,"") | I56: =IF(AND(A56="",C56=""),"",IF(C56="Payment Received",I55-IFERROR(G56,0),IF(C56="Monthly Rent Charge",I55+IFERROR(E56,0)+IFERROR(F56,0),I55)))
A57: 46180 | C57: Payment Received | E57: =IF(C57="Monthly Rent Charge",$D$3,"") | F57: =IF(C57="Monthly Rent Charge",$F$3,"") | G57: 4500 | H57: UF75A7H5IT | I57: =IF(AND(A57="",C57=""),"",IF(C57="Payment Received",I56-IFERROR(G57,0),IF(C57="Monthly Rent Charge",I56+IFERROR(E57,0)+IFERROR(F57,0),I56)))
A58: =IF(B58="","",DATE(YEAR(TODAY()),MATCH(B58,{"January","February","March","April","May","June","July","August","September","October","November","December"},0),1)) | B58: July | C58: =IF(B58="","","Monthly Rent Charge") | E58: =IF(C58="Monthly Rent Charge",$D$3,"") | F58: =IF(C58="Monthly Rent Charge",$F$3,"") | I58: =IF(AND(A58="",C58=""),"",IF(C58="Payment Received",I57-IFERROR(G58,0),IF(C58="Monthly Rent Charge",I57+IFERROR(E58,0)+IFERROR(F58,0),I57)))
A59: 46209 | C59: Payment Received | E59: =IF(C59="Monthly Rent Charge",$D$3,"") | F59: =IF(C59="Monthly Rent Charge",$F$3,"") | G59: 4500 | H59: UG65AATKKN4 | I59: =IF(AND(A59="",C59=""),"",IF(C59="Payment Received",I58-IFERROR(G59,0),IF(C59="Monthly Rent Charge",I58+IFERROR(E59,0)+IFERROR(F59,0),I58)))
A60: =IF(B60="","",DATE(YEAR(TODAY()),MATCH(B60,{"January","February","March","April","May","June","July","August","September","October","November","December"},0),1)) | B60: August | C60: =IF(B60="","","Monthly Rent Charge") | E60: =IF(C60="Monthly Rent Charge",$D$3,"") | F60: =IF(C60="Monthly Rent Charge",$F$3,"") | I60: =IF(AND(A60="",C60=""),"",IF(C60="Payment Received",I59-IFERROR(G60,0),IF(C60="Monthly Rent Charge",I59+IFERROR(E60,0)+IFERROR(F60,0),I59)))
A61: 46237 | C61: Payment Received | E61: =IF(C61="Monthly Rent Charge",$D$3,"") | F61: =IF(C61="Monthly Rent Charge",$F$3,"") | G61: 4500 | H61: UH35A27V6D | I61: =IF(AND(A61="",C61=""),"",IF(C61="Payment Received",I60-IFERROR(G61,0),IF(C61="Monthly Rent Charge",I60+IFERROR(E61,0)+IFERROR(F61,0),IFERROR(I60,0))))
C62: =IF(B62="","","Monthly Rent Charge") | E62: =IF(C62="Monthly Rent Charge",$D$3,"") | F62: =IF(C62="Monthly Rent Charge",$F$3,"") | I62: =IF(AND(A62="",C62=""),"",IF(C62="Payment Received",I61-IFERROR(G62,0),IF(C62="Monthly Rent Charge",I61+IFERROR(E62,0)+IFERROR(F62,0),IFERROR(I61,0))))
A63: =IF(B63="","",DATE(YEAR(TODAY()),MATCH(B63,{"January","February","March","April","May","June","July","August","September","October","November","December"},0),1)) | C63: =IF(B63="","","Monthly Rent Charge") | E63: =IF(C63="Monthly Rent Charge",$D$3,"") | F63: =IF(C63="Monthly Rent Charge",$F$3,"") | I63: =IF(AND(A63="",C63=""),"",IF(C63="Payment Received",I62-IFERROR(G63,0),IF(C63="Monthly Rent Charge",I62+IFERROR(E63,0)+IFERROR(F63,0),IFERROR(I62,0))))
A64: =IF(B64="","",DATE(YEAR(TODAY()),MATCH(B64,{"January","February","March","April","May","June","July","August","September","October","November","December"},0),1)) | C64: =IF(B64="","","Monthly Rent Charge") | E64: =IF(C64="Monthly Rent Charge",$D$3,"") | F64: =IF(C64="Monthly Rent Charge",$F$3,"") | I64: =IF(AND(A64="",C64=""),"",IF(C64="Payment Received",I63-IFERROR(G64,0),IF(C64="Monthly Rent Charge",I63+IFERROR(E64,0)+IFERROR(F64,0),IFERROR(I63,0))))
A65: =IF(B65="","",DATE(YEAR(TODAY()),MATCH(B65,{"January","February","March","April","May","June","July","August","September","October","November","December"},0),1)) | C65: =IF(B65="","","Monthly Rent Charge") | E65: =IF(C65="Monthly Rent Charge",$D$3,"") | F65: =IF(C65="Monthly Rent Charge",$F$3,"") | I65: =IF(AND(A65="",C65=""),"",IF(C65="Payment Received",I64-IFERROR(G65,0),IF(C65="Monthly Rent Charge",I64+IFERROR(E65,0)+IFERROR(F65,0),IFERROR(I64,0))))
A66: =IF(B66="","",DATE(YEAR(TODAY()),MATCH(B66,{"January","February","March","April","May","June","July","August","September","October","November","December"},0),1)) | C66: =IF(B66="","","Monthly Rent Charge") | E66: =IF(C66="Monthly Rent Charge",$D$3,"") | F66: =IF(C66="Monthly Rent Charge",$F$3,"") | I66: =IF(AND(A66="",C66=""),"",IF(C66="Payment Received",I65-IFERROR(G66,0),IF(C66="Monthly Rent Charge",I65+IFERROR(E66,0)+IFERROR(F66,0),IFERROR(I65,0))))
A67: =IF(B67="","",DATE(YEAR(TODAY()),MATCH(B67,{"January","February","March","April","May","June","July","August","September","October","November","December"},0),1)) | C67: =IF(B67="","","Monthly Rent Charge") | E67: =IF(C67="Monthly Rent Charge",$D$3,"") | F67: =IF(C67="Monthly Rent Charge",$F$3,"") | I67: =IF(AND(A67="",C67=""),"",IF(C67="Payment Received",I66-IFERROR(G67,0),IF(C67="Monthly Rent Charge",I66+IFERROR(E67,0)+IFERROR(F67,0),IFERROR(I66,0))))
A68: =IF(B68="","",DATE(YEAR(TODAY()),MATCH(B68,{"January","February","March","April","May","June","July","August","September","October","November","December"},0),1)) | C68: =IF(B68="","","Monthly Rent Charge") | E68: =IF(C68="Monthly Rent Charge",$D$3,"") | F68: =IF(C68="Monthly Rent Charge",$F$3,"") | I68: =IF(AND(A68="",C68=""),"",IF(C68="Payment Received",I67-IFERROR(G68,0),IF(C68="Monthly Rent Charge",I67+IFERROR(E68,0)+IFERROR(F68,0),IFERROR(I67,0))))
A69: =IF(B69="","",DATE(YEAR(TODAY()),MATCH(B69,{"January","February","March","April","May","June","July","August","September","October","November","December"},0),1)) | C69: =IF(B69="","","Monthly Rent Charge") | E69: =IF(C69="Monthly Rent Charge",$D$3,"") | F69: =IF(C69="Monthly Rent Charge",$F$3,"") | I69: =IF(AND(A69="",C69=""),"",IF(C69="Payment Received",I68-IFERROR(G69,0),IF(C69="Monthly Rent Charge",I68+IFERROR(E69,0)+IFERROR(F69,0),IFERROR(I68,0))))
A70: =IF(B70="","",DATE(YEAR(TODAY()),MATCH(B70,{"January","February","March","April","May","June","July","August","September","October","November","December"},0),1)) | C70: =IF(B70="","","Monthly Rent Charge") | E70: =IF(C70="Monthly Rent Charge",$D$3,"") | F70: =IF(C70="Monthly Rent Charge",$F$3,"") | I70: =IF(AND(A70="",C70=""),"",IF(C70="Payment Received",I69-IFERROR(G70,0),IF(C70="Monthly Rent Charge",I69+IFERROR(E70,0)+IFERROR(F70,0),IFERROR(I69,0))))
A71: =IF(B71="","",DATE(YEAR(TODAY()),MATCH(B71,{"January","February","March","April","May","June","July","August","September","October","November","December"},0),1)) | C71: =IF(B71="","","Monthly Rent Charge") | E71: =IF(C71="Monthly Rent Charge",$D$3,"") | F71: =IF(C71="Monthly Rent Charge",$F$3,"") | I71: =IF(AND(A71="",C71=""),"",IF(C71="Payment Received",I70-IFERROR(G71,0),IF(C71="Monthly Rent Charge",I70+IFERROR(E71,0)+IFERROR(F71,0),IFERROR(I70,0))))
A72: =IF(B72="","",DATE(YEAR(TODAY()),MATCH(B72,{"January","February","March","April","May","June","July","August","September","October","November","December"},0),1)) | C72: =IF(B72="","","Monthly Rent Charge") | E72: =IF(C72="Monthly Rent Charge",$D$3,"") | F72: =IF(C72="Monthly Rent Charge",$F$3,"") | I72: =IF(AND(A72="",C72=""),"",IF(C72="Payment Received",I71-IFERROR(G72,0),IF(C72="Monthly Rent Charge",I71+IFERROR(E72,0)+IFERROR(F72,0),IFERROR(I71,0))))
A73: =IF(B73="","",DATE(YEAR(TODAY()),MATCH(B73,{"January","February","March","April","May","June","July","August","September","October","November","December"},0),1)) | C73: =IF(B73="","","Monthly Rent Charge") | E73: =IF(C73="Monthly Rent Charge",$D$3,"") | F73: =IF(C73="Monthly Rent Charge",$F$3,"") | I73: =IF(AND(A73="",C73=""),"",IF(C73="Payment Received",I72-IFERROR(G73,0),IF(C73="Monthly Rent Charge",I72+IFERROR(E73,0)+IFERROR(F73,0),IFERROR(I72,0))))
A74: =IF(B74="","",DATE(YEAR(TODAY()),MATCH(B74,{"January","February","March","April","May","June","July","August","September","October","November","December"},0),1)) | C74: =IF(B74="","","Monthly Rent Charge") | E74: =IF(C74="Monthly Rent Charge",$D$3,"") | F74: =IF(C74="Monthly Rent Charge",$F$3,"") | I74: =IF(AND(A74="",C74=""),"",IF(C74="Payment Received",I73-IFERROR(G74,0),IF(C74="Monthly Rent Charge",I73+IFERROR(E74,0)+IFERROR(F74,0),IFERROR(I73,0))))
A75: =IF(B75="","",DATE(YEAR(TODAY()),MATCH(B75,{"January","February","March","April","May","June","July","August","September","October","November","December"},0),1)) | C75: =IF(B75="","","Monthly Rent Charge") | E75: =IF(C75="Monthly Rent Charge",$D$3,"") | F75: =IF(C75="Monthly Rent Charge",$F$3,"") | I75: =IF(AND(A75="",C75=""),"",IF(C75="Payment Received",I74-IFERROR(G75,0),IF(C75="Monthly Rent Charge",I74+IFERROR(E75,0)+IFERROR(F75,0),IFERROR(I74,0))))
A220: =IF(B220="","",DATE(YEAR(TODAY()),MATCH(B220,{"January","February","March","April","May","June","July","August","September","October","November","December"},0),1)) | C220: =IF(B220="","","Monthly Rent Charge") | E220: =IF(C220="Monthly Rent Charge",$D$3,"") | F220: =IF(C220="Monthly Rent Charge",$F$3,"") | I220: =IF(A220="","",IF(C220="Payment Received",I219-IFERROR(G220,0),IF(C220="Monthly Rent Charge",I219+IFERROR(E220,0)+IFERROR(F220,0),I219)))

Sheet A3
A1: Unit A3 — Tenant Statement / Ledger
A2: Select a month to create a Monthly Rent Charge: the date fills as the first day of that month (current year) and description fills automatically. For a payment, leave Month blank and choose Payment Received.
A3: Unit | B3: A3 | C3: Current Rent | D3: 4500 | E3: Garbage | F3: 200 | G3: Current Balance | H3: =IFERROR(LOOKUP(9.99E+307,I6:I33),0) | I3: Tenant | J3: Shaline Chepkirui/HILARY | K3: Deposit Held | L3: 4500
A4: Current tenant only. When vacating → copy rows to Archive sheet, then clear this ledger.
A5: Date | B5: Month | C5: Description | D5: Tenant | E5: Rent Charged | F5: Garbage Charged | G5: Payment Received | H5: M-Pesa Reference | I5: Running Balance | J5: Remarks
A6: =IF(B6="","",DATE(YEAR(TODAY()),MATCH(B6,{"January","February","March","April","May","June","July","August","September","October","November","December"},0),1)) | B6: January | C6: =IF(B6="","","Monthly Rent Charge") | E6: =IF(C6="Monthly Rent Charge",$D$3,"") | F6: =IF(C6="Monthly Rent Charge",$F$3,"") | I6: =IF(A6="","",IF(C6="Payment Received",-IFERROR(G6,0),IF(C6="Monthly Rent Charge",IFERROR(E6,0)+IFERROR(F6,0),0))) | J6: Depo c/f from previous tenant
A7: 46035 | C7: Payment Received | E7: =IF(C7="Monthly Rent Charge",$D$3,"") | F7: =IF(C7="Monthly Rent Charge",$F$3,"") | G7: 4500 | H7: UADFU3JC98 | I7: =IF(A7="","",IF(C7="Payment Received",I6-IFERROR(G7,0),IF(C7="Monthly Rent Charge",I6+IFERROR(E7,0)+IFERROR(F7,0),I6)))
A8: =IF(B8="","",DATE(YEAR(TODAY()),MATCH(B8,{"January","February","March","April","May","June","July","August","September","October","November","December"},0),1)) | B8: February | C8: =IF(B8="","","Monthly Rent Charge") | E8: =IF(C8="Monthly Rent Charge",$D$3,"") | F8: =IF(C8="Monthly Rent Charge",$F$3,"") | I8: =IF(A8="","",IF(C8="Payment Received",I7-IFERROR(G8,0),IF(C8="Monthly Rent Charge",I7+IFERROR(E8,0)+IFERROR(F8,0),I7)))
A9: 46061 | C9: Payment Received | E9: =IF(C9="Monthly Rent Charge",$D$3,"") | F9: =IF(C9="Monthly Rent Charge",$F$3,"") | G9: 4500 | H9: UB8F264RJM | I9: =IF(A9="","",IF(C9="Payment Received",I8-IFERROR(G9,0),IF(C9="Monthly Rent Charge",I8+IFERROR(E9,0)+IFERROR(F9,0),I8)))
A10: =IF(B10="","",DATE(YEAR(TODAY()),MATCH(B10,{"January","February","March","April","May","June","July","August","September","October","November","December"},0),1)) | B10: March | C10: =IF(B10="","","Monthly Rent Charge") | E10: =IF(C10="Monthly Rent Charge",$D$3,"") | F10: =IF(C10="Monthly Rent Charge",$F$3,"") | I10: =IF(A10="","",IF(C10="Payment Received",I9-IFERROR(G10,0),IF(C10="Monthly Rent Charge",I9+IFERROR(E10,0)+IFERROR(F10,0),I9)))
A11: 46088 | C11: Payment Received | E11: =IF(C11="Monthly Rent Charge",$D$3,"") | G11: 5100 | H11: UC7O98C3B3 | I11: =IF(A11="","",IF(C11="Payment Received",I10-IFERROR(G11,0),IF(C11="Monthly Rent Charge",I10+IFERROR(E11,0)+IFERROR(F11,0),I10)))
A12: =IF(B12="","",DATE(YEAR(TODAY()),MATCH(B12,{"January","February","March","April","May","June","July","August","September","October","November","December"},0),1)) | B12: April | C12: =IF(B12="","","Monthly Rent Charge") | E12: =IF(C12="Monthly Rent Charge",$D$3,"") | F12: =IF(C12="Monthly Rent Charge",$F$3,"") | I12: =IF(A12="","",IF(C12="Payment Received",I11-IFERROR(G12,0),IF(C12="Monthly Rent Charge",I11+IFERROR(E12,0)+IFERROR(F12,0),I11)))
A13: 46130 | C13: Payment Received | E13: =IF(C13="Monthly Rent Charge",$D$3,"") | F13: =IF(C13="Monthly Rent Charge",$F$3,"") | G13: 4700 | H13: UDIFU11SD2 | I13: =IF(A13="","",IF(C13="Payment Received",I12-IFERROR(G13,0),IF(C13="Monthly Rent Charge",I12+IFERROR(E13,0)+IFERROR(F13,0),I12)))
A14: =IF(B14="","",DATE(YEAR(TODAY()),MATCH(B14,{"January","February","March","April","May","June","July","August","September","October","November","December"},0),1)) | B14: May | C14: =IF(B14="","","Monthly Rent Charge") | E14: =IF(C14="Monthly Rent Charge",$D$3,"") | F14: =IF(C14="Monthly Rent Charge",$F$3,"") | I14: =IF(AND(A14="",C14=""),"",IF(C14="Payment Received",I13-IFERROR(G14,0),IF(C14="Monthly Rent Charge",I13+IFERROR(E14,0)+IFERROR(F14,0),I13)))
A15: 46158 | C15: Payment Received | E15: =IF(C15="Monthly Rent Charge",$D$3,"") | F15: =IF(C15="Monthly Rent Charge",$F$3,"") | G15: 4700 | H15: UEGF24H7JL | I15: =IF(AND(A15="",C15=""),"",IF(C15="Payment Received",I14-IFERROR(G15,0),IF(C15="Monthly Rent Charge",I14+IFERROR(E15,0)+IFERROR(F15,0),I14)))
A16: =IF(B16="","",DATE(YEAR(TODAY()),MATCH(B16,{"January","February","March","April","May","June","July","August","September","October","November","December"},0),1)) | B16: June | C16: =IF(B16="","","Monthly Rent Charge") | E16: =IF(C16="Monthly Rent Charge",$D$3,"") | F16: =IF(C16="Monthly Rent Charge",$F$3,"") | I16: =IF(AND(A16="",C16=""),"",IF(C16="Payment Received",I15-IFERROR(G16,0),IF(C16="Monthly Rent Charge",I15+IFERROR(E16,0)+IFERROR(F16,0),I15)))
A17: 46194 | C17: Payment Received | E17: =IF(C17="Monthly Rent Charge",$D$3,"") | F17: =IF(C17="Monthly Rent Charge",$F$3,"") | G17: 4700 | H17: UF11FU89MKJ | I17: =IF(AND(A17="",C17=""),"",IF(C17="Payment Received",I16-IFERROR(G17,0),IF(C17="Monthly Rent Charge",I16+IFERROR(E17,0)+IFERROR(F17,0),I16)))
A18: =IF(B18="","",DATE(YEAR(TODAY()),MATCH(B18,{"January","February","March","April","May","June","July","August","September","October","November","December"},0),1)) | B18: July | C18: =IF(B18="","","Monthly Rent Charge") | E18: =IF(C18="Monthly Rent Charge",$D$3,"") | F18: =IF(C18="Monthly Rent Charge",$F$3,"") | I18: =IF(AND(A18="",C18=""),"",IF(C18="Payment Received",I17-IFERROR(G18,0),IF(C18="Monthly Rent Charge",I17+IFERROR(E18,0)+IFERROR(F18,0),I17)))
A19: 46231 | C19: Payment Received | E19: =IF(C19="Monthly Rent Charge",$D$3,"") | F19: =IF(C19="Monthly Rent Charge",$F$3,"") | G19: 4700 | H19: UGSF20TNYT | I19: =IF(AND(A19="",C19=""),"",IF(C19="Payment Received",I18-IFERROR(G19,0),IF(C19="Monthly Rent Charge",I18+IFERROR(E19,0)+IFERROR(F19,0),IFERROR(I18,0))))
A20: =IF(B20="","",DATE(YEAR(TODAY()),MATCH(B20,{"January","February","March","April","May","June","July","August","September","October","November","December"},0),1)) | B20: August | C20: =IF(B20="","","Monthly Rent Charge") | E20: =IF(C20="Monthly Rent Charge",$D$3,"") | F20: =IF(C20="Monthly Rent Charge",$F$3,"") | I20: =IF(AND(A20="",C20=""),"",IF(C20="Payment Received",I19-IFERROR(G20,0),IF(C20="Monthly Rent Charge",I19+IFERROR(E20,0)+IFERROR(F20,0),IFERROR(I19,0))))
A21: 46258 | C21: Payment Received | E21: =IF(C21="Monthly Rent Charge",$D$3,"") | F21: =IF(C21="Monthly Rent Charge",$F$3,"") | G21: 4700 | H21: UHOF23XZXA | I21: =IF(AND(A21="",C21=""),"",IF(C21="Payment Received",I20-IFERROR(G21,0),IF(C21="Monthly Rent Charge",I20+IFERROR(E21,0)+IFERROR(F21,0),IFERROR(I20,0))))
A22: =IF(B22="","",DATE(YEAR(TODAY()),MATCH(B22,{"January","February","March","April","May","June","July","August","September","October","November","December"},0),1)) | C22: =IF(B22="","","Monthly Rent Charge") | E22: =IF(C22="Monthly Rent Charge",$D$3,"") | F22: =IF(C22="Monthly Rent Charge",$F$3,"") | I22: =IF(AND(A22="",C22=""),"",IF(C22="Payment Received",I21-IFERROR(G22,0),IF(C22="Monthly Rent Charge",I21+IFERROR(E22,0)+IFERROR(F22,0),IFERROR(I21,0))))
A23: =IF(B23="","",DATE(YEAR(TODAY()),MATCH(B23,{"January","February","March","April","May","June","July","August","September","October","November","December"},0),1)) | C23: =IF(B23="","","Monthly Rent Charge") | E23: =IF(C23="Monthly Rent Charge",$D$3,"") | F23: =IF(C23="Monthly Rent Charge",$F$3,"") | I23: =IF(AND(A23="",C23=""),"",IF(C23="Payment Received",I22-IFERROR(G23,0),IF(C23="Monthly Rent Charge",I22+IFERROR(E23,0)+IFERROR(F23,0),IFERROR(I22,0))))
A24: =IF(B24="","",DATE(YEAR(TODAY()),MATCH(B24,{"January","February","March","April","May","June","July","August","September","October","November","December"},0),1)) | C24: =IF(B24="","","Monthly Rent Charge") | E24: =IF(C24="Monthly Rent Charge",$D$3,"") | F24: =IF(C24="Monthly Rent Charge",$F$3,"") | I24: =IF(AND(A24="",C24=""),"",IF(C24="Payment Received",I23-IFERROR(G24,0),IF(C24="Monthly Rent Charge",I23+IFERROR(E24,0)+IFERROR(F24,0),IFERROR(I23,0))))
A25: =IF(B25="","",DATE(YEAR(TODAY()),MATCH(B25,{"January","February","March","April","May","June","July","August","September","October","November","December"},0),1)) | C25: =IF(B25="","","Monthly Rent Charge") | E25: =IF(C25="Monthly Rent Charge",$D$3,"") | F25: =IF(C25="Monthly Rent Charge",$F$3,"") | I25: =IF(AND(A25="",C25=""),"",IF(C25="Payment Received",I24-IFERROR(G25,0),IF(C25="Monthly Rent Charge",I24+IFERROR(E25,0)+IFERROR(F25,0),IFERROR(I24,0))))
A26: =IF(B26="","",DATE(YEAR(TODAY()),MATCH(B26,{"January","February","March","April","May","June","July","August","September","October","November","December"},0),1)) | C26: =IF(B26="","","Monthly Rent Charge") | E26: =IF(C26="Monthly Rent Charge",$D$3,"") | F26: =IF(C26="Monthly Rent Charge",$F$3,"") | I26: =IF(AND(A26="",C26=""),"",IF(C26="Payment Received",I25-IFERROR(G26,0),IF(C26="Monthly Rent Charge",I25+IFERROR(E26,0)+IFERROR(F26,0),IFERROR(I25,0))))
A27: =IF(B27="","",DATE(YEAR(TODAY()),MATCH(B27,{"January","February","March","April","May","June","July","August","September","October","November","December"},0),1)) | C27: =IF(B27="","","Monthly Rent Charge") | E27: =IF(C27="Monthly Rent Charge",$D$3,"") | F27: =IF(C27="Monthly Rent Charge",$F$3,"") | I27: =IF(AND(A27="",C27=""),"",IF(C27="Payment Received",I26-IFERROR(G27,0),IF(C27="Monthly Rent Charge",I26+IFERROR(E27,0)+IFERROR(F27,0),IFERROR(I26,0))))
A28: =IF(B28="","",DATE(YEAR(TODAY()),MATCH(B28,{"January","February","March","April","May","June","July","August","September","October","November","December"},0),1)) | C28: =IF(B28="","","Monthly Rent Charge") | E28: =IF(C28="Monthly Rent Charge",$D$3,"") | F28: =IF(C28="Monthly Rent Charge",$F$3,"") | I28: =IF(AND(A28="",C28=""),"",IF(C28="Payment Received",I27-IFERROR(G28,0),IF(C28="Monthly Rent Charge",I27+IFERROR(E28,0)+IFERROR(F28,0),IFERROR(I27,0))))
A29: =IF(B29="","",DATE(YEAR(TODAY()),MATCH(B29,{"January","February","March","April","May","June","July","August","September","October","November","December"},0),1)) | C29: =IF(B29="","","Monthly Rent Charge") | E29: =IF(C29="Monthly Rent Charge",$D$3,"") | F29: =IF(C29="Monthly Rent Charge",$F$3,"") | I29: =IF(AND(A29="",C29=""),"",IF(C29="Payment Received",I28-IFERROR(G29,0),IF(C29="Monthly Rent Charge",I28+IFERROR(E29,0)+IFERROR(F29,0),IFERROR(I28,0))))
A30: =IF(B30="","",DATE(YEAR(TODAY()),MATCH(B30,{"January","February","March","April","May","June","July","August","September","October","November","December"},0),1)) | C30: =IF(B30="","","Monthly Rent Charge") | E30: =IF(C30="Monthly Rent Charge",$D$3,"") | F30: =IF(C30="Monthly Rent Charge",$F$3,"") | I30: =IF(AND(A30="",C30=""),"",IF(C30="Payment Received",I29-IFERROR(G30,0),IF(C30="Monthly Rent Charge",I29+IFERROR(E30,0)+IFERROR(F30,0),IFERROR(I29,0))))
A31: =IF(B31="","",DATE(YEAR(TODAY()),MATCH(B31,{"January","February","March","April","May","June","July","August","September","October","November","December"},0),1)) | C31: =IF(B31="","","Monthly Rent Charge") | E31: =IF(C31="Monthly Rent Charge",$D$3,"") | F31: =IF(C31="Monthly Rent Charge",$F$3,"") | I31: =IF(AND(A31="",C31=""),"",IF(C31="Payment Received",I30-IFERROR(G31,0),IF(C31="Monthly Rent Charge",I30+IFERROR(E31,0)+IFERROR(F31,0),IFERROR(I30,0))))
A32: =IF(B32="","",DATE(YEAR(TODAY()),MATCH(B32,{"January","February","March","April","May","June","July","August","September","October","November","December"},0),1)) | C32: =IF(B32="","","Monthly Rent Charge") | E32: =IF(C32="Monthly Rent Charge",$D$3,"") | F32: =IF(C32="Monthly Rent Charge",$F$3,"") | I32: =IF(AND(A32="",C32=""),"",IF(C32="Payment Received",I31-IFERROR(G32,0),IF(C32="Monthly Rent Charge",I31+IFERROR(E32,0)+IFERROR(F32,0),IFERROR(I31,0))))
A33: =IF(B33="","",DATE(YEAR(TODAY()),MATCH(B33,{"January","February","March","April","May","June","July","August","September","October","November","December"},0),1)) | C33: =IF(B33="","","Monthly Rent Charge") | E33: =IF(C33="Monthly Rent Charge",$D$3,"") | F33: =IF(C33="Monthly Rent Charge",$F$3,"") | I33: =IF(AND(A33="",C33=""),"",IF(C33="Payment Received",I32-IFERROR(G33,0),IF(C33="Monthly Rent Charge",I32+IFERROR(E33,0)+IFERROR(F33,0),IFERROR(I32,0))))

Sheet A4
A1: Unit A4 — Tenant Statement / Ledger
A2: Select a month to create a Monthly Rent Charge: the date fills as the first day of that month (current year) and description fills automatically. For a payment, leave Month blank and choose Payment Received.
A3: Unit | B3: A4 | C3: Current Rent | D3: 3000 | E3: Garbage | F3: 200 | G3: Current Balance | H3: =IFERROR(LOOKUP(9.99E+307,I6:I73),0) | I3: Tenant | J3: RAPHAEL NDELEVA / BENEDETTAH NDELEVA | K3: Deposit Held | L3: 0
A4: Current tenant only. When vacating → copy rows to Archive sheet, then clear this ledger.
A5: Date | B5: Month | C5: Description | D5: Tenant | E5: Rent Charged | F5: Garbage Charged | G5: Payment Received | H5: M-Pesa Reference | I5: Running Balance | J5: Remarks
A6: 45413 | B6: May | C6: =IF(B6="","","Monthly Rent Charge") | E6: =IF(C6="Monthly Rent Charge",$D$3,"") | F6: =IF(C6="Monthly Rent Charge",$F$3,"") | I6: =IF(A6="","",IF(C6="Payment Received",-IFERROR(G6,0),IF(C6="Monthly Rent Charge",IFERROR(E6,0)+IFERROR(F6,0),0)))
A7: 45420 | C7: Payment Received | G7: 3200 | H7: SE86JZPCN2 | I7: =IF(A7="","",IF(C7="Payment Received",I6-IFERROR(G7,0),IF(C7="Monthly Rent Charge",I6+IFERROR(E7,0)+IFERROR(F7,0),I6)))
A8: 45444 | B8: June | C8: =IF(B8="","","Monthly Rent Charge") | E8: =IF(C8="Monthly Rent Charge",$D$3,"") | F8: =IF(C8="Monthly Rent Charge",$F$3,"") | I8: =IF(A8="","",IF(C8="Payment Received",I7-IFERROR(G8,0),IF(C8="Monthly Rent Charge",I7+IFERROR(E8,0)+IFERROR(F8,0),I7)))
A9: 45452 | C9: Payment Received | G9: 3200 | H9: SF96VY6NXY | I9: =IF(A9="","",IF(C9="Payment Received",I8-IFERROR(G9,0),IF(C9="Monthly Rent Charge",I8+IFERROR(E9,0)+IFERROR(F9,0),I8)))
A10: 45474 | B10: July | C10: =IF(B10="","","Monthly Rent Charge") | E10: =IF(C10="Monthly Rent Charge",$D$3,"") | F10: =IF(C10="Monthly Rent Charge",$F$3,"") | I10: =IF(A10="","",IF(C10="Payment Received",I9-IFERROR(G10,0),IF(C10="Monthly Rent Charge",I9+IFERROR(E10,0)+IFERROR(F10,0),I9)))
A11: 45482 | C11: Payment Received | G11: 3200 | H11: SG974VW31B | I11: =IF(A11="","",IF(C11="Payment Received",I10-IFERROR(G11,0),IF(C11="Monthly Rent Charge",I10+IFERROR(E11,0)+IFERROR(F11,0),I10)))
A12: 45505 | B12: August | C12: Monthly Rent Charge | E12: =IF(C12="Monthly Rent Charge",$D$3,"") | F12: =IF(C12="Monthly Rent Charge",$F$3,"") | I12: =IF(A12="","",IF(C12="Payment Received",I11-IFERROR(G12,0),IF(C12="Monthly Rent Charge",I11+IFERROR(E12,0)+IFERROR(F12,0),I11)))
A13: 45514 | C13: Payment Received | G13: 3200 | H13: SHA2JVN500 | I13: =IF(A13="","",IF(C13="Payment Received",I12-IFERROR(G13,0),IF(C13="Monthly Rent Charge",I12+IFERROR(E13,0)+IFERROR(F13,0),I12)))
A14: 45536 | B14: September | C14: Monthly Rent Charge | E14: =IF(C14="Monthly Rent Charge",$D$3,"") | F14: =IF(C14="Monthly Rent Charge",$F$3,"") | I14: =IF(A14="","",IF(C14="Payment Received",I13-IFERROR(G14,0),IF(C14="Monthly Rent Charge",I13+IFERROR(E14,0)+IFERROR(F14,0),I13)))
A15: 45545 | C15: Payment Received | G15: 3200 | H15: SIA92B1A6T | I15: =IF(A15="","",IF(C15="Payment Received",I14-IFERROR(G15,0),IF(C15="Monthly Rent Charge",I14+IFERROR(E15,0)+IFERROR(F15,0),I14)))
A16: 45566 | B16: October | C16: =IF(B16="","","Monthly Rent Charge") | E16: =IF(C16="Monthly Rent Charge",$D$3,"") | F16: =IF(C16="Monthly Rent Charge",$F$3,"") | I16: =IF(A16="","",IF(C16="Payment Received",I15-IFERROR(G16,0),IF(C16="Monthly Rent Charge",I15+IFERROR(E16,0)+IFERROR(F16,0),I15)))
A17: 45575 | C17: Payment Received | G17: 3200 | H17: SJA5JU1PN7 | I17: =IF(A17="","",IF(C17="Payment Received",I16-IFERROR(G17,0),IF(C17="Monthly Rent Charge",I16+IFERROR(E17,0)+IFERROR(F17,0),I16)))
A18: 45597 | B18: November | C18: =IF(B18="","","Monthly Rent Charge") | E18: =IF(C18="Monthly Rent Charge",$D$3,"") | F18: =IF(C18="Monthly Rent Charge",$F$3,"") | I18: =IF(A18="","",IF(C18="Payment Received",I17-IFERROR(G18,0),IF(C18="Monthly Rent Charge",I17+IFERROR(E18,0)+IFERROR(F18,0),I17)))
A19: 45606 | C19: Payment Received | G19: 3200 | H19: SKA8CNTZV8 | I19: =IF(A19="","",IF(C19="Payment Received",I18-IFERROR(G19,0),IF(C19="Monthly Rent Charge",I18+IFERROR(E19,0)+IFERROR(F19,0),I18)))
A20: 45627 | B20: December | C20: =IF(B20="","","Monthly Rent Charge") | E20: =IF(C20="Monthly Rent Charge",$D$3,"") | F20: =IF(C20="Monthly Rent Charge",$F$3,"") | I20: =IF(A20="","",IF(C20="Payment Received",I19-IFERROR(G20,0),IF(C20="Monthly Rent Charge",I19+IFERROR(E20,0)+IFERROR(F20,0),I19)))
A21: 45636 | C21: Payment Received | G21: 3200 | H21: SLA8ZXHCHE | I21: =IF(A21="","",IF(C21="Payment Received",I20-IFERROR(G21,0),IF(C21="Monthly Rent Charge",I20+IFERROR(E21,0)+IFERROR(F21,0),I20)))
A22: 45658 | B22: January | C22: Monthly Rent Charge | E22: =IF(C22="Monthly Rent Charge",$D$3,"") | F22: =IF(C22="Monthly Rent Charge",$F$3,"") | I22: =IF(A22="","",IF(C22="Payment Received",I21-IFERROR(G22,0),IF(C22="Monthly Rent Charge",I21+IFERROR(E22,0)+IFERROR(F22,0),I21)))
A23: 45666 | C23: Payment Received | G23: 3200 | H23: TA93LIURJX | I23: =IF(A23="","",IF(C23="Payment Received",I22-IFERROR(G23,0),IF(C23="Monthly Rent Charge",I22+IFERROR(E23,0)+IFERROR(F23,0),I22)))
A24: 45689 | B24: February | C24: =IF(B24="","","Monthly Rent Charge") | E24: =IF(C24="Monthly Rent Charge",$D$3,"") | F24: =IF(C24="Monthly Rent Charge",$F$3,"") | I24: =IF(A24="","",IF(C24="Payment Received",I23-IFERROR(G24,0),IF(C24="Monthly Rent Charge",I23+IFERROR(E24,0)+IFERROR(F24,0),I23)))
A25: 45698 | C25: Payment Received | G25: 3200 | H25: TBA8G3NFOG | I25: =IF(A25="","",IF(C25="Payment Received",I24-IFERROR(G25,0),IF(C25="Monthly Rent Charge",I24+IFERROR(E25,0)+IFERROR(F25,0),I24)))
A26: 45717 | B26: March | C26: =IF(B26="","","Monthly Rent Charge") | E26: =IF(C26="Monthly Rent Charge",$D$3,"") | F26: =IF(C26="Monthly Rent Charge",$F$3,"") | I26: =IF(A26="","",IF(C26="Payment Received",I25-IFERROR(G26,0),IF(C26="Monthly Rent Charge",I25+IFERROR(E26,0)+IFERROR(F26,0),I25)))
A27: 45725 | C27: Payment Received | G27: 3200 | H27: TC931LUOB5 | I27: =IF(A27="","",IF(C27="Payment Received",I26-IFERROR(G27,0),IF(C27="Monthly Rent Charge",I26+IFERROR(E27,0)+IFERROR(F27,0),I26)))
A28: 45748 | B28: April | C28: =IF(B28="","","Monthly Rent Charge") | E28: =IF(C28="Monthly Rent Charge",$D$3,"") | F28: =IF(C28="Monthly Rent Charge",$F$3,"") | I28: =IF(A28="","",IF(C28="Payment Received",I27-IFERROR(G28,0),IF(C28="Monthly Rent Charge",I27+IFERROR(E28,0)+IFERROR(F28,0),I27)))
A29: 45757 | C29: Payment Received | G29: 3200 | H29: TDA87E6O5M | I29: =IF(A29="","",IF(C29="Payment Received",I28-IFERROR(G29,0),IF(C29="Monthly Rent Charge",I28+IFERROR(E29,0)+IFERROR(F29,0),I28)))
A30: 45778 | B30: May | C30: =IF(B30="","","Monthly Rent Charge") | E30: =IF(C30="Monthly Rent Charge",$D$3,"") | F30: =IF(C30="Monthly Rent Charge",$F$3,"") | I30: =IF(A30="","",IF(C30="Payment Received",I29-IFERROR(G30,0),IF(C30="Monthly Rent Charge",I29+IFERROR(E30,0)+IFERROR(F30,0),I29)))
A31: 45787 | C31: Payment Received | G31: 3200 | H31: TEA06SQNHA | I31: =IF(A31="","",IF(C31="Payment Received",I30-IFERROR(G31,0),IF(C31="Monthly Rent Charge",I30+IFERROR(E31,0)+IFERROR(F31,0),I30)))
A32: 45779 | B32: June | C32: =IF(B32="","","Monthly Rent Charge") | E32: =IF(C32="Monthly Rent Charge",$D$3,"") | F32: =IF(C32="Monthly Rent Charge",$F$3,"") | I32: =IF(A32="","",IF(C32="Payment Received",I31-IFERROR(G32,0),IF(C32="Monthly Rent Charge",I31+IFERROR(E32,0)+IFERROR(F32,0),I31)))
A33: 45818 | C33: Payment Received | G33: 3200 | H33: TFA3A1JX4L | I33: =IF(A33="","",IF(C33="Payment Received",I32-IFERROR(G33,0),IF(C33="Monthly Rent Charge",I32+IFERROR(E33,0)+IFERROR(F33,0),I32)))
A34: 45780 | B34: July | C34: =IF(B34="","","Monthly Rent Charge") | E34: =IF(C34="Monthly Rent Charge",$D$3,"") | F34: =IF(C34="Monthly Rent Charge",$F$3,"") | I34: =IF(A34="","",IF(C34="Payment Received",I33-IFERROR(G34,0),IF(C34="Monthly Rent Charge",I33+IFERROR(E34,0)+IFERROR(F34,0),I33)))
A35: 45483 | C35: Payment Received | G35: 3200 | H35: TGA1DUSCK3 | I35: =IF(A35="","",IF(C35="Payment Received",I34-IFERROR(G35,0),IF(C35="Monthly Rent Charge",I34+IFERROR(E35,0)+IFERROR(F35,0),I34)))
A36: 45781 | B36: August | C36: =IF(B36="","","Monthly Rent Charge") | E36: =IF(C36="Monthly Rent Charge",$D$3,"") | F36: =IF(C36="Monthly Rent Charge",$F$3,"") | I36: =IF(A36="","",IF(C36="Payment Received",I35-IFERROR(G36,0),IF(C36="Monthly Rent Charge",I35+IFERROR(E36,0)+IFERROR(F36,0),I35)))
A37: 45879 | C37: Payment Received | G37: 3200 | H37: THA2SHDDI8 | I37: =IF(A37="","",IF(C37="Payment Received",I36-IFERROR(G37,0),IF(C37="Monthly Rent Charge",I36+IFERROR(E37,0)+IFERROR(F37,0),I36)))
A38: 45782 | B38: September | C38: =IF(B38="","","Monthly Rent Charge") | E38: =IF(C38="Monthly Rent Charge",$D$3,"") | F38: =IF(C38="Monthly Rent Charge",$F$3,"") | I38: =IF(A38="","",IF(C38="Payment Received",I37-IFERROR(G38,0),IF(C38="Monthly Rent Charge",I37+IFERROR(E38,0)+IFERROR(F38,0),I37)))
A39: 45909 | C39: Payment Received | G39: 3200 | H39: TI9444DD9G | I39: =IF(A39="","",IF(C39="Payment Received",I38-IFERROR(G39,0),IF(C39="Monthly Rent Charge",I38+IFERROR(E39,0)+IFERROR(F39,0),I38)))
A40: 45783 | B40: October | C40: =IF(B40="","","Monthly Rent Charge") | E40: =IF(C40="Monthly Rent Charge",$D$3,"") | F40: =IF(C40="Monthly Rent Charge",$F$3,"") | I40: =IF(A40="","",IF(C40="Payment Received",I39-IFERROR(G40,0),IF(C40="Monthly Rent Charge",I39+IFERROR(E40,0)+IFERROR(F40,0),I39)))
A41: 45940 | C41: Payment Received | G41: 3200 | H41: TJA866WD2O | I41: =IF(A41="","",IF(C41="Payment Received",I40-IFERROR(G41,0),IF(C41="Monthly Rent Charge",I40+IFERROR(E41,0)+IFERROR(F41,0),I40)))
A42: 45962 | B42: November | C42: =IF(B42="","","Monthly Rent Charge") | E42: =IF(C42="Monthly Rent Charge",$D$3,"") | F42: =IF(C42="Monthly Rent Charge",$F$3,"") | I42: =IF(A42="","",IF(C42="Payment Received",I41-IFERROR(G42,0),IF(C42="Monthly Rent Charge",I41+IFERROR(E42,0)+IFERROR(F42,0),I41)))
A43: 45972 | C43: Payment Received | E43: =IF(C43="Monthly Rent Charge",$D$3,"") | F43: =IF(C43="Monthly Rent Charge",$F$3,"") | G43: 3200 | H43: TKB869PPT2 | I43: =IF(A43="","",IF(C43="Payment Received",I42-IFERROR(G43,0),IF(C43="Monthly Rent Charge",I42+IFERROR(E43,0)+IFERROR(F43,0),I42)))
A44: 45992 | B44: December | C44: =IF(B44="","","Monthly Rent Charge") | E44: =IF(C44="Monthly Rent Charge",$D$3,"") | F44: =IF(C44="Monthly Rent Charge",$F$3,"") | I44: =IF(A44="","",IF(C44="Payment Received",I43-IFERROR(G44,0),IF(C44="Monthly Rent Charge",I43+IFERROR(E44,0)+IFERROR(F44,0),I43)))
A45: 46001 | C45: Payment Received | E45: =IF(C45="Monthly Rent Charge",$D$3,"") | F45: =IF(C45="Monthly Rent Charge",$F$3,"") | G45: 3200 | H45: TLA860IG77 | I45: =IF(A45="","",IF(C45="Payment Received",I44-IFERROR(G45,0),IF(C45="Monthly Rent Charge",I44+IFERROR(E45,0)+IFERROR(F45,0),I44)))
A46: =IF(B46="","",DATE(YEAR(TODAY()),MATCH(B46,{"January","February","March","April","May","June","July","August","September","October","November","December"},0),1)) | B46: January | C46: =IF(B46="","","Monthly Rent Charge") | E46: =IF(C46="Monthly Rent Charge",$D$3,"") | F46: =IF(C46="Monthly Rent Charge",$F$3,"") | I46: =IF(A46="","",IF(C46="Payment Received",I45-IFERROR(G46,0),IF(C46="Monthly Rent Charge",I45+IFERROR(E46,0)+IFERROR(F46,0),I45)))
A47: 46033 | C47: Payment Received | E47: =IF(C47="Monthly Rent Charge",$D$3,"") | F47: =IF(C47="Monthly Rent Charge",$F$3,"") | G47: 3200 | H47: UAB863DHXT | I47: =IF(A47="","",IF(C47="Payment Received",I46-IFERROR(G47,0),IF(C47="Monthly Rent Charge",I46+IFERROR(E47,0)+IFERROR(F47,0),I46)))
A48: =IF(B48="","",DATE(YEAR(TODAY()),MATCH(B48,{"January","February","March","April","May","June","July","August","September","October","November","December"},0),1)) | B48: February | C48: =IF(B48="","","Monthly Rent Charge") | E48: =IF(C48="Monthly Rent Charge",$D$3,"") | F48: =IF(C48="Monthly Rent Charge",$F$3,"") | I48: =IF(A48="","",IF(C48="Payment Received",I47-IFERROR(G48,0),IF(C48="Monthly Rent Charge",I47+IFERROR(E48,0)+IFERROR(F48,0),I47)))
A49: 46063 | C49: Payment Received | E49: =IF(C49="Monthly Rent Charge",$D$3,"") | F49: =IF(C49="Monthly Rent Charge",$F$3,"") | G49: 3200 | H49: UBA8665D1T | I49: =IF(A49="","",IF(C49="Payment Received",I48-IFERROR(G49,0),IF(C49="Monthly Rent Charge",I48+IFERROR(E49,0)+IFERROR(F49,0),I48)))
A50: =IF(B50="","",DATE(YEAR(TODAY()),MATCH(B50,{"January","February","March","April","May","June","July","August","September","October","November","December"},0),1)) | B50: March | C50: =IF(B50="","","Monthly Rent Charge") | E50: =IF(C50="Monthly Rent Charge",$D$3,"") | F50: =IF(C50="Monthly Rent Charge",$F$3,"") | I50: =IF(A50="","",IF(C50="Payment Received",I49-IFERROR(G50,0),IF(C50="Monthly Rent Charge",I49+IFERROR(E50,0)+IFERROR(F50,0),I49)))
A51: 46091 | C51: Payment Received | E51: =IF(C51="Monthly Rent Charge",$D$3,"") | F51: =IF(C51="Monthly Rent Charge",$F$3,"") | G51: 3200 | H51: UCA868PYRO | I51: =IF(A51="","",IF(C51="Payment Received",I50-IFERROR(G51,0),IF(C51="Monthly Rent Charge",I50+IFERROR(E51,0)+IFERROR(F51,0),I50)))
A52: =IF(B52="","",DATE(YEAR(TODAY()),MATCH(B52,{"January","February","March","April","May","June","July","August","September","October","November","December"},0),1)) | B52: April | C52: =IF(B52="","","Monthly Rent Charge") | E52: =IF(C52="Monthly Rent Charge",$D$3,"") | F52: =IF(C52="Monthly Rent Charge",$F$3,"") | I52: =IF(A52="","",IF(C52="Payment Received",I51-IFERROR(G52,0),IF(C52="Monthly Rent Charge",I51+IFERROR(E52,0)+IFERROR(F52,0),I51)))
A53: 46123 | C53: Payment Received | E53: =IF(C53="Monthly Rent Charge",$D$3,"") | F53: =IF(C53="Monthly Rent Charge",$F$3,"") | G53: 3200 | H53: UDB8609U2D | I53: =IF(A53="","",IF(C53="Payment Received",I52-IFERROR(G53,0),IF(C53="Monthly Rent Charge",I52+IFERROR(E53,0)+IFERROR(F53,0),I52)))
A54: =IF(B54="","",DATE(YEAR(TODAY()),MATCH(B54,{"January","February","March","April","May","June","July","August","September","October","November","December"},0),1)) | B54: May | C54: =IF(B54="","","Monthly Rent Charge") | E54: =IF(C54="Monthly Rent Charge",$D$3,"") | F54: =IF(C54="Monthly Rent Charge",$F$3,"") | I54: =IF(AND(A54="",C54=""),"",IF(C54="Payment Received",I53-IFERROR(G54,0),IF(C54="Monthly Rent Charge",I53+IFERROR(E54,0)+IFERROR(F54,0),I53)))
A55: 46151 | C55: Payment Received | E55: =IF(C55="Monthly Rent Charge",$D$3,"") | F55: =IF(C55="Monthly Rent Charge",$F$3,"") | G55: 3200 | H55: UE9863H978 | I55: =IF(AND(A55="",C55=""),"",IF(C55="Payment Received",I54-IFERROR(G55,0),IF(C55="Monthly Rent Charge",I54+IFERROR(E55,0)+IFERROR(F55,0),I54)))
A56: =IF(B56="","",DATE(YEAR(TODAY()),MATCH(B56,{"January","February","March","April","May","June","July","August","September","October","November","December"},0),1)) | B56: June | C56: =IF(B56="","","Monthly Rent Charge") | E56: =IF(C56="Monthly Rent Charge",$D$3,"") | F56: =IF(C56="Monthly Rent Charge",$F$3,"") | I56: =IF(AND(A56="",C56=""),"",IF(C56="Payment Received",I55-IFERROR(G56,0),IF(C56="Monthly Rent Charge",I55+IFERROR(E56,0)+IFERROR(F56,0),I55)))
A57: 46186 | C57: Payment Received | E57: =IF(C57="Monthly Rent Charge",$D$3,"") | F57: =IF(C57="Monthly Rent Charge",$F$3,"") | G57: 3200 | H57: UFD867HYKV | I57: =IF(AND(A57="",C57=""),"",IF(C57="Payment Received",I56-IFERROR(G57,0),IF(C57="Monthly Rent Charge",I56+IFERROR(E57,0)+IFERROR(F57,0),I56)))
A58: =IF(B58="","",DATE(YEAR(TODAY()),MATCH(B58,{"January","February","March","April","May","June","July","August","September","October","November","December"},0),1)) | B58: July | C58: =IF(B58="","","Monthly Rent Charge") | E58: =IF(C58="Monthly Rent Charge",$D$3,"") | F58: =IF(C58="Monthly Rent Charge",$F$3,"") | I58: =IF(AND(A58="",C58=""),"",IF(C58="Payment Received",I57-IFERROR(G58,0),IF(C58="Monthly Rent Charge",I57+IFERROR(E58,0)+IFERROR(F58,0),I57)))
A59: 46215 | C59: Payment Received | E59: =IF(C59="Monthly Rent Charge",$D$3,"") | F59: =IF(C59="Monthly Rent Charge",$F$3,"") | G59: 3200 | H59: UGCPFAZDD2 | I59: =IF(AND(A59="",C59=""),"",IF(C59="Payment Received",I58-IFERROR(G59,0),IF(C59="Monthly Rent Charge",I58+IFERROR(E59,0)+IFERROR(F59,0),IFERROR(I58,0)))) | J59: BENEDETTAH NDELEVA
A60: =IF(B60="","",DATE(YEAR(TODAY()),MATCH(B60,{"January","February","March","April","May","June","July","August","September","October","November","December"},0),1)) | B60: August | C60: =IF(B60="","","Monthly Rent Charge") | E60: =IF(C60="Monthly Rent Charge",$D$3,"") | F60: =IF(C60="Monthly Rent Charge",$F$3,"") | I60: =IF(AND(A60="",C60=""),"",IF(C60="Payment Received",I59-IFERROR(G60,0),IF(C60="Monthly Rent Charge",I59+IFERROR(E60,0)+IFERROR(F60,0),IFERROR(I59,0))))
A61: 46246 | C61: Payment Received | E61: =IF(C61="Monthly Rent Charge",$D$3,"") | F61: =IF(C61="Monthly Rent Charge",$F$3,"") | G61: 6400 | H61: UHC862HCU | I61: =IF(AND(A61="",C61=""),"",IF(C61="Payment Received",I60-IFERROR(G61,0),IF(C61="Monthly Rent Charge",I60+IFERROR(E61,0)+IFERROR(F61,0),IFERROR(I60,0))))
A62: =IF(B62="","",DATE(YEAR(TODAY()),MATCH(B62,{"January","February","March","April","May","June","July","August","September","October","November","December"},0),1)) | C62: =IF(B62="","","Monthly Rent Charge") | E62: =IF(C62="Monthly Rent Charge",$D$3,"") | F62: =IF(C62="Monthly Rent Charge",$F$3,"") | I62: =IF(AND(A62="",C62=""),"",IF(C62="Payment Received",I61-IFERROR(G62,0),IF(C62="Monthly Rent Charge",I61+IFERROR(E62,0)+IFERROR(F62,0),IFERROR(I61,0))))
A63: =IF(B63="","",DATE(YEAR(TODAY()),MATCH(B63,{"January","February","March","April","May","June","July","August","September","October","November","December"},0),1)) | C63: =IF(B63="","","Monthly Rent Charge") | E63: =IF(C63="Monthly Rent Charge",$D$3,"") | F63: =IF(C63="Monthly Rent Charge",$F$3,"") | I63: =IF(AND(A63="",C63=""),"",IF(C63="Payment Received",I62-IFERROR(G63,0),IF(C63="Monthly Rent Charge",I62+IFERROR(E63,0)+IFERROR(F63,0),IFERROR(I62,0))))
A64: =IF(B64="","",DATE(YEAR(TODAY()),MATCH(B64,{"January","February","March","April","May","June","July","August","September","October","November","December"},0),1)) | C64: =IF(B64="","","Monthly Rent Charge") | E64: =IF(C64="Monthly Rent Charge",$D$3,"") | F64: =IF(C64="Monthly Rent Charge",$F$3,"") | I64: =IF(AND(A64="",C64=""),"",IF(C64="Payment Received",I63-IFERROR(G64,0),IF(C64="Monthly Rent Charge",I63+IFERROR(E64,0)+IFERROR(F64,0),IFERROR(I63,0))))
A65: =IF(B65="","",DATE(YEAR(TODAY()),MATCH(B65,{"January","February","March","April","May","June","July","August","September","October","November","December"},0),1)) | C65: =IF(B65="","","Monthly Rent Charge") | E65: =IF(C65="Monthly Rent Charge",$D$3,"") | F65: =IF(C65="Monthly Rent Charge",$F$3,"") | I65: =IF(AND(A65="",C65=""),"",IF(C65="Payment Received",I64-IFERROR(G65,0),IF(C65="Monthly Rent Charge",I64+IFERROR(E65,0)+IFERROR(F65,0),IFERROR(I64,0))))
A66: =IF(B66="","",DATE(YEAR(TODAY()),MATCH(B66,{"January","February","March","April","May","June","July","August","September","October","November","December"},0),1)) | C66: =IF(B66="","","Monthly Rent Charge") | E66: =IF(C66="Monthly Rent Charge",$D$3,"") | F66: =IF(C66="Monthly Rent Charge",$F$3,"") | I66: =IF(AND(A66="",C66=""),"",IF(C66="Payment Received",I65-IFERROR(G66,0),IF(C66="Monthly Rent Charge",I65+IFERROR(E66,0)+IFERROR(F66,0),IFERROR(I65,0))))
A67: =IF(B67="","",DATE(YEAR(TODAY()),MATCH(B67,{"January","February","March","April","May","June","July","August","September","October","November","December"},0),1)) | C67: =IF(B67="","","Monthly Rent Charge") | E67: =IF(C67="Monthly Rent Charge",$D$3,"") | F67: =IF(C67="Monthly Rent Charge",$F$3,"") | I67: =IF(AND(A67="",C67=""),"",IF(C67="Payment Received",I66-IFERROR(G67,0),IF(C67="Monthly Rent Charge",I66+IFERROR(E67,0)+IFERROR(F67,0),IFERROR(I66,0))))
A68: =IF(B68="","",DATE(YEAR(TODAY()),MATCH(B68,{"January","February","March","April","May","June","July","August","September","October","November","December"},0),1)) | C68: =IF(B68="","","Monthly Rent Charge") | E68: =IF(C68="Monthly Rent Charge",$D$3,"") | F68: =IF(C68="Monthly Rent Charge",$F$3,"") | I68: =IF(AND(A68="",C68=""),"",IF(C68="Payment Received",I67-IFERROR(G68,0),IF(C68="Monthly Rent Charge",I67+IFERROR(E68,0)+IFERROR(F68,0),IFERROR(I67,0))))
A69: =IF(B69="","",DATE(YEAR(TODAY()),MATCH(B69,{"January","February","March","April","May","June","July","August","September","October","November","December"},0),1)) | C69: =IF(B69="","","Monthly Rent Charge") | E69: =IF(C69="Monthly Rent Charge",$D$3,"") | F69: =IF(C69="Monthly Rent Charge",$F$3,"") | I69: =IF(AND(A69="",C69=""),"",IF(C69="Payment Received",I68-IFERROR(G69,0),IF(C69="Monthly Rent Charge",I68+IFERROR(E69,0)+IFERROR(F69,0),IFERROR(I68,0))))
A70: =IF(B70="","",DATE(YEAR(TODAY()),MATCH(B70,{"January","February","March","April","May","June","July","August","September","October","November","December"},0),1)) | C70: =IF(B70="","","Monthly Rent Charge") | E70: =IF(C70="Monthly Rent Charge",$D$3,"") | F70: =IF(C70="Monthly Rent Charge",$F$3,"") | I70: =IF(AND(A70="",C70=""),"",IF(C70="Payment Received",I69-IFERROR(G70,0),IF(C70="Monthly Rent Charge",I69+IFERROR(E70,0)+IFERROR(F70,0),IFERROR(I69,0))))
A71: =IF(B71="","",DATE(YEAR(TODAY()),MATCH(B71,{"January","February","March","April","May","June","July","August","September","October","November","December"},0),1)) | C71: =IF(B71="","","Monthly Rent Charge") | E71: =IF(C71="Monthly Rent Charge",$D$3,"") | F71: =IF(C71="Monthly Rent Charge",$F$3,"") | I71: =IF(AND(A71="",C71=""),"",IF(C71="Payment Received",I70-IFERROR(G71,0),IF(C71="Monthly Rent Charge",I70+IFERROR(E71,0)+IFERROR(F71,0),IFERROR(I70,0))))
A72: =IF(B72="","",DATE(YEAR(TODAY()),MATCH(B72,{"January","February","March","April","May","June","July","August","September","October","November","December"},0),1)) | C72: =IF(B72="","","Monthly Rent Charge") | E72: =IF(C72="Monthly Rent Charge",$D$3,"") | F72: =IF(C72="Monthly Rent Charge",$F$3,"") | I72: =IF(AND(A72="",C72=""),"",IF(C72="Payment Received",I71-IFERROR(G72,0),IF(C72="Monthly Rent Charge",I71+IFERROR(E72,0)+IFERROR(F72,0),IFERROR(I71,0))))
A73: =IF(B73="","",DATE(YEAR(TODAY()),MATCH(B73,{"January","February","March","April","May","June","July","August","September","October","November","December"},0),1)) | C73: =IF(B73="","","Monthly Rent Charge") | E73: =IF(C73="Monthly Rent Charge",$D$3,"") | F73: =IF(C73="Monthly Rent Charge",$F$3,"") | I73: =IF(AND(A73="",C73=""),"",IF(C73="Payment Received",I72-IFERROR(G73,0),IF(C73="Monthly Rent Charge",I72+IFERROR(E73,0)+IFERROR(F73,0),IFERROR(I72,0))))

Sheet A5
A1: Unit A5 — Tenant Statement / Ledger
A2: Select a month to create a Monthly Rent Charge: the date fills as the first day of that month (current year) and description fills automatically. For a payment, leave Month blank and choose Payment Received.
A3: Unit | B3: A5 | C3: Current Rent | D3: 3000 | E3: Garbage | F3: 200 | G3: Current Balance | H3: =IFERROR(LOOKUP(9.99E+307,I6:I31),0) | I3: Tenant | J3: Joseph Musyoka | K3: Deposit Held | L3: 0
A4: Current tenant only. When vacating → copy rows to Archive sheet, then clear this ledger.
A5: Date | B5: Month | C5: Description | D5: Tenant | E5: Rent Charged | F5: Garbage Charged | G5: Payment Received | H5: M-Pesa Reference | I5: Running Balance | J5: Remarks
A6: =IF(B6="","",DATE(YEAR(TODAY()),MATCH(B6,{"January","February","March","April","May","June","July","August","September","October","November","December"},0),1)) | B6: February | C6: =IF(B6="","","Monthly Rent Charge") | E6: =IF(C6="Monthly Rent Charge",$D$3,"") | F6: =IF(C6="Monthly Rent Charge",$F$3,"") | I6: =IF(A6="","",IF(C6="Payment Received",-IFERROR(G6,0),IF(C6="Monthly Rent Charge",IFERROR(E6,0)+IFERROR(F6,0),0)))
A7: 46066 | C7: Payment Received | E7: =IF(C7="Monthly Rent Charge",$D$3,"") | F7: =IF(C7="Monthly Rent Charge",$F$3,"") | G7: 3200 | H7: ubddq6egva | I7: =IF(A7="","",IF(C7="Payment Received",I6-IFERROR(G7,0),IF(C7="Monthly Rent Charge",I6+IFERROR(E7,0)+IFERROR(F7,0),I6)))
A8: =IF(B8="","",DATE(YEAR(TODAY()),MATCH(B8,{"January","February","March","April","May","June","July","August","September","October","November","December"},0),1)) | B8: March | C8: =IF(B8="","","Monthly Rent Charge") | E8: =IF(C8="Monthly Rent Charge",$D$3,"") | F8: =IF(C8="Monthly Rent Charge",$F$3,"") | I8: =IF(A8="","",IF(C8="Payment Received",I7-IFERROR(G8,0),IF(C8="Monthly Rent Charge",I7+IFERROR(E8,0)+IFERROR(F8,0),I7)))
A9: 46091 | C9: Payment Received | E9: =IF(C9="Monthly Rent Charge",$D$3,"") | F9: =IF(C9="Monthly Rent Charge",$F$3,"") | G9: 3200 | H9: UCADQ8RPFP | I9: =IF(A9="","",IF(C9="Payment Received",I8-IFERROR(G9,0),IF(C9="Monthly Rent Charge",I8+IFERROR(E9,0)+IFERROR(F9,0),I8)))
A10: =IF(B10="","",DATE(YEAR(TODAY()),MATCH(B10,{"January","February","March","April","May","June","July","August","September","October","November","December"},0),1)) | B10: April | C10: =IF(B10="","","Monthly Rent Charge") | E10: =IF(C10="Monthly Rent Charge",$D$3,"") | F10: =IF(C10="Monthly Rent Charge",$F$3,"") | I10: =IF(A10="","",IF(C10="Payment Received",I9-IFERROR(G10,0),IF(C10="Monthly Rent Charge",I9+IFERROR(E10,0)+IFERROR(F10,0),I9)))
A11: 46123 | C11: Payment Received | E11: =IF(C11="Monthly Rent Charge",$D$3,"") | F11: =IF(C11="Monthly Rent Charge",$F$3,"") | G11: 3200 | H11: UDBDQOANDR | I11: =IF(A11="","",IF(C11="Payment Received",I10-IFERROR(G11,0),IF(C11="Monthly Rent Charge",I10+IFERROR(E11,0)+IFERROR(F11,0),I10)))
A12: =IF(B12="","",DATE(YEAR(TODAY()),MATCH(B12,{"January","February","March","April","May","June","July","August","September","October","November","December"},0),1)) | B12: May | C12: =IF(B12="","","Monthly Rent Charge") | E12: =IF(C12="Monthly Rent Charge",$D$3,"") | F12: =IF(C12="Monthly Rent Charge",$F$3,"") | I12: =IF(AND(A12="",C12=""),"",IF(C12="Payment Received",I11-IFERROR(G12,0),IF(C12="Monthly Rent Charge",I11+IFERROR(E12,0)+IFERROR(F12,0),I11)))
A13: 46153 | C13: Payment Received | E13: =IF(C13="Monthly Rent Charge",$D$3,"") | F13: =IF(C13="Monthly Rent Charge",$F$3,"") | G13: 3200 | H13: UEBDQ3OJVX | I13: =IF(AND(A13="",C13=""),"",IF(C13="Payment Received",I12-IFERROR(G13,0),IF(C13="Monthly Rent Charge",I12+IFERROR(E13,0)+IFERROR(F13,0),I12)))
A14: =IF(B14="","",DATE(YEAR(TODAY()),MATCH(B14,{"January","February","March","April","May","June","July","August","September","October","November","December"},0),1)) | B14: June | C14: =IF(B14="","","Monthly Rent Charge") | E14: =IF(C14="Monthly Rent Charge",$D$3,"") | F14: =IF(C14="Monthly Rent Charge",$F$3,"") | I14: =IF(AND(A14="",C14=""),"",IF(C14="Payment Received",I13-IFERROR(G14,0),IF(C14="Monthly Rent Charge",I13+IFERROR(E14,0)+IFERROR(F14,0),I13)))
A15: 46185 | C15: Payment Received | E15: =IF(C15="Monthly Rent Charge",$D$3,"") | F15: =IF(C15="Monthly Rent Charge",$F$3,"") | G15: 3200 | H15: UFCDQ79PMC | I15: =IF(AND(A15="",C15=""),"",IF(C15="Payment Received",I14-IFERROR(G15,0),IF(C15="Monthly Rent Charge",I14+IFERROR(E15,0)+IFERROR(F15,0),I14)))
A16: =IF(B16="","",DATE(YEAR(TODAY()),MATCH(B16,{"January","February","March","April","May","June","July","August","September","October","November","December"},0),1)) | B16: July | C16: =IF(B16="","","Monthly Rent Charge") | E16: =IF(C16="Monthly Rent Charge",$D$3,"") | F16: =IF(C16="Monthly Rent Charge",$F$3,"") | I16: =IF(AND(A16="",C16=""),"",IF(C16="Payment Received",I15-IFERROR(G16,0),IF(C16="Monthly Rent Charge",I15+IFERROR(E16,0)+IFERROR(F16,0),I15)))
A17: 46216 | C17: Payment Received | E17: =IF(C17="Monthly Rent Charge",$D$3,"") | F17: =IF(C17="Monthly Rent Charge",$F$3,"") | G17: 3200 | H17: UGDDQARLX0 | I17: =IF(AND(A17="",C17=""),"",IF(C17="Payment Received",I16-IFERROR(G17,0),IF(C17="Monthly Rent Charge",I16+IFERROR(E17,0)+IFERROR(F17,0),IFERROR(I16,0))))
A18: =IF(B18="","",DATE(YEAR(TODAY()),MATCH(B18,{"January","February","March","April","May","June","July","August","September","October","November","December"},0),1)) | B18: August | C18: =IF(B18="","","Monthly Rent Charge") | E18: =IF(C18="Monthly Rent Charge",$D$3,"") | F18: =IF(C18="Monthly Rent Charge",$F$3,"") | I18: =IF(AND(A18="",C18=""),"",IF(C18="Payment Received",I17-IFERROR(G18,0),IF(C18="Monthly Rent Charge",I17+IFERROR(E18,0)+IFERROR(F18,0),IFERROR(I17,0))))
A19: 46246 | C19: Payment Received | E19: =IF(C19="Monthly Rent Charge",$D$3,"") | F19: =IF(C19="Monthly Rent Charge",$F$3,"") | G19: 3200 | H19: UHCDQ26GRT | I19: =IF(AND(A19="",C19=""),"",IF(C19="Payment Received",I18-IFERROR(G19,0),IF(C19="Monthly Rent Charge",I18+IFERROR(E19,0)+IFERROR(F19,0),IFERROR(I18,0))))
A20: =IF(B20="","",DATE(YEAR(TODAY()),MATCH(B20,{"January","February","March","April","May","June","July","August","September","October","November","December"},0),1)) | C20: =IF(B20="","","Monthly Rent Charge") | E20: =IF(C20="Monthly Rent Charge",$D$3,"") | F20: =IF(C20="Monthly Rent Charge",$F$3,"") | I20: =IF(AND(A20="",C20=""),"",IF(C20="Payment Received",I19-IFERROR(G20,0),IF(C20="Monthly Rent Charge",I19+IFERROR(E20,0)+IFERROR(F20,0),IFERROR(I19,0))))
A21: =IF(B21="","",DATE(YEAR(TODAY()),MATCH(B21,{"January","February","March","April","May","June","July","August","September","October","November","December"},0),1)) | C21: =IF(B21="","","Monthly Rent Charge") | E21: =IF(C21="Monthly Rent Charge",$D$3,"") | F21: =IF(C21="Monthly Rent Charge",$F$3,"") | I21: =IF(AND(A21="",C21=""),"",IF(C21="Payment Received",I20-IFERROR(G21,0),IF(C21="Monthly Rent Charge",I20+IFERROR(E21,0)+IFERROR(F21,0),IFERROR(I20,0))))
A22: =IF(B22="","",DATE(YEAR(TODAY()),MATCH(B22,{"January","February","March","April","May","June","July","August","September","October","November","December"},0),1)) | C22: =IF(B22="","","Monthly Rent Charge") | E22: =IF(C22="Monthly Rent Charge",$D$3,"") | F22: =IF(C22="Monthly Rent Charge",$F$3,"") | I22: =IF(AND(A22="",C22=""),"",IF(C22="Payment Received",I21-IFERROR(G22,0),IF(C22="Monthly Rent Charge",I21+IFERROR(E22,0)+IFERROR(F22,0),IFERROR(I21,0))))
A23: =IF(B23="","",DATE(YEAR(TODAY()),MATCH(B23,{"January","February","March","April","May","June","July","August","September","October","November","December"},0),1)) | C23: =IF(B23="","","Monthly Rent Charge") | E23: =IF(C23="Monthly Rent Charge",$D$3,"") | F23: =IF(C23="Monthly Rent Charge",$F$3,"") | I23: =IF(AND(A23="",C23=""),"",IF(C23="Payment Received",I22-IFERROR(G23,0),IF(C23="Monthly Rent Charge",I22+IFERROR(E23,0)+IFERROR(F23,0),IFERROR(I22,0))))
A24: =IF(B24="","",DATE(YEAR(TODAY()),MATCH(B24,{"January","February","March","April","May","June","July","August","September","October","November","December"},0),1)) | C24: =IF(B24="","","Monthly Rent Charge") | E24: =IF(C24="Monthly Rent Charge",$D$3,"") | F24: =IF(C24="Monthly Rent Charge",$F$3,"") | I24: =IF(AND(A24="",C24=""),"",IF(C24="Payment Received",I23-IFERROR(G24,0),IF(C24="Monthly Rent Charge",I23+IFERROR(E24,0)+IFERROR(F24,0),IFERROR(I23,0))))
A25: =IF(B25="","",DATE(YEAR(TODAY()),MATCH(B25,{"January","February","March","April","May","June","July","August","September","October","November","December"},0),1)) | C25: =IF(B25="","","Monthly Rent Charge") | E25: =IF(C25="Monthly Rent Charge",$D$3,"") | F25: =IF(C25="Monthly Rent Charge",$F$3,"") | I25: =IF(AND(A25="",C25=""),"",IF(C25="Payment Received",I24-IFERROR(G25,0),IF(C25="Monthly Rent Charge",I24+IFERROR(E25,0)+IFERROR(F25,0),IFERROR(I24,0))))
A26: =IF(B26="","",DATE(YEAR(TODAY()),MATCH(B26,{"January","February","March","April","May","June","July","August","September","October","November","December"},0),1)) | C26: =IF(B26="","","Monthly Rent Charge") | E26: =IF(C26="Monthly Rent Charge",$D$3,"") | F26: =IF(C26="Monthly Rent Charge",$F$3,"") | I26: =IF(AND(A26="",C26=""),"",IF(C26="Payment Received",I25-IFERROR(G26,0),IF(C26="Monthly Rent Charge",I25+IFERROR(E26,0)+IFERROR(F26,0),IFERROR(I25,0))))
A27: =IF(B27="","",DATE(YEAR(TODAY()),MATCH(B27,{"January","February","March","April","May","June","July","August","September","October","November","December"},0),1)) | C27: =IF(B27="","","Monthly Rent Charge") | E27: =IF(C27="Monthly Rent Charge",$D$3,"") | F27: =IF(C27="Monthly Rent Charge",$F$3,"") | I27: =IF(AND(A27="",C27=""),"",IF(C27="Payment Received",I26-IFERROR(G27,0),IF(C27="Monthly Rent Charge",I26+IFERROR(E27,0)+IFERROR(F27,0),IFERROR(I26,0))))
A28: =IF(B28="","",DATE(YEAR(TODAY()),MATCH(B28,{"January","February","March","April","May","June","July","August","September","October","November","December"},0),1)) | C28: =IF(B28="","","Monthly Rent Charge") | E28: =IF(C28="Monthly Rent Charge",$D$3,"") | F28: =IF(C28="Monthly Rent Charge",$F$3,"") | I28: =IF(AND(A28="",C28=""),"",IF(C28="Payment Received",I27-IFERROR(G28,0),IF(C28="Monthly Rent Charge",I27+IFERROR(E28,0)+IFERROR(F28,0),IFERROR(I27,0))))
A29: =IF(B29="","",DATE(YEAR(TODAY()),MATCH(B29,{"January","February","March","April","May","June","July","August","September","October","November","December"},0),1)) | C29: =IF(B29="","","Monthly Rent Charge") | E29: =IF(C29="Monthly Rent Charge",$D$3,"") | F29: =IF(C29="Monthly Rent Charge",$F$3,"") | I29: =IF(AND(A29="",C29=""),"",IF(C29="Payment Received",I28-IFERROR(G29,0),IF(C29="Monthly Rent Charge",I28+IFERROR(E29,0)+IFERROR(F29,0),IFERROR(I28,0))))
A30: =IF(B30="","",DATE(YEAR(TODAY()),MATCH(B30,{"January","February","March","April","May","June","July","August","September","October","November","December"},0),1)) | C30: =IF(B30="","","Monthly Rent Charge") | E30: =IF(C30="Monthly Rent Charge",$D$3,"") | F30: =IF(C30="Monthly Rent Charge",$F$3,"") | I30: =IF(AND(A30="",C30=""),"",IF(C30="Payment Received",I29-IFERROR(G30,0),IF(C30="Monthly Rent Charge",I29+IFERROR(E30,0)+IFERROR(F30,0),IFERROR(I29,0))))
A31: =IF(B31="","",DATE(YEAR(TODAY()),MATCH(B31,{"January","February","March","April","May","June","July","August","September","October","November","December"},0),1)) | C31: =IF(B31="","","Monthly Rent Charge") | E31: =IF(C31="Monthly Rent Charge",$D$3,"") | F31: =IF(C31="Monthly Rent Charge",$F$3,"") | I31: =IF(AND(A31="",C31=""),"",IF(C31="Payment Received",I30-IFERROR(G31,0),IF(C31="Monthly Rent Charge",I30+IFERROR(E31,0)+IFERROR(F31,0),IFERROR(I30,0))))

Sheet A6
A1: Unit A6 — Tenant Statement / Ledger
A2: Select a month to create a Monthly Rent Charge: the date fills as the first day of that month (current year) and description fills automatically. For a payment, leave Month blank and choose Payment Received.
A3: Unit | B3: A6 | C3: Current Rent | D3: 3000 | E3: Garbage | F3: 200 | G3: Current Balance | H3: =IFERROR(LOOKUP(9.99E+307,I6:I43),0) | I3: Tenant | J3: SAMUEL VICTOR BEET | K3: Deposit Held | L3: 0
A4: Current tenant only. When vacating → copy rows to Archive sheet, then clear this ledger.
A5: Date | B5: Month | C5: Description | D5: Tenant | E5: Rent Charged | F5: Garbage Charged | G5: Payment Received | H5: M-Pesa Reference | I5: Running Balance | J5: Remarks
A6: 45962 | B6: November | C6: =IF(B6="","","Monthly Rent Charge") | E6: =IF(C6="Monthly Rent Charge",$D$3,"") | F6: =IF(C6="Monthly Rent Charge",$F$3,"") | I6: =IF(A6="","",IF(C6="Payment Received",-IFERROR(G6,0),IF(C6="Monthly Rent Charge",IFERROR(E6,0)+IFERROR(F6,0),0)))
A7: 45982 | C7: Payment Received | E7: =IF(C7="Monthly Rent Charge",$D$3,"") | F7: =IF(C7="Monthly Rent Charge",$F$3,"") | G7: 3200 | H7: TKLA4SAS3T8 | I7: =IF(A7="","",IF(C7="Payment Received",I6-IFERROR(G7,0),IF(C7="Monthly Rent Charge",I6+IFERROR(E7,0)+IFERROR(F7,0),I6)))
A8: 45992 | B8: December | C8: =IF(B8="","","Monthly Rent Charge") | E8: =IF(C8="Monthly Rent Charge",$D$3,"") | F8: =IF(C8="Monthly Rent Charge",$F$3,"") | I8: =IF(A8="","",IF(C8="Payment Received",I7-IFERROR(G8,0),IF(C8="Monthly Rent Charge",I7+IFERROR(E8,0)+IFERROR(F8,0),I7)))
A9: 45994 | C9: Payment Received | E9: =IF(C9="Monthly Rent Charge",$D$3,"") | F9: =IF(C9="Monthly Rent Charge",$F$3,"") | G9: 2000 | H9: TL34SBU1VB | I9: =IF(A9="","",IF(C9="Payment Received",I8-IFERROR(G9,0),IF(C9="Monthly Rent Charge",I8+IFERROR(E9,0)+IFERROR(F9,0),I8)))
A10: 46004 | C10: Payment Received | E10: =IF(C10="Monthly Rent Charge",$D$3,"") | F10: =IF(C10="Monthly Rent Charge",$F$3,"") | G10: 1200 | H10: TDL4SOWW8K | I10: =IF(A10="","",IF(C10="Payment Received",I9-IFERROR(G10,0),IF(C10="Monthly Rent Charge",I9+IFERROR(E10,0)+IFERROR(F10,0),I9)))
A11: =IF(B11="","",DATE(YEAR(TODAY()),MATCH(B11,{"January","February","March","April","May","June","July","August","September","October","November","December"},0),1)) | B11: January | C11: =IF(B11="","","Monthly Rent Charge") | E11: =IF(C11="Monthly Rent Charge",$D$3,"") | F11: =IF(C11="Monthly Rent Charge",$F$3,"") | I11: =IF(A11="","",IF(C11="Payment Received",I10-IFERROR(G11,0),IF(C11="Monthly Rent Charge",I10+IFERROR(E11,0)+IFERROR(F11,0),I10)))
A12: 46028 | C12: Payment Received | E12: =IF(C12="Monthly Rent Charge",$D$3,"") | F12: =IF(C12="Monthly Rent Charge",$F$3,"") | G12: 1500 | H12: UA64S32JO1 | I12: =IF(A12="","",IF(C12="Payment Received",I11-IFERROR(G12,0),IF(C12="Monthly Rent Charge",I11+IFERROR(E12,0)+IFERROR(F12,0),I11)))
A13: 46038 | C13: Payment Received | E13: =IF(C13="Monthly Rent Charge",$D$3,"") | F13: =IF(C13="Monthly Rent Charge",$F$3,"") | G13: 1700 | H13: UAG4S3ZOC3 | I13: =IF(A13="","",IF(C13="Payment Received",I12-IFERROR(G13,0),IF(C13="Monthly Rent Charge",I12+IFERROR(E13,0)+IFERROR(F13,0),I12)))
A14: =IF(B14="","",DATE(YEAR(TODAY()),MATCH(B14,{"January","February","March","April","May","June","July","August","September","October","November","December"},0),1)) | B14: February | C14: =IF(B14="","","Monthly Rent Charge") | E14: =IF(C14="Monthly Rent Charge",$D$3,"") | F14: =IF(C14="Monthly Rent Charge",$F$3,"") | I14: =IF(A14="","",IF(C14="Payment Received",I13-IFERROR(G14,0),IF(C14="Monthly Rent Charge",I13+IFERROR(E14,0)+IFERROR(F14,0),I13)))
A15: 46057 | C15: Payment Received | E15: =IF(C15="Monthly Rent Charge",$D$3,"") | F15: =IF(C15="Monthly Rent Charge",$F$3,"") | G15: 1700 | H15: UB44S5QQGL | I15: =IF(A15="","",IF(C15="Payment Received",I14-IFERROR(G15,0),IF(C15="Monthly Rent Charge",I14+IFERROR(E15,0)+IFERROR(F15,0),I14)))
A16: 46077 | C16: Payment Received | E16: =IF(C16="Monthly Rent Charge",$D$3,"") | F16: =IF(C16="Monthly Rent Charge",$F$3,"") | G16: 1500 | H16: UBO4S7L8EH | I16: =IF(A16="","",IF(C16="Payment Received",I15-IFERROR(G16,0),IF(C16="Monthly Rent Charge",I15+IFERROR(E16,0)+IFERROR(F16,0),I15)))
A17: =IF(B17="","",DATE(YEAR(TODAY()),MATCH(B17,{"January","February","March","April","May","June","July","August","September","October","November","December"},0),1)) | B17: March | C17: =IF(B17="","","Monthly Rent Charge") | E17: =IF(C17="Monthly Rent Charge",$D$3,"") | F17: =IF(C17="Monthly Rent Charge",$F$3,"") | I17: =IF(A17="","",IF(C17="Payment Received",I16-IFERROR(G17,0),IF(C17="Monthly Rent Charge",I16+IFERROR(E17,0)+IFERROR(F17,0),I16)))
A18: 46090 | C18: Payment Received | E18: =IF(C18="Monthly Rent Charge",$D$3,"") | F18: =IF(C18="Monthly Rent Charge",$F$3,"") | G18: 2000 | H18: UC94S8TX9Y | I18: =IF(A18="","",IF(C18="Payment Received",I17-IFERROR(G18,0),IF(C18="Monthly Rent Charge",I17+IFERROR(E18,0)+IFERROR(F18,0),I17)))
A19: 46104 | C19: Payment Received | E19: =IF(C19="Monthly Rent Charge",$D$3,"") | F19: =IF(C19="Monthly Rent Charge",$F$3,"") | G19: 1200 | H19: UCN4SA7F8S | I19: =IF(A19="","",IF(C19="Payment Received",I18-IFERROR(G19,0),IF(C19="Monthly Rent Charge",I18+IFERROR(E19,0)+IFERROR(F19,0),I18)))
A20: =IF(B20="","",DATE(YEAR(TODAY()),MATCH(B20,{"January","February","March","April","May","June","July","August","September","October","November","December"},0),1)) | B20: April | C20: =IF(B20="","","Monthly Rent Charge") | E20: =IF(C20="Monthly Rent Charge",$D$3,"") | F20: =IF(C20="Monthly Rent Charge",$F$3,"") | I20: =IF(A20="","",IF(C20="Payment Received",I19-IFERROR(G20,0),IF(C20="Monthly Rent Charge",I19+IFERROR(E20,0)+IFERROR(F20,0),I19)))
A21: 46130 | C21: Payment Received | E21: =IF(C21="Monthly Rent Charge",$D$3,"") | F21: =IF(C21="Monthly Rent Charge",$F$3,"") | G21: 3200 | H21: UDI4S19MUS | I21: =IF(A21="","",IF(C21="Payment Received",I20-IFERROR(G21,0),IF(C21="Monthly Rent Charge",I20+IFERROR(E21,0)+IFERROR(F21,0),I20)))
A22: =IF(B22="","",DATE(YEAR(TODAY()),MATCH(B22,{"January","February","March","April","May","June","July","August","September","October","November","December"},0),1)) | B22: May | C22: =IF(B22="","","Monthly Rent Charge") | E22: =IF(C22="Monthly Rent Charge",$D$3,"") | F22: =IF(C22="Monthly Rent Charge",$F$3,"") | I22: =IF(A22="","",IF(C22="Payment Received",I21-IFERROR(G22,0),IF(C22="Monthly Rent Charge",I21+IFERROR(E22,0)+IFERROR(F22,0),I21)))
A23: 46148 | C23: Payment Received | E23: =IF(C23="Monthly Rent Charge",$D$3,"") | F23: =IF(C23="Monthly Rent Charge",$F$3,"") | G23: 1200 | H23: UE64S3C2RF | I23: =IF(A23="","",IF(C23="Payment Received",I22-IFERROR(G23,0),IF(C23="Monthly Rent Charge",I22+IFERROR(E23,0)+IFERROR(F23,0),I22)))
A24: =IF(B24="","",DATE(YEAR(TODAY()),MATCH(B24,{"January","February","March","April","May","June","July","August","September","October","November","December"},0),1)) | B24: June | C24: =IF(B24="","","Monthly Rent Charge") | E24: =IF(C24="Monthly Rent Charge",$D$3,"") | F24: =IF(C24="Monthly Rent Charge",$F$3,"") | I24: =IF(AND(A24="",C24=""),"",IF(C24="Payment Received",I23-IFERROR(G24,0),IF(C24="Monthly Rent Charge",I23+IFERROR(E24,0)+IFERROR(F24,0),I23)))
A25: =IF(B25="","",DATE(YEAR(TODAY()),MATCH(B25,{"January","February","March","April","May","June","July","August","September","October","November","December"},0),1)) | B25: July | C25: Monthly Rent Charge | E25: =IF(C25="Monthly Rent Charge",$D$3,"") | F25: =IF(C25="Monthly Rent Charge",$F$3,"") | I25: =IF(AND(A25="",C25=""),"",IF(C25="Payment Received",I24-IFERROR(G25,0),IF(C25="Monthly Rent Charge",I24+IFERROR(E25,0)+IFERROR(F25,0),I24)))
A26: 46204 | C26: Payment Received | E26: =IF(C26="Monthly Rent Charge",$D$3,"") | F26: =IF(C26="Monthly Rent Charge",$F$3,"") | G26: 5200 | H26: UG14S9PNPS | I26: =IF(AND(A26="",C26=""),"",IF(C26="Payment Received",I25-IFERROR(G26,0),IF(C26="Monthly Rent Charge",I25+IFERROR(E26,0)+IFERROR(F26,0),I25)))
A27: =IF(B27="","",DATE(YEAR(TODAY()),MATCH(B27,{"January","February","March","April","May","June","July","August","September","October","November","December"},0),1)) | B27: August | C27: =IF(B27="","","Monthly Rent Charge") | E27: =IF(C27="Monthly Rent Charge",$D$3,"") | F27: =IF(C27="Monthly Rent Charge",$F$3,"") | I27: =IF(AND(A27="",C27=""),"",IF(C27="Payment Received",I26-IFERROR(G27,0),IF(C27="Monthly Rent Charge",I26+IFERROR(E27,0)+IFERROR(F27,0),I26)))
A28: 46236 | C28: Payment Received | E28: =IF(C28="Monthly Rent Charge",$D$3,"") | F28: =IF(C28="Monthly Rent Charge",$F$3,"") | G28: 3200 | H28: UH24S1F3B7 | I28: =IF(AND(A28="",C28=""),"",IF(C28="Payment Received",I27-IFERROR(G28,0),IF(C28="Monthly Rent Charge",I27+IFERROR(E28,0)+IFERROR(F28,0),I27)))
A29: =IF(B29="","",DATE(YEAR(TODAY()),MATCH(B29,{"January","February","March","April","May","June","July","August","September","October","November","December"},0),1)) | C29: =IF(B29="","","Monthly Rent Charge") | E29: =IF(C29="Monthly Rent Charge",$D$3,"") | F29: =IF(C29="Monthly Rent Charge",$F$3,"") | I29: =IF(AND(A29="",C29=""),"",IF(C29="Payment Received",I28-IFERROR(G29,0),IF(C29="Monthly Rent Charge",I28+IFERROR(E29,0)+IFERROR(F29,0),IFERROR(I28,0))))
A30: =IF(B30="","",DATE(YEAR(TODAY()),MATCH(B30,{"January","February","March","April","May","June","July","August","September","October","November","December"},0),1)) | C30: =IF(B30="","","Monthly Rent Charge") | E30: =IF(C30="Monthly Rent Charge",$D$3,"") | F30: =IF(C30="Monthly Rent Charge",$F$3,"") | I30: =IF(AND(A30="",C30=""),"",IF(C30="Payment Received",I29-IFERROR(G30,0),IF(C30="Monthly Rent Charge",I29+IFERROR(E30,0)+IFERROR(F30,0),IFERROR(I29,0))))
A31: =IF(B31="","",DATE(YEAR(TODAY()),MATCH(B31,{"January","February","March","April","May","June","July","August","September","October","November","December"},0),1)) | C31: =IF(B31="","","Monthly Rent Charge") | E31: =IF(C31="Monthly Rent Charge",$D$3,"") | F31: =IF(C31="Monthly Rent Charge",$F$3,"") | I31: =IF(AND(A31="",C31=""),"",IF(C31="Payment Received",I30-IFERROR(G31,0),IF(C31="Monthly Rent Charge",I30+IFERROR(E31,0)+IFERROR(F31,0),IFERROR(I30,0))))
A32: =IF(B32="","",DATE(YEAR(TODAY()),MATCH(B32,{"January","February","March","April","May","June","July","August","September","October","November","December"},0),1)) | C32: =IF(B32="","","Monthly Rent Charge") | E32: =IF(C32="Monthly Rent Charge",$D$3,"") | F32: =IF(C32="Monthly Rent Charge",$F$3,"") | I32: =IF(AND(A32="",C32=""),"",IF(C32="Payment Received",I31-IFERROR(G32,0),IF(C32="Monthly Rent Charge",I31+IFERROR(E32,0)+IFERROR(F32,0),IFERROR(I31,0))))
A33: =IF(B33="","",DATE(YEAR(TODAY()),MATCH(B33,{"January","February","March","April","May","June","July","August","September","October","November","December"},0),1)) | C33: =IF(B33="","","Monthly Rent Charge") | E33: =IF(C33="Monthly Rent Charge",$D$3,"") | F33: =IF(C33="Monthly Rent Charge",$F$3,"") | I33: =IF(AND(A33="",C33=""),"",IF(C33="Payment Received",I32-IFERROR(G33,0),IF(C33="Monthly Rent Charge",I32+IFERROR(E33,0)+IFERROR(F33,0),IFERROR(I32,0))))
A34: =IF(B34="","",DATE(YEAR(TODAY()),MATCH(B34,{"January","February","March","April","May","June","July","August","September","October","November","December"},0),1)) | C34: =IF(B34="","","Monthly Rent Charge") | E34: =IF(C34="Monthly Rent Charge",$D$3,"") | F34: =IF(C34="Monthly Rent Charge",$F$3,"") | I34: =IF(AND(A34="",C34=""),"",IF(C34="Payment Received",I33-IFERROR(G34,0),IF(C34="Monthly Rent Charge",I33+IFERROR(E34,0)+IFERROR(F34,0),IFERROR(I33,0))))
A35: =IF(B35="","",DATE(YEAR(TODAY()),MATCH(B35,{"January","February","March","April","May","June","July","August","September","October","November","December"},0),1)) | C35: =IF(B35="","","Monthly Rent Charge") | E35: =IF(C35="Monthly Rent Charge",$D$3,"") | F35: =IF(C35="Monthly Rent Charge",$F$3,"") | I35: =IF(AND(A35="",C35=""),"",IF(C35="Payment Received",I34-IFERROR(G35,0),IF(C35="Monthly Rent Charge",I34+IFERROR(E35,0)+IFERROR(F35,0),IFERROR(I34,0))))
A36: =IF(B36="","",DATE(YEAR(TODAY()),MATCH(B36,{"January","February","March","April","May","June","July","August","September","October","November","December"},0),1)) | C36: =IF(B36="","","Monthly Rent Charge") | E36: =IF(C36="Monthly Rent Charge",$D$3,"") | F36: =IF(C36="Monthly Rent Charge",$F$3,"") | I36: =IF(AND(A36="",C36=""),"",IF(C36="Payment Received",I35-IFERROR(G36,0),IF(C36="Monthly Rent Charge",I35+IFERROR(E36,0)+IFERROR(F36,0),IFERROR(I35,0))))
A37: =IF(B37="","",DATE(YEAR(TODAY()),MATCH(B37,{"January","February","March","April","May","June","July","August","September","October","November","December"},0),1)) | C37: =IF(B37="","","Monthly Rent Charge") | E37: =IF(C37="Monthly Rent Charge",$D$3,"") | F37: =IF(C37="Monthly Rent Charge",$F$3,"") | I37: =IF(AND(A37="",C37=""),"",IF(C37="Payment Received",I36-IFERROR(G37,0),IF(C37="Monthly Rent Charge",I36+IFERROR(E37,0)+IFERROR(F37,0),IFERROR(I36,0))))
A38: =IF(B38="","",DATE(YEAR(TODAY()),MATCH(B38,{"January","February","March","April","May","June","July","August","September","October","November","December"},0),1)) | C38: =IF(B38="","","Monthly Rent Charge") | E38: =IF(C38="Monthly Rent Charge",$D$3,"") | F38: =IF(C38="Monthly Rent Charge",$F$3,"") | I38: =IF(AND(A38="",C38=""),"",IF(C38="Payment Received",I37-IFERROR(G38,0),IF(C38="Monthly Rent Charge",I37+IFERROR(E38,0)+IFERROR(F38,0),IFERROR(I37,0))))
A39: =IF(B39="","",DATE(YEAR(TODAY()),MATCH(B39,{"January","February","March","April","May","June","July","August","September","October","November","December"},0),1)) | C39: =IF(B39="","","Monthly Rent Charge") | E39: =IF(C39="Monthly Rent Charge",$D$3,"") | F39: =IF(C39="Monthly Rent Charge",$F$3,"") | I39: =IF(AND(A39="",C39=""),"",IF(C39="Payment Received",I38-IFERROR(G39,0),IF(C39="Monthly Rent Charge",I38+IFERROR(E39,0)+IFERROR(F39,0),IFERROR(I38,0))))
A40: =IF(B40="","",DATE(YEAR(TODAY()),MATCH(B40,{"January","February","March","April","May","June","July","August","September","October","November","December"},0),1)) | C40: =IF(B40="","","Monthly Rent Charge") | E40: =IF(C40="Monthly Rent Charge",$D$3,"") | F40: =IF(C40="Monthly Rent Charge",$F$3,"") | I40: =IF(AND(A40="",C40=""),"",IF(C40="Payment Received",I39-IFERROR(G40,0),IF(C40="Monthly Rent Charge",I39+IFERROR(E40,0)+IFERROR(F40,0),IFERROR(I39,0))))
... A43: =IF(B43="","",DATE(YEAR(TODAY()),MATCH(B43,{"January","February","March","April","May","June","July","August","September","October","November","December"},0),1)) | C43: =IF(B43="","","Monthly Rent Charge") | E43: =IF(C43="Monthly Rent Charge",$D$3,"") | F43: =IF(C43="Monthly Rent Charge",$F$3,"") | I43: =IF(AND(A43="",C43=""),"",IF(C43="Payment Received",I42-IFERROR(G43,0),IF(C43="Monthly Rent Charge",I42+IFERROR(E43,0)+IFERROR(F43,0),IFERROR(I42,0))))

Sheet A7
A1: Unit A7 — Tenant Statement / Ledger
A2: Select a month to create a Monthly Rent Charge: the date fills as the first day of that month (current year) and description fills automatically. For a payment, leave Month blank and choose Payment Received.
A3: Unit | B3: A7 | C3: Current Rent | D3: 3000 | E3: Garbage | F3: 100 | G3: Current Balance | H3: =IFERROR(LOOKUP(9.99E+307,I6:I69),0) | I3: Tenant | J3: ODENY ODONGO | K3: Deposit Held | L3: 0
A4: Current tenant only. When vacating → copy rows to Archive sheet, then clear this ledger.
A5: Date | B5: Month | C5: Description | D5: Tenant | E5: Rent Charged | F5: Garbage Charged | G5: Payment Received | H5: M-Pesa Reference | I5: Running Balance | J5: Remarks
A6: 45413 | B6: May | C6: =IF(B6="","","Monthly Rent Charge") | E6: =IF(C6="Monthly Rent Charge",$D$3,"") | F6: =IF(C6="Monthly Rent Charge",$F$3,"") | I6: =IF(A6="","",IF(C6="Payment Received",-IFERROR(G6,0),IF(C6="Monthly Rent Charge",IFERROR(E6,0)+IFERROR(F6,0),0)))
A7: 45428 | C7: Payment Received | E7: =IF(C7="Monthly Rent Charge",$D$3,"") | F7: =IF(C7="Monthly Rent Charge",$F$3,"") | G7: 3100 | I7: =IF(A7="","",IF(C7="Payment Received",I6-IFERROR(G7,0),IF(C7="Monthly Rent Charge",I6+IFERROR(E7,0)+IFERROR(F7,0),I6)))
A8: 45444 | B8: June | C8: =IF(B8="","","Monthly Rent Charge") | E8: =IF(C8="Monthly Rent Charge",$D$3,"") | F8: =IF(C8="Monthly Rent Charge",$F$3,"") | I8: =IF(A8="","",IF(C8="Payment Received",I7-IFERROR(G8,0),IF(C8="Monthly Rent Charge",I7+IFERROR(E8,0)+IFERROR(F8,0),I7)))
A9: 45468 | C9: Payment Received | E9: =IF(C9="Monthly Rent Charge",$D$3,"") | F9: =IF(C9="Monthly Rent Charge",$F$3,"") | G9: 3100 | I9: =IF(A9="","",IF(C9="Payment Received",I8-IFERROR(G9,0),IF(C9="Monthly Rent Charge",I8+IFERROR(E9,0)+IFERROR(F9,0),I8)))
A10: 45474 | B10: July | C10: =IF(B10="","","Monthly Rent Charge") | E10: =IF(C10="Monthly Rent Charge",$D$3,"") | F10: =IF(C10="Monthly Rent Charge",$F$3,"") | I10: =IF(A10="","",IF(C10="Payment Received",I9-IFERROR(G10,0),IF(C10="Monthly Rent Charge",I9+IFERROR(E10,0)+IFERROR(F10,0),I9)))
A11: 45491 | C11: Payment Received | E11: =IF(C11="Monthly Rent Charge",$D$3,"") | F11: =IF(C11="Monthly Rent Charge",$F$3,"") | G11: 3100 | I11: =IF(A11="","",IF(C11="Payment Received",I10-IFERROR(G11,0),IF(C11="Monthly Rent Charge",I10+IFERROR(E11,0)+IFERROR(F11,0),I10)))
A12: 45505 | B12: August | C12: =IF(B12="","","Monthly Rent Charge") | E12: =IF(C12="Monthly Rent Charge",$D$3,"") | F12: =IF(C12="Monthly Rent Charge",$F$3,"") | I12: =IF(A12="","",IF(C12="Payment Received",I11-IFERROR(G12,0),IF(C12="Monthly Rent Charge",I11+IFERROR(E12,0)+IFERROR(F12,0),I11)))
A13: 45525 | C13: Payment Received | E13: =IF(C13="Monthly Rent Charge",$D$3,"") | F13: =IF(C13="Monthly Rent Charge",$F$3,"") | G13: 3000 | I13: =IF(A13="","",IF(C13="Payment Received",I12-IFERROR(G13,0),IF(C13="Monthly Rent Charge",I12+IFERROR(E13,0)+IFERROR(F13,0),I12)))
A14: 45536 | B14: September | C14: =IF(B14="","","Monthly Rent Charge") | E14: =IF(C14="Monthly Rent Charge",$D$3,"") | F14: =IF(C14="Monthly Rent Charge",$F$3,"") | I14: =IF(A14="","",IF(C14="Payment Received",I13-IFERROR(G14,0),IF(C14="Monthly Rent Charge",I13+IFERROR(E14,0)+IFERROR(F14,0),I13)))
A15: 45566 | B15: October | C15: =IF(B15="","","Monthly Rent Charge") | E15: =IF(C15="Monthly Rent Charge",$D$3,"") | F15: =IF(C15="Monthly Rent Charge",$F$3,"") | I15: =IF(A15="","",IF(C15="Payment Received",I14-IFERROR(G15,0),IF(C15="Monthly Rent Charge",I14+IFERROR(E15,0)+IFERROR(F15,0),I14)))
A16: 45572 | C16: Payment Received | E16: =IF(C16="Monthly Rent Charge",$D$3,"") | F16: =IF(C16="Monthly Rent Charge",$F$3,"") | G16: 3100 | I16: =IF(A16="","",IF(C16="Payment Received",I15-IFERROR(G16,0),IF(C16="Monthly Rent Charge",I15+IFERROR(E16,0)+IFERROR(F16,0),I15)))
A17: 45597 | B17: November | C17: =IF(B17="","","Monthly Rent Charge") | E17: =IF(C17="Monthly Rent Charge",$D$3,"") | F17: =IF(C17="Monthly Rent Charge",$F$3,"") | I17: =IF(A17="","",IF(C17="Payment Received",I16-IFERROR(G17,0),IF(C17="Monthly Rent Charge",I16+IFERROR(E17,0)+IFERROR(F17,0),I16)))
A18: 45614 | C18: Payment Received | E18: =IF(C18="Monthly Rent Charge",$D$3,"") | F18: =IF(C18="Monthly Rent Charge",$F$3,"") | G18: 3000 | I18: =IF(A18="","",IF(C18="Payment Received",I17-IFERROR(G18,0),IF(C18="Monthly Rent Charge",I17+IFERROR(E18,0)+IFERROR(F18,0),I17)))
A19: 45627 | B19: December | C19: =IF(B19="","","Monthly Rent Charge") | E19: =IF(C19="Monthly Rent Charge",$D$3,"") | F19: =IF(C19="Monthly Rent Charge",$F$3,"") | I19: =IF(A19="","",IF(C19="Payment Received",I18-IFERROR(G19,0),IF(C19="Monthly Rent Charge",I18+IFERROR(E19,0)+IFERROR(F19,0),I18)))
A20: 45627 | C20: Payment Received | E20: =IF(C20="Monthly Rent Charge",$D$3,"") | F20: =IF(C20="Monthly Rent Charge",$F$3,"") | G20: 3000 | I20: =IF(A20="","",IF(C20="Payment Received",I19-IFERROR(G20,0),IF(C20="Monthly Rent Charge",I19+IFERROR(E20,0)+IFERROR(F20,0),I19)))
A21: 45658 | B21: January | C21: =IF(B21="","","Monthly Rent Charge") | E21: =IF(C21="Monthly Rent Charge",$D$3,"") | F21: =IF(C21="Monthly Rent Charge",$F$3,"") | I21: =IF(A21="","",IF(C21="Payment Received",I20-IFERROR(G21,0),IF(C21="Monthly Rent Charge",I20+IFERROR(E21,0)+IFERROR(F21,0),I20)))
A22: 45661 | C22: Payment Received | E22: =IF(C22="Monthly Rent Charge",$D$3,"") | F22: =IF(C22="Monthly Rent Charge",$F$3,"") | G22: 3000 | H22: TA48VOSWB2 | I22: =IF(A22="","",IF(C22="Payment Received",I21-IFERROR(G22,0),IF(C22="Monthly Rent Charge",I21+IFERROR(E22,0)+IFERROR(F22,0),I21)))
A23: 45689 | B23: February | C23: =IF(B23="","","Monthly Rent Charge") | E23: =IF(C23="Monthly Rent Charge",$D$3,"") | F23: =IF(C23="Monthly Rent Charge",$F$3,"") | I23: =IF(A23="","",IF(C23="Payment Received",I22-IFERROR(G23,0),IF(C23="Monthly Rent Charge",I22+IFERROR(E23,0)+IFERROR(F23,0),I22)))
A24: 45705 | C24: Payment Received | E24: =IF(C24="Monthly Rent Charge",$D$3,"") | F24: =IF(C24="Monthly Rent Charge",$F$3,"") | G24: 4500 | H24: TBH1CXME8H | I24: =IF(A24="","",IF(C24="Payment Received",I23-IFERROR(G24,0),IF(C24="Monthly Rent Charge",I23+IFERROR(E24,0)+IFERROR(F24,0),I23)))
A25: 45717 | B25: March | C25: =IF(B25="","","Monthly Rent Charge") | E25: =IF(C25="Monthly Rent Charge",$D$3,"") | F25: =IF(C25="Monthly Rent Charge",$F$3,"") | I25: =IF(A25="","",IF(C25="Payment Received",I24-IFERROR(G25,0),IF(C25="Monthly Rent Charge",I24+IFERROR(E25,0)+IFERROR(F25,0),I24)))
A26: 45739 | C26: Payment Received | E26: =IF(C26="Monthly Rent Charge",$D$3,"") | F26: =IF(C26="Monthly Rent Charge",$F$3,"") | G26: 4000 | H26: TCN2UO3OLA | I26: =IF(A26="","",IF(C26="Payment Received",I25-IFERROR(G26,0),IF(C26="Monthly Rent Charge",I25+IFERROR(E26,0)+IFERROR(F26,0),I25)))
A27: 45748 | B27: April | C27: =IF(B27="","","Monthly Rent Charge") | E27: =IF(C27="Monthly Rent Charge",$D$3,"") | F27: =IF(C27="Monthly Rent Charge",$F$3,"") | I27: =IF(A27="","",IF(C27="Payment Received",I26-IFERROR(G27,0),IF(C27="Monthly Rent Charge",I26+IFERROR(E27,0)+IFERROR(F27,0),I26)))
A28: 45778 | B28: May | C28: =IF(B28="","","Monthly Rent Charge") | E28: =IF(C28="Monthly Rent Charge",$D$3,"") | F28: =IF(C28="Monthly Rent Charge",$F$3,"") | I28: =IF(A28="","",IF(C28="Payment Received",I27-IFERROR(G28,0),IF(C28="Monthly Rent Charge",I27+IFERROR(E28,0)+IFERROR(F28,0),I27)))
A29: 45787 | C29: Payment Received | E29: =IF(C29="Monthly Rent Charge",$D$3,"") | F29: =IF(C29="Monthly Rent Charge",$F$3,"") | G29: 4000 | H29: TEA154FEJT | I29: =IF(A29="","",IF(C29="Payment Received",I28-IFERROR(G29,0),IF(C29="Monthly Rent Charge",I28+IFERROR(E29,0)+IFERROR(F29,0),I28)))
A30: 45809 | B30: June | C30: =IF(B30="","","Monthly Rent Charge") | E30: =IF(C30="Monthly Rent Charge",$D$3,"") | F30: =IF(C30="Monthly Rent Charge",$F$3,"") | I30: =IF(A30="","",IF(C30="Payment Received",I29-IFERROR(G30,0),IF(C30="Monthly Rent Charge",I29+IFERROR(E30,0)+IFERROR(F30,0),I29)))
A31: 45839 | B31: July | C31: =IF(B31="","","Monthly Rent Charge") | E31: =IF(C31="Monthly Rent Charge",$D$3,"") | F31: =IF(C31="Monthly Rent Charge",$F$3,"") | I31: =IF(A31="","",IF(C31="Payment Received",I30-IFERROR(G31,0),IF(C31="Monthly Rent Charge",I30+IFERROR(E31,0)+IFERROR(F31,0),I30)))
A32: 45850 | C32: Payment Received | E32: =IF(C32="Monthly Rent Charge",$D$3,"") | F32: =IF(C32="Monthly Rent Charge",$F$3,"") | G32: 5000 | H32: TGC9R2RCKV | I32: =IF(A32="","",IF(C32="Payment Received",I31-IFERROR(G32,0),IF(C32="Monthly Rent Charge",I31+IFERROR(E32,0)+IFERROR(F32,0),I31)))
A33: 45870 | B33: August | C33: =IF(B33="","","Monthly Rent Charge") | E33: =IF(C33="Monthly Rent Charge",$D$3,"") | F33: =IF(C33="Monthly Rent Charge",$F$3,"") | I33: =IF(A33="","",IF(C33="Payment Received",I32-IFERROR(G33,0),IF(C33="Monthly Rent Charge",I32+IFERROR(E33,0)+IFERROR(F33,0),I32)))
A34: 45883 | C34: Payment Received | E34: =IF(C34="Monthly Rent Charge",$D$3,"") | F34: =IF(C34="Monthly Rent Charge",$F$3,"") | G34: 4000 | H34: THE89DS530 | I34: =IF(A34="","",IF(C34="Payment Received",I33-IFERROR(G34,0),IF(C34="Monthly Rent Charge",I33+IFERROR(E34,0)+IFERROR(F34,0),I33)))
A35: 45901 | B35: September | C35: =IF(B35="","","Monthly Rent Charge") | E35: =IF(C35="Monthly Rent Charge",$D$3,"") | F35: =IF(C35="Monthly Rent Charge",$F$3,"") | I35: =IF(A35="","",IF(C35="Payment Received",I34-IFERROR(G35,0),IF(C35="Monthly Rent Charge",I34+IFERROR(E35,0)+IFERROR(F35,0),I34)))
A36: 45911 | C36: Payment Received | E36: =IF(C36="Monthly Rent Charge",$D$3,"") | F36: =IF(C36="Monthly Rent Charge",$F$3,"") | G36: 3100 | H36: TIB5D4NWMV | I36: =IF(A36="","",IF(C36="Payment Received",I35-IFERROR(G36,0),IF(C36="Monthly Rent Charge",I35+IFERROR(E36,0)+IFERROR(F36,0),I35)))
A37: 45931 | B37: October | C37: =IF(B37="","","Monthly Rent Charge") | E37: =IF(C37="Monthly Rent Charge",$D$3,"") | F37: =IF(C37="Monthly Rent Charge",$F$3,"") | I37: =IF(A37="","",IF(C37="Payment Received",I36-IFERROR(G37,0),IF(C37="Monthly Rent Charge",I36+IFERROR(E37,0)+IFERROR(F37,0),I36)))
A38: 45956 | C38: Payment Received | E38: =IF(C38="Monthly Rent Charge",$D$3,"") | F38: =IF(C38="Monthly Rent Charge",$F$3,"") | G38: 3100 | H38: TJQIU8C8Q9 | I38: =IF(A38="","",IF(C38="Payment Received",I37-IFERROR(G38,0),IF(C38="Monthly Rent Charge",I37+IFERROR(E38,0)+IFERROR(F38,0),I37)))
A39: 45962 | B39: November | C39: =IF(B39="","","Monthly Rent Charge") | E39: =IF(C39="Monthly Rent Charge",$D$3,"") | F39: =IF(C39="Monthly Rent Charge",$F$3,"") | I39: =IF(A39="","",IF(C39="Payment Received",I38-IFERROR(G39,0),IF(C39="Monthly Rent Charge",I38+IFERROR(E39,0)+IFERROR(F39,0),I38)))
A40: 45986 | C40: Payment Received | E40: =IF(C40="Monthly Rent Charge",$D$3,"") | F40: =IF(C40="Monthly Rent Charge",$F$3,"") | G40: 3100 | H40: TKPIUB3KFA | I40: =IF(A40="","",IF(C40="Payment Received",I39-IFERROR(G40,0),IF(C40="Monthly Rent Charge",I39+IFERROR(E40,0)+IFERROR(F40,0),I39)))
A41: 45992 | B41: December | C41: =IF(B41="","","Monthly Rent Charge") | E41: =IF(C41="Monthly Rent Charge",$D$3,"") | F41: =IF(C41="Monthly Rent Charge",$F$3,"") | I41: =IF(A41="","",IF(C41="Payment Received",I40-IFERROR(G41,0),IF(C41="Monthly Rent Charge",I40+IFERROR(E41,0)+IFERROR(F41,0),I40)))
A42: =IF(B42="","",DATE(YEAR(TODAY()),MATCH(B42,{"January","February","March","April","May","June","July","August","September","October","November","December"},0),1)) | B42: January | C42: Monthly Rent Charge | E42: =IF(C42="Monthly Rent Charge",$D$3,"") | F42: =IF(C42="Monthly Rent Charge",$F$3,"") | I42: =IF(A42="","",IF(C42="Payment Received",I41-IFERROR(G42,0),IF(C42="Monthly Rent Charge",I41+IFERROR(E42,0)+IFERROR(F42,0),I41)))
A43: 46028 | C43: Payment Received | E43: =IF(C43="Monthly Rent Charge",$D$3,"") | F43: =IF(C43="Monthly Rent Charge",$F$3,"") | G43: 4000 | H43: ua6iu2y99K | I43: =IF(A43="","",IF(C43="Payment Received",I42-IFERROR(G43,0),IF(C43="Monthly Rent Charge",I42+IFERROR(E43,0)+IFERROR(F43,0),I42)))
A44: =IF(B44="","",DATE(YEAR(TODAY()),MATCH(B44,{"January","February","March","April","May","June","July","August","September","October","November","December"},0),1)) | B44: February | C44: =IF(B44="","","Monthly Rent Charge") | E44: =IF(C44="Monthly Rent Charge",$D$3,"") | F44: =IF(C44="Monthly Rent Charge",$F$3,"") | I44: =IF(A44="","",IF(C44="Payment Received",I43-IFERROR(G44,0),IF(C44="Monthly Rent Charge",I43+IFERROR(E44,0)+IFERROR(F44,0),I43)))
A45: 46073 | C45: Payment Received | E45: =IF(C45="Monthly Rent Charge",$D$3,"") | F45: =IF(C45="Monthly Rent Charge",$F$3,"") | G45: 4100 | H45: UBKIU73PZH | I45: =IF(A45="","",IF(C45="Payment Received",I44-IFERROR(G45,0),IF(C45="Monthly Rent Charge",I44+IFERROR(E45,0)+IFERROR(F45,0),I44)))
A46: =IF(B46="","",DATE(YEAR(TODAY()),MATCH(B46,{"January","February","March","April","May","June","July","August","September","October","November","December"},0),1)) | B46: March | C46: =IF(B46="","","Monthly Rent Charge") | E46: =IF(C46="Monthly Rent Charge",$D$3,"") | F46: =IF(C46="Monthly Rent Charge",$F$3,"") | I46: =IF(A46="","",IF(C46="Payment Received",I45-IFERROR(G46,0),IF(C46="Monthly Rent Charge",I45+IFERROR(E46,0)+IFERROR(F46,0),I45)))
A47: 46100 | C47: Payment Received | E47: =IF(C47="Monthly Rent Charge",$D$3,"") | F47: =IF(C47="Monthly Rent Charge",$F$3,"") | G47: 4100 | H47: UCJIU9OJZN | I47: =IF(A47="","",IF(C47="Payment Received",I46-IFERROR(G47,0),IF(C47="Monthly Rent Charge",I46+IFERROR(E47,0)+IFERROR(F47,0),I46)))
A48: =IF(B48="","",DATE(YEAR(TODAY()),MATCH(B48,{"January","February","March","April","May","June","July","August","September","October","November","December"},0),1)) | B48: April | C48: =IF(B48="","","Monthly Rent Charge") | E48: =IF(C48="Monthly Rent Charge",$D$3,"") | F48: =IF(C48="Monthly Rent Charge",$F$3,"") | I48: =IF(A48="","",IF(C48="Payment Received",I47-IFERROR(G48,0),IF(C48="Monthly Rent Charge",I47+IFERROR(E48,0)+IFERROR(F48,0),I47)))
A49: 46137 | C49: Payment Received | E49: =IF(C49="Monthly Rent Charge",$D$3,"") | F49: =IF(C49="Monthly Rent Charge",$F$3,"") | G49: 3000 | H49: UDPIU20RHL | I49: =IF(A49="","",IF(C49="Payment Received",I48-IFERROR(G49,0),IF(C49="Monthly Rent Charge",I48+IFERROR(E49,0)+IFERROR(F49,0),I48)))
A50: =IF(B50="","",DATE(YEAR(TODAY()),MATCH(B50,{"January","February","March","April","May","June","July","August","September","October","November","December"},0),1)) | B50: May | C50: =IF(B50="","","Monthly Rent Charge") | E50: =IF(C50="Monthly Rent Charge",$D$3,"") | F50: =IF(C50="Monthly Rent Charge",$F$3,"") | I50: =IF(AND(A50="",C50=""),"",IF(C50="Payment Received",I49-IFERROR(G50,0),IF(C50="Monthly Rent Charge",I49+IFERROR(E50,0)+IFERROR(F50,0),I49)))
A51: =IF(B51="","",DATE(YEAR(TODAY()),MATCH(B51,{"January","February","March","April","May","June","July","August","September","October","November","December"},0),1)) | B51: June | C51: =IF(B51="","","Monthly Rent Charge") | E51: =IF(C51="Monthly Rent Charge",$D$3,"") | F51: =IF(C51="Monthly Rent Charge",$F$3,"") | I51: =IF(AND(A51="",C51=""),"",IF(C51="Payment Received",I50-IFERROR(G51,0),IF(C51="Monthly Rent Charge",I50+IFERROR(E51,0)+IFERROR(F51,0),I50)))
A52: 46183 | C52: Payment Received | E52: =IF(C52="Monthly Rent Charge",$D$3,"") | F52: =IF(C52="Monthly Rent Charge",$F$3,"") | G52: 4000 | H52: UFAIU76PUE | I52: =IF(AND(A52="",C52=""),"",IF(C52="Payment Received",I51-IFERROR(G52,0),IF(C52="Monthly Rent Charge",I51+IFERROR(E52,0)+IFERROR(F52,0),I51)))
A53: =IF(B53="","",DATE(YEAR(TODAY()),MATCH(B53,{"January","February","March","April","May","June","July","August","September","October","November","December"},0),1)) | B53: July | C53: =IF(B53="","","Monthly Rent Charge") | E53: =IF(C53="Monthly Rent Charge",$D$3,"") | F53: =IF(C53="Monthly Rent Charge",$F$3,"") | I53: =IF(AND(A53="",C53=""),"",IF(C53="Payment Received",I52-IFERROR(G53,0),IF(C53="Monthly Rent Charge",I52+IFERROR(E53,0)+IFERROR(F53,0),I52)))
A54: =IF(B54="","",DATE(YEAR(TODAY()),MATCH(B54,{"January","February","March","April","May","June","July","August","September","October","November","December"},0),1)) | B54: August | C54: =IF(B54="","","Monthly Rent Charge") | E54: =IF(C54="Monthly Rent Charge",$D$3,"") | F54: =IF(C54="Monthly Rent Charge",$F$3,"") | I54: =IF(AND(A54="",C54=""),"",IF(C54="Payment Received",I53-IFERROR(G54,0),IF(C54="Monthly Rent Charge",I53+IFERROR(E54,0)+IFERROR(F54,0),I53)))
A55: 46235 | C55: Payment Received | E55: =IF(C55="Monthly Rent Charge",$D$3,"") | F55: =IF(C55="Monthly Rent Charge",$F$3,"") | G55: 4500 | I55: =IF(AND(A55="",C55=""),"",IF(C55="Payment Received",I54-IFERROR(G55,0),IF(C55="Monthly Rent Charge",I54+IFERROR(E55,0)+IFERROR(F55,0),IFERROR(I54,0)))) | J55: CASH
A56: =IF(B56="","",DATE(YEAR(TODAY()),MATCH(B56,{"January","February","March","April","May","June","July","August","September","October","November","December"},0),1)) | C56: =IF(B56="","","Monthly Rent Charge") | E56: =IF(C56="Monthly Rent Charge",$D$3,"") | F56: =IF(C56="Monthly Rent Charge",$F$3,"") | I56: =IF(AND(A56="",C56=""),"",IF(C56="Payment Received",I55-IFERROR(G56,0),IF(C56="Monthly Rent Charge",I55+IFERROR(E56,0)+IFERROR(F56,0),IFERROR(I55,0))))
A57: =IF(B57="","",DATE(YEAR(TODAY()),MATCH(B57,{"January","February","March","April","May","June","July","August","September","October","November","December"},0),1)) | C57: =IF(B57="","","Monthly Rent Charge") | E57: =IF(C57="Monthly Rent Charge",$D$3,"") | F57: =IF(C57="Monthly Rent Charge",$F$3,"") | I57: =IF(AND(A57="",C57=""),"",IF(C57="Payment Received",I56-IFERROR(G57,0),IF(C57="Monthly Rent Charge",I56+IFERROR(E57,0)+IFERROR(F57,0),IFERROR(I56,0))))
A58: =IF(B58="","",DATE(YEAR(TODAY()),MATCH(B58,{"January","February","March","April","May","June","July","August","September","October","November","December"},0),1)) | C58: =IF(B58="","","Monthly Rent Charge") | E58: =IF(C58="Monthly Rent Charge",$D$3,"") | F58: =IF(C58="Monthly Rent Charge",$F$3,"") | I58: =IF(AND(A58="",C58=""),"",IF(C58="Payment Received",I57-IFERROR(G58,0),IF(C58="Monthly Rent Charge",I57+IFERROR(E58,0)+IFERROR(F58,0),IFERROR(I57,0))))
A59: =IF(B59="","",DATE(YEAR(TODAY()),MATCH(B59,{"January","February","March","April","May","June","July","August","September","October","November","December"},0),1)) | C59: =IF(B59="","","Monthly Rent Charge") | E59: =IF(C59="Monthly Rent Charge",$D$3,"") | F59: =IF(C59="Monthly Rent Charge",$F$3,"") | I59: =IF(AND(A59="",C59=""),"",IF(C59="Payment Received",I58-IFERROR(G59,0),IF(C59="Monthly Rent Charge",I58+IFERROR(E59,0)+IFERROR(F59,0),IFERROR(I58,0))))
A60: =IF(B60="","",DATE(YEAR(TODAY()),MATCH(B60,{"January","February","March","April","May","June","July","August","September","October","November","December"},0),1)) | C60: =IF(B60="","","Monthly Rent Charge") | E60: =IF(C60="Monthly Rent Charge",$D$3,"") | F60: =IF(C60="Monthly Rent Charge",$F$3,"") | I60: =IF(AND(A60="",C60=""),"",IF(C60="Payment Received",I59-IFERROR(G60,0),IF(C60="Monthly Rent Charge",I59+IFERROR(E60,0)+IFERROR(F60,0),IFERROR(I59,0))))
A61: =IF(B61="","",DATE(YEAR(TODAY()),MATCH(B61,{"January","February","March","April","May","June","July","August","September","October","November","December"},0),1)) | C61: =IF(B61="","","Monthly Rent Charge") | E61: =IF(C61="Monthly Rent Charge",$D$3,"") | F61: =IF(C61="Monthly Rent Charge",$F$3,"") | I61: =IF(AND(A61="",C61=""),"",IF(C61="Payment Received",I60-IFERROR(G61,0),IF(C61="Monthly Rent Charge",I60+IFERROR(E61,0)+IFERROR(F61,0),IFERROR(I60,0))))
A62: =IF(B62="","",DATE(YEAR(TODAY()),MATCH(B62,{"January","February","March","April","May","June","July","August","September","October","November","December"},0),1)) | C62: =IF(B62="","","Monthly Rent Charge") | E62: =IF(C62="Monthly Rent Charge",$D$3,"") | F62: =IF(C62="Monthly Rent Charge",$F$3,"") | I62: =IF(AND(A62="",C62=""),"",IF(C62="Payment Received",I61-IFERROR(G62,0),IF(C62="Monthly Rent Charge",I61+IFERROR(E62,0)+IFERROR(F62,0),IFERROR(I61,0))))
A63: =IF(B63="","",DATE(YEAR(TODAY()),MATCH(B63,{"January","February","March","April","May","June","July","August","September","October","November","December"},0),1)) | C63: =IF(B63="","","Monthly Rent Charge") | E63: =IF(C63="Monthly Rent Charge",$D$3,"") | F63: =IF(C63="Monthly Rent Charge",$F$3,"") | I63: =IF(AND(A63="",C63=""),"",IF(C63="Payment Received",I62-IFERROR(G63,0),IF(C63="Monthly Rent Charge",I62+IFERROR(E63,0)+IFERROR(F63,0),IFERROR(I62,0))))
A64: =IF(B64="","",DATE(YEAR(TODAY()),MATCH(B64,{"January","February","March","April","May","June","July","August","September","October","November","December"},0),1)) | C64: =IF(B64="","","Monthly Rent Charge") | E64: =IF(C64="Monthly Rent Charge",$D$3,"") | F64: =IF(C64="Monthly Rent Charge",$F$3,"") | I64: =IF(AND(A64="",C64=""),"",IF(C64="Payment Received",I63-IFERROR(G64,0),IF(C64="Monthly Rent Charge",I63+IFERROR(E64,0)+IFERROR(F64,0),IFERROR(I63,0))))
A65: =IF(B65="","",DATE(YEAR(TODAY()),MATCH(B65,{"January","February","March","April","May","June","July","August","September","October","November","December"},0),1)) | C65: =IF(B65="","","Monthly Rent Charge") | E65: =IF(C65="Monthly Rent Charge",$D$3,"") | F65: =IF(C65="Monthly Rent Charge",$F$3,"") | I65: =IF(AND(A65="",C65=""),"",IF(C65="Payment Received",I64-IFERROR(G65,0),IF(C65="Monthly Rent Charge",I64+IFERROR(E65,0)+IFERROR(F65,0),IFERROR(I64,0))))
A66: =IF(B66="","",DATE(YEAR(TODAY()),MATCH(B66,{"January","February","March","April","May","June","July","August","September","October","November","December"},0),1)) | C66: =IF(B66="","","Monthly Rent Charge") | E66: =IF(C66="Monthly Rent Charge",$D$3,"") | F66: =IF(C66="Monthly Rent Charge",$F$3,"") | I66: =IF(AND(A66="",C66=""),"",IF(C66="Payment Received",I65-IFERROR(G66,0),IF(C66="Monthly Rent Charge",I65+IFERROR(E66,0)+IFERROR(F66,0),IFERROR(I65,0))))
A67: =IF(B67="","",DATE(YEAR(TODAY()),MATCH(B67,{"January","February","March","April","May","June","July","August","September","October","November","December"},0),1)) | C67: =IF(B67="","","Monthly Rent Charge") | E67: =IF(C67="Monthly Rent Charge",$D$3,"") | F67: =IF(C67="Monthly Rent Charge",$F$3,"") | I67: =IF(AND(A67="",C67=""),"",IF(C67="Payment Received",I66-IFERROR(G67,0),IF(C67="Monthly Rent Charge",I66+IFERROR(E67,0)+IFERROR(F67,0),IFERROR(I66,0))))
... A69: =IF(B69="","",DATE(YEAR(TODAY()),MATCH(B69,{"January","February","March","April","May","June","July","August","September","October","November","December"},0),1)) | C69: =IF(B69="","","Monthly Rent Charge") | E69: =IF(C69="Monthly Rent Charge",$D$3,"") | F69: =IF(C69="Monthly Rent Charge",$F$3,"") | I69: =IF(AND(A69="",C69=""),"",IF(C69="Payment Received",I68-IFERROR(G69,0),IF(C69="Monthly Rent Charge",I68+IFERROR(E69,0)+IFERROR(F69,0),IFERROR(I68,0))))

Sheet B1
A1: Unit B1 — Tenant Statement / Ledger
A2: Select a month to create a Monthly Rent Charge: the date fills as the first day of that month (current year) and description fills automatically. For a payment, leave Month blank and choose Payment Received.
A3: Unit | B3: B1 | C3: Current Rent | D3: 3000 | E3: Garbage | F3: 200 | G3: Current Balance | H3: =IFERROR(LOOKUP(9.99E+307,I6:I60),0) | I3: Tenant | J3: JACKLYNE CHENINGINGWA | K3: Deposit Held | L3: 0
A4: Current tenant only. When vacating → copy rows to Archive sheet, then clear this ledger.
A5: Date | B5: Month | C5: Description | D5: Tenant | E5: Rent Charged | F5: Garbage Charged | G5: Payment Received | H5: M-Pesa Reference | I5: Running Balance | J5: Remarks
A6: 45566 | B6: October | C6: =IF(B6="","","Monthly Rent Charge") | E6: =IF(C6="Monthly Rent Charge",$D$3,"") | F6: =IF(C6="Monthly Rent Charge",$F$3,"") | I6: =IF(A6="","",IF(C6="Payment Received",-IFERROR(G6,0),IF(C6="Monthly Rent Charge",IFERROR(E6,0)+IFERROR(F6,0),0)))
A7: 45595 | C7: Payment Received | E7: =IF(C7="Monthly Rent Charge",$D$3,"") | F7: =IF(C7="Monthly Rent Charge",$F$3,"") | G7: 3500 | I7: =IF(A7="","",IF(C7="Payment Received",I6-IFERROR(G7,0),IF(C7="Monthly Rent Charge",I6+IFERROR(E7,0)+IFERROR(F7,0),I6)))
A8: 45597 | B8: November | C8: =IF(B8="","","Monthly Rent Charge") | E8: =IF(C8="Monthly Rent Charge",$D$3,"") | F8: =IF(C8="Monthly Rent Charge",$F$3,"") | I8: =IF(A8="","",IF(C8="Payment Received",I7-IFERROR(G8,0),IF(C8="Monthly Rent Charge",I7+IFERROR(E8,0)+IFERROR(F8,0),I7)))
A9: 45627 | B9: December | C9: =IF(B9="","","Monthly Rent Charge") | E9: =IF(C9="Monthly Rent Charge",$D$3,"") | F9: =IF(C9="Monthly Rent Charge",$F$3,"") | I9: =IF(A9="","",IF(C9="Payment Received",I8-IFERROR(G9,0),IF(C9="Monthly Rent Charge",I8+IFERROR(E9,0)+IFERROR(F9,0),I8)))
A10: 45653 | C10: Payment Received | E10: =IF(C10="Monthly Rent Charge",$D$3,"") | F10: =IF(C10="Monthly Rent Charge",$F$3,"") | G10: 3200 | I10: =IF(A10="","",IF(C10="Payment Received",I9-IFERROR(G10,0),IF(C10="Monthly Rent Charge",I9+IFERROR(E10,0)+IFERROR(F10,0),I9)))
A11: 45658 | B11: January | C11: =IF(B11="","","Monthly Rent Charge") | E11: =IF(C11="Monthly Rent Charge",$D$3,"") | F11: =IF(C11="Monthly Rent Charge",$F$3,"") | I11: =IF(A11="","",IF(C11="Payment Received",I10-IFERROR(G11,0),IF(C11="Monthly Rent Charge",I10+IFERROR(E11,0)+IFERROR(F11,0),I10)))
A12: 45658 | C12: Payment Received | G12: 3200 | I12: =IF(A12="","",IF(C12="Payment Received",I11-IFERROR(G12,0),IF(C12="Monthly Rent Charge",I11+IFERROR(E12,0)+IFERROR(F12,0),I11)))
A13: 45689 | B13: February | C13: =IF(B13="","","Monthly Rent Charge") | E13: =IF(C13="Monthly Rent Charge",$D$3,"") | F13: =IF(C13="Monthly Rent Charge",$F$3,"") | I13: =IF(A13="","",IF(C13="Payment Received",I12-IFERROR(G13,0),IF(C13="Monthly Rent Charge",I12+IFERROR(E13,0)+IFERROR(F13,0),I12)))
A14: 45689 | C14: Payment Received | E14: =IF(C14="Monthly Rent Charge",$D$3,"") | F14: =IF(C14="Monthly Rent Charge",$F$3,"") | G14: 3200 | I14: =IF(A14="","",IF(C14="Payment Received",I13-IFERROR(G14,0),IF(C14="Monthly Rent Charge",I13+IFERROR(E14,0)+IFERROR(F14,0),I13)))
A15: 45717 | B15: March | C15: =IF(B15="","","Monthly Rent Charge") | E15: =IF(C15="Monthly Rent Charge",$D$3,"") | F15: =IF(C15="Monthly Rent Charge",$F$3,"") | I15: =IF(A15="","",IF(C15="Payment Received",I14-IFERROR(G15,0),IF(C15="Monthly Rent Charge",I14+IFERROR(E15,0)+IFERROR(F15,0),I14)))
A16: 45723 | C16: Payment Received | E16: =IF(C16="Monthly Rent Charge",$D$3,"") | F16: =IF(C16="Monthly Rent Charge",$F$3,"") | G16: 2000 | H16: TC70SR0JO2 | I16: =IF(A16="","",IF(C16="Payment Received",I15-IFERROR(G16,0),IF(C16="Monthly Rent Charge",I15+IFERROR(E16,0)+IFERROR(F16,0),I15)))
A17: 45736 | C17: Payment Received | E17: =IF(C17="Monthly Rent Charge",$D$3,"") | F17: =IF(C17="Monthly Rent Charge",$F$3,"") | G17: 1000 | H17: TCK4FJKOF6 | I17: =IF(A17="","",IF(C17="Payment Received",I16-IFERROR(G17,0),IF(C17="Monthly Rent Charge",I16+IFERROR(E17,0)+IFERROR(F17,0),I16)))
A18: 45748 | B18: April | C18: =IF(B18="","","Monthly Rent Charge") | E18: =IF(C18="Monthly Rent Charge",$D$3,"") | F18: =IF(C18="Monthly Rent Charge",$F$3,"") | I18: =IF(A18="","",IF(C18="Payment Received",I17-IFERROR(G18,0),IF(C18="Monthly Rent Charge",I17+IFERROR(E18,0)+IFERROR(F18,0),I17)))
A19: 45778 | B19: May | C19: =IF(B19="","","Monthly Rent Charge") | E19: =IF(C19="Monthly Rent Charge",$D$3,"") | F19: =IF(C19="Monthly Rent Charge",$F$3,"") | I19: =IF(A19="","",IF(C19="Payment Received",I18-IFERROR(G19,0),IF(C19="Monthly Rent Charge",I18+IFERROR(E19,0)+IFERROR(F19,0),I18)))
A20: 45793 | C20: Payment Received | E20: =IF(C20="Monthly Rent Charge",$D$3,"") | F20: =IF(C20="Monthly Rent Charge",$F$3,"") | G20: 9600 | H20: TEG4WN2RS4 | I20: =IF(A20="","",IF(C20="Payment Received",I19-IFERROR(G20,0),IF(C20="Monthly Rent Charge",I19+IFERROR(E20,0)+IFERROR(F20,0),I19)))
A21: 45809 | B21: June | C21: =IF(B21="","","Monthly Rent Charge") | E21: =IF(C21="Monthly Rent Charge",$D$3,"") | F21: =IF(C21="Monthly Rent Charge",$F$3,"") | I21: =IF(A21="","",IF(C21="Payment Received",I20-IFERROR(G21,0),IF(C21="Monthly Rent Charge",I20+IFERROR(E21,0)+IFERROR(F21,0),I20)))
A22: 45836 | C22: Payment Received | E22: =IF(C22="Monthly Rent Charge",$D$3,"") | F22: =IF(C22="Monthly Rent Charge",$F$3,"") | G22: 3200 | H22: TFS0RQ4RVA | I22: =IF(A22="","",IF(C22="Payment Received",I21-IFERROR(G22,0),IF(C22="Monthly Rent Charge",I21+IFERROR(E22,0)+IFERROR(F22,0),I21)))
A23: 45839 | B23: July | C23: =IF(B23="","","Monthly Rent Charge") | E23: =IF(C23="Monthly Rent Charge",$D$3,"") | F23: =IF(C23="Monthly Rent Charge",$F$3,"") | I23: =IF(A23="","",IF(C23="Payment Received",I22-IFERROR(G23,0),IF(C23="Monthly Rent Charge",I22+IFERROR(E23,0)+IFERROR(F23,0),I22)))
A24: 45859 | C24: Payment Received | E24: =IF(C24="Monthly Rent Charge",$D$3,"") | F24: =IF(C24="Monthly Rent Charge",$F$3,"") | G24: 3200 | H24: TGL7Y7OV6P | I24: =IF(A24="","",IF(C24="Payment Received",I23-IFERROR(G24,0),IF(C24="Monthly Rent Charge",I23+IFERROR(E24,0)+IFERROR(F24,0),I23)))
A25: 45870 | B25: August | C25: =IF(B25="","","Monthly Rent Charge") | E25: =IF(C25="Monthly Rent Charge",$D$3,"") | F25: =IF(C25="Monthly Rent Charge",$F$3,"") | I25: =IF(A25="","",IF(C25="Payment Received",I24-IFERROR(G25,0),IF(C25="Monthly Rent Charge",I24+IFERROR(E25,0)+IFERROR(F25,0),I24)))
A26: 45884 | C26: Payment Received | E26: =IF(C26="Monthly Rent Charge",$D$3,"") | F26: =IF(C26="Monthly Rent Charge",$F$3,"") | G26: 3200 | H26: THF0ELQV9Y | I26: =IF(A26="","",IF(C26="Payment Received",I25-IFERROR(G26,0),IF(C26="Monthly Rent Charge",I25+IFERROR(E26,0)+IFERROR(F26,0),I25)))
A27: 45901 | B27: September | C27: =IF(B27="","","Monthly Rent Charge") | E27: =IF(C27="Monthly Rent Charge",$D$3,"") | F27: =IF(C27="Monthly Rent Charge",$F$3,"") | I27: =IF(A27="","",IF(C27="Payment Received",I26-IFERROR(G27,0),IF(C27="Monthly Rent Charge",I26+IFERROR(E27,0)+IFERROR(F27,0),I26)))
A28: 45931 | B28: October | C28: =IF(B28="","","Monthly Rent Charge") | E28: =IF(C28="Monthly Rent Charge",$D$3,"") | F28: =IF(C28="Monthly Rent Charge",$F$3,"") | I28: =IF(A28="","",IF(C28="Payment Received",I27-IFERROR(G28,0),IF(C28="Monthly Rent Charge",I27+IFERROR(E28,0)+IFERROR(F28,0),I27)))
A29: 45962 | B29: November | C29: =IF(B29="","","Monthly Rent Charge") | E29: =IF(C29="Monthly Rent Charge",$D$3,"") | F29: =IF(C29="Monthly Rent Charge",$F$3,"") | I29: =IF(A29="","",IF(C29="Payment Received",I28-IFERROR(G29,0),IF(C29="Monthly Rent Charge",I28+IFERROR(E29,0)+IFERROR(F29,0),I28)))
A30: 45966 | C30: Payment Received | E30: =IF(C30="Monthly Rent Charge",$D$3,"") | F30: =IF(C30="Monthly Rent Charge",$F$3,"") | G30: 1500 | H30: TK5DC9D8XI | I30: =IF(A30="","",IF(C30="Payment Received",I29-IFERROR(G30,0),IF(C30="Monthly Rent Charge",I29+IFERROR(E30,0)+IFERROR(F30,0),I29)))
A31: 45992 | B31: December | C31: =IF(B31="","","Monthly Rent Charge") | E31: =IF(C31="Monthly Rent Charge",$D$3,"") | F31: =IF(C31="Monthly Rent Charge",$F$3,"") | I31: =IF(A31="","",IF(C31="Payment Received",I30-IFERROR(G31,0),IF(C31="Monthly Rent Charge",I30+IFERROR(E31,0)+IFERROR(F31,0),I30)))
A32: 45996 | C32: Payment Received | E32: =IF(C32="Monthly Rent Charge",$D$3,"") | F32: =IF(C32="Monthly Rent Charge",$F$3,"") | G32: 3500 | H32: TL5DC06X48 | I32: =IF(A32="","",IF(C32="Payment Received",I31-IFERROR(G32,0),IF(C32="Monthly Rent Charge",I31+IFERROR(E32,0)+IFERROR(F32,0),I31)))
A33: =IF(B33="","",DATE(YEAR(TODAY()),MATCH(B33,{"January","February","March","April","May","June","July","August","September","October","November","December"},0),1)) | B33: January | C33: =IF(B33="","","Monthly Rent Charge") | E33: =IF(C33="Monthly Rent Charge",$D$3,"") | F33: =IF(C33="Monthly Rent Charge",$F$3,"") | I33: =IF(A33="","",IF(C33="Payment Received",I32-IFERROR(G33,0),IF(C33="Monthly Rent Charge",I32+IFERROR(E33,0)+IFERROR(F33,0),I32)))
A34: =IF(B34="","",DATE(YEAR(TODAY()),MATCH(B34,{"January","February","March","April","May","June","July","August","September","October","November","December"},0),1)) | B34: February | C34: =IF(B34="","","Monthly Rent Charge") | E34: =IF(C34="Monthly Rent Charge",$D$3,"") | F34: =IF(C34="Monthly Rent Charge",$F$3,"") | I34: =IF(A34="","",IF(C34="Payment Received",I33-IFERROR(G34,0),IF(C34="Monthly Rent Charge",I33+IFERROR(E34,0)+IFERROR(F34,0),I33)))
A35: =IF(B35="","",DATE(YEAR(TODAY()),MATCH(B35,{"January","February","March","April","May","June","July","August","September","October","November","December"},0),1)) | B35: March | C35: =IF(B35="","","Monthly Rent Charge") | E35: =IF(C35="Monthly Rent Charge",$D$3,"") | F35: =IF(C35="Monthly Rent Charge",$F$3,"") | I35: =IF(A35="","",IF(C35="Payment Received",I34-IFERROR(G35,0),IF(C35="Monthly Rent Charge",I34+IFERROR(E35,0)+IFERROR(F35,0),I34)))
A36: 46090 | C36: Payment Received | E36: =IF(C36="Monthly Rent Charge",$D$3,"") | F36: =IF(C36="Monthly Rent Charge",$F$3,"") | G36: 4600 | H36: UC9HU8OTKI | I36: =IF(A36="","",IF(C36="Payment Received",I35-IFERROR(G36,0),IF(C36="Monthly Rent Charge",I35+IFERROR(E36,0)+IFERROR(F36,0),I35)))
A37: 46091 | C37: Payment Received | E37: =IF(C37="Monthly Rent Charge",$D$3,"") | F37: =IF(C37="Monthly Rent Charge",$F$3,"") | G37: 9700 | H37: UCAHU8SG1O | I37: =IF(A37="","",IF(C37="Payment Received",I36-IFERROR(G37,0),IF(C37="Monthly Rent Charge",I36+IFERROR(E37,0)+IFERROR(F37,0),I36)))
A38: 46096 | C38: Payment Received | E38: =IF(C38="Monthly Rent Charge",$D$3,"") | F38: =IF(C38="Monthly Rent Charge",$F$3,"") | G38: 1500 | H38: UCFHU98C55 | I38: =IF(A38="","",IF(C38="Payment Received",I37-IFERROR(G38,0),IF(C38="Monthly Rent Charge",I37+IFERROR(E38,0)+IFERROR(F38,0),I37)))
A39: =IF(B39="","",DATE(YEAR(TODAY()),MATCH(B39,{"January","February","March","April","May","June","July","August","September","October","November","December"},0),1)) | B39: April | C39: =IF(B39="","","Monthly Rent Charge") | E39: =IF(C39="Monthly Rent Charge",$D$3,"") | F39: =IF(C39="Monthly Rent Charge",$F$3,"") | I39: =IF(A39="","",IF(C39="Payment Received",I38-IFERROR(G39,0),IF(C39="Monthly Rent Charge",I38+IFERROR(E39,0)+IFERROR(F39,0),I38)))
A40: 46114 | C40: Payment Received | E40: =IF(C40="Monthly Rent Charge",$D$3,"") | F40: =IF(C40="Monthly Rent Charge",$F$3,"") | G40: 4000 | H40: UD2HUB3E14 | I40: =IF(A40="","",IF(C40="Payment Received",I39-IFERROR(G40,0),IF(C40="Monthly Rent Charge",I39+IFERROR(E40,0)+IFERROR(F40,0),I39)))
A41: =IF(B41="","",DATE(YEAR(TODAY()),MATCH(B41,{"January","February","March","April","May","June","July","August","September","October","November","December"},0),1)) | B41: May | C41: =IF(B41="","","Monthly Rent Charge") | E41: =IF(C41="Monthly Rent Charge",$D$3,"") | F41: =IF(C41="Monthly Rent Charge",$F$3,"") | I41: =IF(AND(A41="",C41=""),"",IF(C41="Payment Received",I40-IFERROR(G41,0),IF(C41="Monthly Rent Charge",I40+IFERROR(E41,0)+IFERROR(F41,0),I40)))
A42: 46150 | C42: Payment Received | E42: =IF(C42="Monthly Rent Charge",$D$3,"") | F42: =IF(C42="Monthly Rent Charge",$F$3,"") | G42: 2200 | H42: UE8HU3B6A9 | I42: =IF(AND(A42="",C42=""),"",IF(C42="Payment Received",I41-IFERROR(G42,0),IF(C42="Monthly Rent Charge",I41+IFERROR(E42,0)+IFERROR(F42,0),I41)))
A43: =IF(B43="","",DATE(YEAR(TODAY()),MATCH(B43,{"January","February","March","April","May","June","July","August","September","October","November","December"},0),1)) | B43: June | C43: =IF(B43="","","Monthly Rent Charge") | E43: =IF(C43="Monthly Rent Charge",$D$3,"") | F43: =IF(C43="Monthly Rent Charge",$F$3,"") | I43: =IF(AND(A43="",C43=""),"",IF(C43="Payment Received",I42-IFERROR(G43,0),IF(C43="Monthly Rent Charge",I42+IFERROR(E43,0)+IFERROR(F43,0),I42)))
A44: 46199 | C44: Payment Received | E44: =IF(C44="Monthly Rent Charge",$D$3,"") | F44: =IF(C44="Monthly Rent Charge",$F$3,"") | G44: 2200 | H44: UFQHU8V90K | I44: =IF(AND(A44="",C44=""),"",IF(C44="Payment Received",I43-IFERROR(G44,0),IF(C44="Monthly Rent Charge",I43+IFERROR(E44,0)+IFERROR(F44,0),I43)))
A45: =IF(B45="","",DATE(YEAR(TODAY()),MATCH(B45,{"January","February","March","April","May","June","July","August","September","October","November","December"},0),1)) | B45: July | C45: =IF(B45="","","Monthly Rent Charge") | E45: =IF(C45="Monthly Rent Charge",$D$3,"") | F45: =IF(C45="Monthly Rent Charge",$F$3,"") | I45: =IF(AND(A45="",C45=""),"",IF(C45="Payment Received",I44-IFERROR(G45,0),IF(C45="Monthly Rent Charge",I44+IFERROR(E45,0)+IFERROR(F45,0),I44)))
A46: 46234 | C46: Payment Received | E46: =IF(C46="Monthly Rent Charge",$D$3,"") | F46: =IF(C46="Monthly Rent Charge",$F$3,"") | G46: 3200 | H46: UGVHU0VMOS | I46: =IF(AND(A46="",C46=""),"",IF(C46="Payment Received",I45-IFERROR(G46,0),IF(C46="Monthly Rent Charge",I45+IFERROR(E46,0)+IFERROR(F46,0),IFERROR(I45,0))))
A47: =IF(B47="","",DATE(YEAR(TODAY()),MATCH(B47,{"January","February","March","April","May","June","July","August","September","October","November","December"},0),1)) | B47: August | C47: =IF(B47="","","Monthly Rent Charge") | E47: =IF(C47="Monthly Rent Charge",$D$3,"") | F47: =IF(C47="Monthly Rent Charge",$F$3,"") | I47: =IF(AND(A47="",C47=""),"",IF(C47="Payment Received",I46-IFERROR(G47,0),IF(C47="Monthly Rent Charge",I46+IFERROR(E47,0)+IFERROR(F47,0),IFERROR(I46,0))))
A48: 46264 | C48: Payment Received | E48: =IF(C48="Monthly Rent Charge",$D$3,"") | F48: =IF(C48="Monthly Rent Charge",$F$3,"") | G48: 4200 | H48: UHUHUETOV | I48: =IF(AND(A48="",C48=""),"",IF(C48="Payment Received",I47-IFERROR(G48,0),IF(C48="Monthly Rent Charge",I47+IFERROR(E48,0)+IFERROR(F48,0),IFERROR(I47,0))))
A49: =IF(B49="","",DATE(YEAR(TODAY()),MATCH(B49,{"January","February","March","April","May","June","July","August","September","October","November","December"},0),1)) | C49: =IF(B49="","","Monthly Rent Charge") | E49: =IF(C49="Monthly Rent Charge",$D$3,"") | F49: =IF(C49="Monthly Rent Charge",$F$3,"") | I49: =IF(AND(A49="",C49=""),"",IF(C49="Payment Received",I48-IFERROR(G49,0),IF(C49="Monthly Rent Charge",I48+IFERROR(E49,0)+IFERROR(F49,0),IFERROR(I48,0))))
A50: =IF(B50="","",DATE(YEAR(TODAY()),MATCH(B50,{"January","February","March","April","May","June","July","August","September","October","November","December"},0),1)) | C50: =IF(B50="","","Monthly Rent Charge") | E50: =IF(C50="Monthly Rent Charge",$D$3,"") | F50: =IF(C50="Monthly Rent Charge",$F$3,"") | I50: =IF(AND(A50="",C50=""),"",IF(C50="Payment Received",I49-IFERROR(G50,0),IF(C50="Monthly Rent Charge",I49+IFERROR(E50,0)+IFERROR(F50,0),IFERROR(I49,0))))
A51: =IF(B51="","",DATE(YEAR(TODAY()),MATCH(B51,{"January","February","March","April","May","June","July","August","September","October","November","December"},0),1)) | C51: =IF(B51="","","Monthly Rent Charge") | E51: =IF(C51="Monthly Rent Charge",$D$3,"") | F51: =IF(C51="Monthly Rent Charge",$F$3,"") | I51: =IF(AND(A51="",C51=""),"",IF(C51="Payment Received",I50-IFERROR(G51,0),IF(C51="Monthly Rent Charge",I50+IFERROR(E51,0)+IFERROR(F51,0),IFERROR(I50,0))))
A52: =IF(B52="","",DATE(YEAR(TODAY()),MATCH(B52,{"January","February","March","April","May","June","July","August","September","October","November","December"},0),1)) | C52: =IF(B52="","","Monthly Rent Charge") | E52: =IF(C52="Monthly Rent Charge",$D$3,"") | F52: =IF(C52="Monthly Rent Charge",$F$3,"") | I52: =IF(AND(A52="",C52=""),"",IF(C52="Payment Received",I51-IFERROR(G52,0),IF(C52="Monthly Rent Charge",I51+IFERROR(E52,0)+IFERROR(F52,0),IFERROR(I51,0))))
A53: =IF(B53="","",DATE(YEAR(TODAY()),MATCH(B53,{"January","February","March","April","May","June","July","August","September","October","November","December"},0),1)) | C53: =IF(B53="","","Monthly Rent Charge") | E53: =IF(C53="Monthly Rent Charge",$D$3,"") | F53: =IF(C53="Monthly Rent Charge",$F$3,"") | I53: =IF(AND(A53="",C53=""),"",IF(C53="Payment Received",I52-IFERROR(G53,0),IF(C53="Monthly Rent Charge",I52+IFERROR(E53,0)+IFERROR(F53,0),IFERROR(I52,0))))
A54: =IF(B54="","",DATE(YEAR(TODAY()),MATCH(B54,{"January","February","March","April","May","June","July","August","September","October","November","December"},0),1)) | C54: =IF(B54="","","Monthly Rent Charge") | E54: =IF(C54="Monthly Rent Charge",$D$3,"") | F54: =IF(C54="Monthly Rent Charge",$F$3,"") | I54: =IF(AND(A54="",C54=""),"",IF(C54="Payment Received",I53-IFERROR(G54,0),IF(C54="Monthly Rent Charge",I53+IFERROR(E54,0)+IFERROR(F54,0),IFERROR(I53,0))))
A55: =IF(B55="","",DATE(YEAR(TODAY()),MATCH(B55,{"January","February","March","April","May","June","July","August","September","October","November","December"},0),1)) | C55: =IF(B55="","","Monthly Rent Charge") | E55: =IF(C55="Monthly Rent Charge",$D$3,"") | F55: =IF(C55="Monthly Rent Charge",$F$3,"") | I55: =IF(AND(A55="",C55=""),"",IF(C55="Payment Received",I54-IFERROR(G55,0),IF(C55="Monthly Rent Charge",I54+IFERROR(E55,0)+IFERROR(F55,0),IFERROR(I54,0))))
A56: =IF(B56="","",DATE(YEAR(TODAY()),MATCH(B56,{"January","February","March","April","May","June","July","August","September","October","November","December"},0),1)) | C56: =IF(B56="","","Monthly Rent Charge") | E56: =IF(C56="Monthly Rent Charge",$D$3,"") | F56: =IF(C56="Monthly Rent Charge",$F$3,"") | I56: =IF(AND(A56="",C56=""),"",IF(C56="Payment Received",I55-IFERROR(G56,0),IF(C56="Monthly Rent Charge",I55+IFERROR(E56,0)+IFERROR(F56,0),IFERROR(I55,0))))
A57: =IF(B57="","",DATE(YEAR(TODAY()),MATCH(B57,{"January","February","March","April","May","June","July","August","September","October","November","December"},0),1)) | C57: =IF(B57="","","Monthly Rent Charge") | E57: =IF(C57="Monthly Rent Charge",$D$3,"") | F57: =IF(C57="Monthly Rent Charge",$F$3,"") | I57: =IF(AND(A57="",C57=""),"",IF(C57="Payment Received",I56-IFERROR(G57,0),IF(C57="Monthly Rent Charge",I56+IFERROR(E57,0)+IFERROR(F57,0),IFERROR(I56,0))))
A58: =IF(B58="","",DATE(YEAR(TODAY()),MATCH(B58,{"January","February","March","April","May","June","July","August","September","October","November","December"},0),1)) | C58: =IF(B58="","","Monthly Rent Charge") | E58: =IF(C58="Monthly Rent Charge",$D$3,"") | F58: =IF(C58="Monthly Rent Charge",$F$3,"") | I58: =IF(AND(A58="",C58=""),"",IF(C58="Payment Received",I57-IFERROR(G58,0),IF(C58="Monthly Rent Charge",I57+IFERROR(E58,0)+IFERROR(F58,0),IFERROR(I57,0))))
A59: =IF(B59="","",DATE(YEAR(TODAY()),MATCH(B59,{"January","February","March","April","May","June","July","August","September","October","November","December"},0),1)) | C59: =IF(B59="","","Monthly Rent Charge") | E59: =IF(C59="Monthly Rent Charge",$D$3,"") | F59: =IF(C59="Monthly Rent Charge",$F$3,"") | I59: =IF(AND(A59="",C59=""),"",IF(C59="Payment Received",I58-IFERROR(G59,0),IF(C59="Monthly Rent Charge",I58+IFERROR(E59,0)+IFERROR(F59,0),IFERROR(I58,0))))
A60: =IF(B60="","",DATE(YEAR(TODAY()),MATCH(B60,{"January","February","March","April","May","June","July","August","September","October","November","December"},0),1)) | C60: =IF(B60="","","Monthly Rent Charge") | E60: =IF(C60="Monthly Rent Charge",$D$3,"") | F60: =IF(C60="Monthly Rent Charge",$F$3,"") | I60: =IF(AND(A60="",C60=""),"",IF(C60="Payment Received",I59-IFERROR(G60,0),IF(C60="Monthly Rent Charge",I59+IFERROR(E60,0)+IFERROR(F60,0),IFERROR(I59,0))))

Sheet B2
A1: Unit B2 — Tenant Statement / Ledger
A2: Select a month to create a Monthly Rent Charge: the date fills as the first day of that month (current year) and description fills automatically. For a payment, leave Month blank and choose Payment Received.
A3: Unit | B3: B2 | C3: Current Rent | D3: 6000 | E3: Garbage | F3: 200 | G3: Current Balance | H3: =IFERROR(LOOKUP(9.99E+307,I6:I41),0) | I3: Tenant | J3: ANITA NYAKUNDI / DAVID ODHIAMBO | K3: Deposit Held | L3: 1000
A4: Current tenant only. When vacating → copy rows to Archive sheet, then clear this ledger.
A5: Date | B5: Month | C5: Description | D5: Tenant | E5: Rent Charged | F5: Garbage Charged | G5: Payment Received | H5: M-Pesa Reference | I5: Running Balance | J5: Remarks
A6: 45901 | B6: September | C6: =IF(B6="","","Monthly Rent Charge") | E6: =IF(C6="Monthly Rent Charge",$D$3,"") | F6: =IF(C6="Monthly Rent Charge",$F$3,"") | I6: =IF(A6="","",IF(C6="Payment Received",-IFERROR(G6,0),IF(C6="Monthly Rent Charge",IFERROR(E6,0)+IFERROR(F6,0),0)))
A7: 45908 | C7: Payment Received | E7: =IF(C7="Monthly Rent Charge",$D$3,"") | F7: =IF(C7="Monthly Rent Charge",$F$3,"") | G7: 6200 | H7: TI831503H7 | I7: =IF(A7="","",IF(C7="Payment Received",I6-IFERROR(G7,0),IF(C7="Monthly Rent Charge",I6+IFERROR(E7,0)+IFERROR(F7,0),I6)))
A8: 45931 | B8: October | C8: =IF(B8="","","Monthly Rent Charge") | E8: =IF(C8="Monthly Rent Charge",$D$3,"") | F8: =IF(C8="Monthly Rent Charge",$F$3,"") | I8: =IF(A8="","",IF(C8="Payment Received",I7-IFERROR(G8,0),IF(C8="Monthly Rent Charge",I7+IFERROR(E8,0)+IFERROR(F8,0),I7)))
A9: 45938 | C9: Payment Received | E9: =IF(C9="Monthly Rent Charge",$D$3,"") | F9: =IF(C9="Monthly Rent Charge",$F$3,"") | G9: 6200 | H9: TJ8A66UNIJ | I9: =IF(A9="","",IF(C9="Payment Received",I8-IFERROR(G9,0),IF(C9="Monthly Rent Charge",I8+IFERROR(E9,0)+IFERROR(F9,0),I8)))
A10: 45962 | B10: November | C10: =IF(B10="","","Monthly Rent Charge") | E10: =IF(C10="Monthly Rent Charge",$D$3,"") | F10: =IF(C10="Monthly Rent Charge",$F$3,"") | I10: =IF(A10="","",IF(C10="Payment Received",I9-IFERROR(G10,0),IF(C10="Monthly Rent Charge",I9+IFERROR(E10,0)+IFERROR(F10,0),I9)))
A11: 45991 | C11: Payment Received | E11: =IF(C11="Monthly Rent Charge",$D$3,"") | F11: =IF(C11="Monthly Rent Charge",$F$3,"") | G11: 6200 | H11: TK9R59LY8Q | I11: =IF(A11="","",IF(C11="Payment Received",I10-IFERROR(G11,0),IF(C11="Monthly Rent Charge",I10+IFERROR(E11,0)+IFERROR(F11,0),I10)))
A12: 45992 | B12: December | C12: =IF(B12="","","Monthly Rent Charge") | E12: =IF(C12="Monthly Rent Charge",$D$3,"") | F12: =IF(C12="Monthly Rent Charge",$F$3,"") | I12: =IF(A12="","",IF(C12="Payment Received",I11-IFERROR(G12,0),IF(C12="Monthly Rent Charge",I11+IFERROR(E12,0)+IFERROR(F12,0),I11)))
A13: 45998 | C13: Payment Received | E13: =IF(C13="Monthly Rent Charge",$D$3,"") | F13: =IF(C13="Monthly Rent Charge",$F$3,"") | G13: 6200 | H13: TL7A6OB9T4 | I13: =IF(A13="","",IF(C13="Payment Received",I12-IFERROR(G13,0),IF(C13="Monthly Rent Charge",I12+IFERROR(E13,0)+IFERROR(F13,0),I12)))
A14: =IF(B14="","",DATE(YEAR(TODAY()),MATCH(B14,{"January","February","March","April","May","June","July","August","September","October","November","December"},0),1)) | B14: January | C14: =IF(B14="","","Monthly Rent Charge") | E14: =IF(C14="Monthly Rent Charge",$D$3,"") | F14: =IF(C14="Monthly Rent Charge",$F$3,"") | I14: =IF(A14="","",IF(C14="Payment Received",I13-IFERROR(G14,0),IF(C14="Monthly Rent Charge",I13+IFERROR(E14,0)+IFERROR(F14,0),I13)))
A15: 46031 | C15: Payment Received | E15: =IF(C15="Monthly Rent Charge",$D$3,"") | F15: =IF(C15="Monthly Rent Charge",$F$3,"") | G15: 6200 | H15: UA9A638STU | I15: =IF(A15="","",IF(C15="Payment Received",I14-IFERROR(G15,0),IF(C15="Monthly Rent Charge",I14+IFERROR(E15,0)+IFERROR(F15,0),I14)))
A16: =IF(B16="","",DATE(YEAR(TODAY()),MATCH(B16,{"January","February","March","April","May","June","July","August","September","October","November","December"},0),1)) | B16: February | C16: =IF(B16="","","Monthly Rent Charge") | E16: =IF(C16="Monthly Rent Charge",$D$3,"") | F16: =IF(C16="Monthly Rent Charge",$F$3,"") | I16: =IF(A16="","",IF(C16="Payment Received",I15-IFERROR(G16,0),IF(C16="Monthly Rent Charge",I15+IFERROR(E16,0)+IFERROR(F16,0),I15)))
A17: 46061 | C17: Payment Received | E17: =IF(C17="Monthly Rent Charge",$D$3,"") | F17: =IF(C17="Monthly Rent Charge",$F$3,"") | G17: 6200 | H17: UB8A661JMU | I17: =IF(A17="","",IF(C17="Payment Received",I16-IFERROR(G17,0),IF(C17="Monthly Rent Charge",I16+IFERROR(E17,0)+IFERROR(F17,0),I16)))
A18: =IF(B18="","",DATE(YEAR(TODAY()),MATCH(B18,{"January","February","March","April","May","June","July","August","September","October","November","December"},0),1)) | B18: March | C18: =IF(B18="","","Monthly Rent Charge") | E18: =IF(C18="Monthly Rent Charge",$D$3,"") | F18: =IF(C18="Monthly Rent Charge",$F$3,"") | I18: =IF(A18="","",IF(C18="Payment Received",I17-IFERROR(G18,0),IF(C18="Monthly Rent Charge",I17+IFERROR(E18,0)+IFERROR(F18,0),I17)))
A19: 46091 | C19: Payment Received | E19: =IF(C19="Monthly Rent Charge",$D$3,"") | F19: =IF(C19="Monthly Rent Charge",$F$3,"") | G19: 6200 | H19: UCADZ8VRNX | I19: =IF(A19="","",IF(C19="Payment Received",I18-IFERROR(G19,0),IF(C19="Monthly Rent Charge",I18+IFERROR(E19,0)+IFERROR(F19,0),I18)))
A20: =IF(B20="","",DATE(YEAR(TODAY()),MATCH(B20,{"January","February","March","April","May","June","July","August","September","October","November","December"},0),1)) | B20: April | C20: =IF(B20="","","Monthly Rent Charge") | E20: =IF(C20="Monthly Rent Charge",$D$3,"") | F20: =IF(C20="Monthly Rent Charge",$F$3,"") | I20: =IF(A20="","",IF(C20="Payment Received",I19-IFERROR(G20,0),IF(C20="Monthly Rent Charge",I19+IFERROR(E20,0)+IFERROR(F20,0),I19)))
A21: 46121 | C21: Payment Received | E21: =IF(C21="Monthly Rent Charge",$D$3,"") | F21: =IF(C21="Monthly Rent Charge",$F$3,"") | G21: 6200 | H21: UD9DZ085WS | I21: =IF(A21="","",IF(C21="Payment Received",I20-IFERROR(G21,0),IF(C21="Monthly Rent Charge",I20+IFERROR(E21,0)+IFERROR(F21,0),I20)))
A22: =IF(B22="","",DATE(YEAR(TODAY()),MATCH(B22,{"January","February","March","April","May","June","July","August","September","October","November","December"},0),1)) | B22: May | C22: =IF(B22="","","Monthly Rent Charge") | E22: =IF(C22="Monthly Rent Charge",$D$3,"") | F22: =IF(C22="Monthly Rent Charge",$F$3,"") | I22: =IF(AND(A22="",C22=""),"",IF(C22="Payment Received",I21-IFERROR(G22,0),IF(C22="Monthly Rent Charge",I21+IFERROR(E22,0)+IFERROR(F22,0),I21)))
A23: 46150 | C23: Payment Received | E23: =IF(C23="Monthly Rent Charge",$D$3,"") | F23: =IF(C23="Monthly Rent Charge",$F$3,"") | G23: 6200 | H23: UE8DZ3MMZ0 | I23: =IF(AND(A23="",C23=""),"",IF(C23="Payment Received",I22-IFERROR(G23,0),IF(C23="Monthly Rent Charge",I22+IFERROR(E23,0)+IFERROR(F23,0),I22)))
A24: =IF(B24="","",DATE(YEAR(TODAY()),MATCH(B24,{"January","February","March","April","May","June","July","August","September","October","November","December"},0),1)) | B24: June | C24: =IF(B24="","","Monthly Rent Charge") | E24: =IF(C24="Monthly Rent Charge",$D$3,"") | F24: =IF(C24="Monthly Rent Charge",$F$3,"") | I24: =IF(AND(A24="",C24=""),"",IF(C24="Payment Received",I23-IFERROR(G24,0),IF(C24="Monthly Rent Charge",I23+IFERROR(E24,0)+IFERROR(F24,0),I23)))
